Workbook

Sheet Read me
A1: Gratifi: every use case
A2: Everything a bank's customer can ask Gratifi to do, across every product, service and piece of content R360 and Gratifi provide. One row is one thing a customer wants done in one situation: what they say, what Gratifi does, which UI kit blocks it uses, what the systems decide, and what changes by market.
A4: What is covered
A5: 19 categories and 105 products and services (sheet "Coverage"), built from: the Commerce in chat doc (18 categories and the R360 project list: Open Rewards, TripSure, PHANTOM, Airport VIP, iRewards 2.0, Piingle, new-age rewards, ZERO, Gratifi, R360 core), CACHE, and the Gratifi app sitemap (12 bank areas and every sub-area).
A6: Nothing counts as covered until "Coverage" shows zero gaps. An item is covered when it has at least 6 use cases, at least 2 where nothing goes wrong and at least 2 where something does. Add a product to "Coverage" and it shows as a gap until its use cases exist.
A8: How a row is built
A9: Stage × Job × Constraint × Exception. Stages: Discover, Search, Choose, Pay, Add-ons, Before, During, Problem, After, Account. "Customer says" is one example phrasing; the agent is trained on many per row. "Rules" are decided by systems, never by the model.
A10: "UI blocks" names components in the Gratifi UI kit. "NEW: Name" means the kit does not have that block yet; sheet "Kit gaps" lists every one and how often it is needed.
A12: Scoring (1 low to 5 high) and build waves
A13: Volume: how often customers ask. Value: revenue or loyalty impact. Risk: harm if wrong (money, rights, safety, regulation). Priority = Volume × Value ÷ Risk. Edit the blue cells to change the waves.
A14: Wave 1 needs priority of at least | B14: 6
A15: Wave 1 needs risk no higher than | B15: 2
A16: Risk of at least this goes to wave 3 (legal and human sign-off first) | B16: 4
A17: Core path (Y) rows are wave 1 even at high risk, because a customer cannot complete a booking without them; legal still signs off the high-risk ones before launch.
A19: Status and cautions
A20: • Scores are a first pass for discussion. Re-score with real volumes from partner banks and PHANTOM and TripSure history.
A21: • Compensation and consumer-law amounts are given only where set by law and known (UK261, EU261, UK Section 75). Anything else is named and marked "to confirm" for each bank's legal team. Market notes are prompts to check, not legal advice.
A22: • Investments (C13) and insurance selling need licences per market; those rows are information-only until legal signs off.
A23: • Arabic copy in the kit is a layout draft for native review. Suppliers, airlines and hotels in examples are fictional unless the inventory names the supply.
A24: • To add a use case: add a row at the bottom of "Use cases", fill the item ID and scores; copy Priority and Wave down.

Sheet Summary
A1: Summary
A3: Items with a coverage gap | B3: =COUNTIF(Coverage!$N$2:$N$156,"GAP") -> 0
A4: Use cases | B4: =COUNTA('Use cases'!$C$2:$C$6000) -> 2315
A5: Products and services | B5: =COUNTIF(Coverage!$N$2:$N$156,"Covered")+COUNTIF(Coverage!$N$2:$N$156,"GAP") -> 105
A6: Kit blocks still to build | B6: =COUNTA('Kit gaps'!$A$2:$A$500) -> 106
A8: Category | B8: Products | C8: Use cases | D8: Wave 1 | E8: Wave 2 | F8: Wave 3 | G8: Gaps | H8: Average priority
A9: Flights | B9: =COUNTIF(Coverage!$B$2:$B$156,A9) -> 8 | C9: =COUNTIF('Use cases'!$B$2:$B$6000,A9) -> 146 | D9: =COUNTIFS('Use cases'!$B$2:$B$6000,$A9,'Use cases'!$S$2:$S$6000,1) -> 61 | E9: =COUNTIFS('Use cases'!$B$2:$B$6000,$A9,'Use cases'!$S$2:$S$6000,2) -> 56 | F9: =COUNTIFS('Use cases'!$B$2:$B$6000,$A9,'Use cases'!$S$2:$S$6000,3) -> 29 | G9: =COUNTIFS(Coverage!$B$2:$B$156,A9,Coverage!$N$2:$N$156,"GAP") -> 0 | H9: =IFERROR(ROUND(AVERAGEIF('Use cases'!$B$2:$B$6000,A9,'Use cases'!$R$2:$R$6000),1),0) -> 5.4
A10: Stays | B10: =COUNTIF(Coverage!$B$2:$B$156,A10) -> 6 | C10: =COUNTIF('Use cases'!$B$2:$B$6000,A10) -> 119 | D10: =COUNTIFS('Use cases'!$B$2:$B$6000,$A10,'Use cases'!$S$2:$S$6000,1) -> 31 | E10: =COUNTIFS('Use cases'!$B$2:$B$6000,$A10,'Use cases'!$S$2:$S$6000,2) -> 57 | F10: =COUNTIFS('Use cases'!$B$2:$B$6000,$A10,'Use cases'!$S$2:$S$6000,3) -> 31 | G10: =COUNTIFS(Coverage!$B$2:$B$156,A10,Coverage!$N$2:$N$156,"GAP") -> 0 | H10: =IFERROR(ROUND(AVERAGEIF('Use cases'!$B$2:$B$6000,A10,'Use cases'!$R$2:$R$6000),1),0) -> 4.4
A11: Airport and travel privileges | B11: =COUNTIF(Coverage!$B$2:$B$156,A11) -> 6 | C11: =COUNTIF('Use cases'!$B$2:$B$6000,A11) -> 110 | D11: =COUNTIFS('Use cases'!$B$2:$B$6000,$A11,'Use cases'!$S$2:$S$6000,1) -> 22 | E11: =COUNTIFS('Use cases'!$B$2:$B$6000,$A11,'Use cases'!$S$2:$S$6000,2) -> 71 | F11: =COUNTIFS('Use cases'!$B$2:$B$6000,$A11,'Use cases'!$S$2:$S$6000,3) -> 17 | G11: =COUNTIFS(Coverage!$B$2:$B$156,A11,Coverage!$N$2:$N$156,"GAP") -> 0 | H11: =IFERROR(ROUND(AVERAGEIF('Use cases'!$B$2:$B$6000,A11,'Use cases'!$R$2:$R$6000),1),0) -> 3.6
A12: Ground transport | B12: =COUNTIF(Coverage!$B$2:$B$156,A12) -> 5 | C12: =COUNTIF('Use cases'!$B$2:$B$6000,A12) -> 94 | D12: =COUNTIFS('Use cases'!$B$2:$B$6000,$A12,'Use cases'!$S$2:$S$6000,1) -> 17 | E12: =COUNTIFS('Use cases'!$B$2:$B$6000,$A12,'Use cases'!$S$2:$S$6000,2) -> 64 | F12: =COUNTIFS('Use cases'!$B$2:$B$6000,$A12,'Use cases'!$S$2:$S$6000,3) -> 13 | G12: =COUNTIFS(Coverage!$B$2:$B$156,A12,Coverage!$N$2:$N$156,"GAP") -> 0 | H12: =IFERROR(ROUND(AVERAGEIF('Use cases'!$B$2:$B$6000,A12,'Use cases'!$R$2:$R$6000),1),0) -> 3.4
A13: Experiences | B13: =COUNTIF(Coverage!$B$2:$B$156,A13) -> 5 | C13: =COUNTIF('Use cases'!$B$2:$B$6000,A13) -> 153 | D13: =COUNTIFS('Use cases'!$B$2:$B$6000,$A13,'Use cases'!$S$2:$S$6000,1) -> 39 | E13: =COUNTIFS('Use cases'!$B$2:$B$6000,$A13,'Use cases'!$S$2:$S$6000,2) -> 83 | F13: =COUNTIFS('Use cases'!$B$2:$B$6000,$A13,'Use cases'!$S$2:$S$6000,3) -> 31 | G13: =COUNTIFS(Coverage!$B$2:$B$156,A13,Coverage!$N$2:$N$156,"GAP") -> 0 | H13: =IFERROR(ROUND(AVERAGEIF('Use cases'!$B$2:$B$6000,A13,'Use cases'!$R$2:$R$6000),1),0) -> 4.2
A14: Dining | B14: =COUNTIF(Coverage!$B$2:$B$156,A14) -> 4 | C14: =COUNTIF('Use cases'!$B$2:$B$6000,A14) -> 102 | D14: =COUNTIFS('Use cases'!$B$2:$B$6000,$A14,'Use cases'!$S$2:$S$6000,1) -> 37 | E14: =COUNTIFS('Use cases'!$B$2:$B$6000,$A14,'Use cases'!$S$2:$S$6000,2) -> 61 | F14: =COUNTIFS('Use cases'!$B$2:$B$6000,$A14,'Use cases'!$S$2:$S$6000,3) -> 4 | G14: =COUNTIFS(Coverage!$B$2:$B$156,A14,Coverage!$N$2:$N$156,"GAP") -> 0 | H14: =IFERROR(ROUND(AVERAGEIF('Use cases'!$B$2:$B$6000,A14,'Use cases'!$R$2:$R$6000),1),0) -> 5
A15: Quick commerce and grocery | B15: =COUNTIF(Coverage!$B$2:$B$156,A15) -> 3 | C15: =COUNTIF('Use cases'!$B$2:$B$6000,A15) -> 103 | D15: =COUNTIFS('Use cases'!$B$2:$B$6000,$A15,'Use cases'!$S$2:$S$6000,1) -> 27 | E15: =COUNTIFS('Use cases'!$B$2:$B$6000,$A15,'Use cases'!$S$2:$S$6000,2) -> 62 | F15: =COUNTIFS('Use cases'!$B$2:$B$6000,$A15,'Use cases'!$S$2:$S$6000,3) -> 14 | G15: =COUNTIFS(Coverage!$B$2:$B$156,A15,Coverage!$N$2:$N$156,"GAP") -> 0 | H15: =IFERROR(ROUND(AVERAGEIF('Use cases'!$B$2:$B$6000,A15,'Use cases'!$R$2:$R$6000),1),0) -> 4.6
A16: Shopping | B16: =COUNTIF(Coverage!$B$2:$B$156,A16) -> 7 | C16: =COUNTIF('Use cases'!$B$2:$B$6000,A16) -> 204 | D16: =COUNTIFS('Use cases'!$B$2:$B$6000,$A16,'Use cases'!$S$2:$S$6000,1) -> 65 | E16: =COUNTIFS('Use cases'!$B$2:$B$6000,$A16,'Use cases'!$S$2:$S$6000,2) -> 109 | F16: =COUNTIFS('Use cases'!$B$2:$B$6000,$A16,'Use cases'!$S$2:$S$6000,3) -> 30 | G16: =COUNTIFS(Coverage!$B$2:$B$156,A16,Coverage!$N$2:$N$156,"GAP") -> 0 | H16: =IFERROR(ROUND(AVERAGEIF('Use cases'!$B$2:$B$6000,A16,'Use cases'!$R$2:$R$6000),1),0) -> 4.9
A17: Gift cards | B17: =COUNTIF(Coverage!$B$2:$B$156,A17) -> 5 | C17: =COUNTIF('Use cases'!$B$2:$B$6000,A17) -> 88 | D17: =COUNTIFS('Use cases'!$B$2:$B$6000,$A17,'Use cases'!$S$2:$S$6000,1) -> 21 | E17: =COUNTIFS('Use cases'!$B$2:$B$6000,$A17,'Use cases'!$S$2:$S$6000,2) -> 47 | F17: =COUNTIFS('Use cases'!$B$2:$B$6000,$A17,'Use cases'!$S$2:$S$6000,3) -> 20 | G17: =COUNTIFS(Coverage!$B$2:$B$156,A17,Coverage!$N$2:$N$156,"GAP") -> 0 | H17: =IFERROR(ROUND(AVERAGEIF('Use cases'!$B$2:$B$6000,A17,'Use cases'!$R$2:$R$6000),1),0) -> 3.7
A18: Subscriptions and digital | B18: =COUNTIF(Coverage!$B$2:$B$156,A18) -> 6 | C18: =COUNTIF('Use cases'!$B$2:$B$6000,A18) -> 88 | D18: =COUNTIFS('Use cases'!$B$2:$B$6000,$A18,'Use cases'!$S$2:$S$6000,1) -> 18 | E18: =COUNTIFS('Use cases'!$B$2:$B$6000,$A18,'Use cases'!$S$2:$S$6000,2) -> 65 | F18: =COUNTIFS('Use cases'!$B$2:$B$6000,$A18,'Use cases'!$S$2:$S$6000,3) -> 5 | G18: =COUNTIFS(Coverage!$B$2:$B$156,A18,Coverage!$N$2:$N$156,"GAP") -> 0 | H18: =IFERROR(ROUND(AVERAGEIF('Use cases'!$B$2:$B$6000,A18,'Use cases'!$R$2:$R$6000),1),0) -> 3.6
A19: Entertainment tickets | B19: =COUNTIF(Coverage!$B$2:$B$156,A19) -> 5 | C19: =COUNTIF('Use cases'!$B$2:$B$6000,A19) -> 115 | D19: =COUNTIFS('Use cases'!$B$2:$B$6000,$A19,'Use cases'!$S$2:$S$6000,1) -> 34 | E19: =COUNTIFS('Use cases'!$B$2:$B$6000,$A19,'Use cases'!$S$2:$S$6000,2) -> 74 | F19: =COUNTIFS('Use cases'!$B$2:$B$6000,$A19,'Use cases'!$S$2:$S$6000,3) -> 7 | G19: =COUNTIFS(Coverage!$B$2:$B$156,A19,Coverage!$N$2:$N$156,"GAP") -> 0 | H19: =IFERROR(ROUND(AVERAGEIF('Use cases'!$B$2:$B$6000,A19,'Use cases'!$R$2:$R$6000),1),0) -> 4.6
A20: Points and miles | B20: =COUNTIF(Coverage!$B$2:$B$156,A20) -> 7 | C20: =COUNTIF('Use cases'!$B$2:$B$6000,A20) -> 106 | D20: =COUNTIFS('Use cases'!$B$2:$B$6000,$A20,'Use cases'!$S$2:$S$6000,1) -> 29 | E20: =COUNTIFS('Use cases'!$B$2:$B$6000,$A20,'Use cases'!$S$2:$S$6000,2) -> 57 | F20: =COUNTIFS('Use cases'!$B$2:$B$6000,$A20,'Use cases'!$S$2:$S$6000,3) -> 20 | G20: =COUNTIFS(Coverage!$B$2:$B$156,A20,Coverage!$N$2:$N$156,"GAP") -> 0 | H20: =IFERROR(ROUND(AVERAGEIF('Use cases'!$B$2:$B$6000,A20,'Use cases'!$R$2:$R$6000),1),0) -> 4.1
... A27: Engagement and moments | B27: =COUNTIF(Coverage!$B$2:$B$156,A27) -> 6 | C27: =COUNTIF('Use cases'!$B$2:$B$6000,A27) -> 131 | D27: =COUNTIFS('Use cases'!$B$2:$B$6000,$A27,'Use cases'!$S$2:$S$6000,1) -> 30 | E27: =COUNTIFS('Use cases'!$B$2:$B$6000,$A27,'Use cases'!$S$2:$S$6000,2) -> 84 | F27: =COUNTIFS('Use cases'!$B$2:$B$6000,$A27,'Use cases'!$S$2:$S$6000,3) -> 17 | G27: =COUNTIFS(Coverage!$B$2:$B$156,A27,Coverage!$N$2:$N$156,"GAP") -> 0 | H27: =IFERROR(ROUND(AVERAGEIF('Use cases'!$B$2:$B$6000,A27,'Use cases'!$R$2:$R$6000),1),0) -> 3.4
A28: Total | B28: =SUM(B9:B27) -> 105 | C28: =SUM(C9:C27) -> 2315 | D28: =SUM(D9:D27) -> 512 | E28: =SUM(E9:E27) -> 1285 | F28: =SUM(F9:F27) -> 518 | G28: =SUM(G9:G27) -> 0 | H28: =ROUND(AVERAGE('Use cases'!$R$2:$R$6000),1) -> 3.8
A30: Wave 1 is what the agent handles end to end first. Wave 3 needs legal sign-off and a person in the loop before launch.

Sheet Coverage
A1: Item ID | B1: Category | C1: Item | D1: What it covers | E1: Supply | F1: Status as last recorded | G1: Use cases | H1: Nothing wrong | I1: Something wrong | J1: Pay rows | K1: Handovers | L1: Proactive | M1: New blocks needed | N1: Coverage
A2: FL-01 | B2: Flights | C2: One-way and return flights | D2: Search, compare, book | E2: TripSure, PHANTOM (TBO, TripJack, MistyFly), Kiwi.com and Expedia MCPs | F2: In build | G2: =COUNTIF('Use cases'!$C$2:$C$6000,A2) -> 34 | H2: =COUNTIFS('Use cases'!$C$2:$C$6000,A2,'Use cases'!$H$2:$H$6000,"") -> 30 | I2: =G2-H2 -> 4 | J2: =COUNTIFS('Use cases'!$C$2:$C$6000,A2,'Use cases'!$E$2:$E$6000,"Pay") -> 0 | K2: =COUNTIFS('Use cases'!$C$2:$C$6000,A2,'Use cases'!$K$2:$K$6000,"*Handoff*") -> 1 | L2: =COUNTIFS('Use cases'!$C$2:$C$6000,A2,'Use cases'!$I$2:$I$6000,"(Gratifi starts it)*") -> 1 | M2: =COUNTIFS('Use cases'!$C$2:$C$6000,A2,'Use cases'!$K$2:$K$6000,"*NEW:*") -> 0 | N2: =IF(AND(G2>=6,H2>=2,I2>=2),"Covered","GAP") -> Covered
A3: FL-02 | B3: Flights | C3: Multi-city, open jaw, groups | D3: Complex itineraries | E3: Same as FL-01 | F3: In build | G3: =COUNTIF('Use cases'!$C$2:$C$6000,A3) -> 10 | H3: =COUNTIFS('Use cases'!$C$2:$C$6000,A3,'Use cases'!$H$2:$H$6000,"") -> 7 | I3: =G3-H3 -> 3 | J3: =COUNTIFS('Use cases'!$C$2:$C$6000,A3,'Use cases'!$E$2:$E$6000,"Pay") -> 2 | K3: =COUNTIFS('Use cases'!$C$2:$C$6000,A3,'Use cases'!$K$2:$K$6000,"*Handoff*") -> 3 | L3: =COUNTIFS('Use cases'!$C$2:$C$6000,A3,'Use cases'!$I$2:$I$6000,"(Gratifi starts it)*") -> 0 | M3: =COUNTIFS('Use cases'!$C$2:$C$6000,A3,'Use cases'!$K$2:$K$6000,"*NEW:*") -> 0 | N3: =IF(AND(G3>=6,H3>=2,I3>=2),"Covered","GAP") -> Covered
A4: FL-03 | B4: Flights | C4: Award seats and upgrades | D4: Points for seats and cabins | E4: Bank programmes, airline partners | F4: To source | G4: =COUNTIF('Use cases'!$C$2:$C$6000,A4) -> 9 | H4: =COUNTIFS('Use cases'!$C$2:$C$6000,A4,'Use cases'!$H$2:$H$6000,"") -> 7 | I4: =G4-H4 -> 2 | J4: =COUNTIFS('Use cases'!$C$2:$C$6000,A4,'Use cases'!$E$2:$E$6000,"Pay") -> 1 | K4: =COUNTIFS('Use cases'!$C$2:$C$6000,A4,'Use cases'!$K$2:$K$6000,"*Handoff*") -> 1 | L4: =COUNTIFS('Use cases'!$C$2:$C$6000,A4,'Use cases'!$I$2:$I$6000,"(Gratifi starts it)*") -> 1 | M4: =COUNTIFS('Use cases'!$C$2:$C$6000,A4,'Use cases'!$K$2:$K$6000,"*NEW:*") -> 0 | N4: =IF(AND(G4>=6,H4>=2,I4>=2),"Covered","GAP") -> Covered
A5: FL-04 | B5: Flights | C5: Seats, bags, meals, assistance | D5: Ancillaries | E5: Supplier APIs | F5: In build | G5: =COUNTIF('Use cases'!$C$2:$C$6000,A5) -> 18 | H5: =COUNTIFS('Use cases'!$C$2:$C$6000,A5,'Use cases'!$H$2:$H$6000,"") -> 14 | I5: =G5-H5 -> 4 | J5: =COUNTIFS('Use cases'!$C$2:$C$6000,A5,'Use cases'!$E$2:$E$6000,"Pay") -> 0 | K5: =COUNTIFS('Use cases'!$C$2:$C$6000,A5,'Use cases'!$K$2:$K$6000,"*Handoff*") -> 3 | L5: =COUNTIFS('Use cases'!$C$2:$C$6000,A5,'Use cases'!$I$2:$I$6000,"(Gratifi starts it)*") -> 0 | M5: =COUNTIFS('Use cases'!$C$2:$C$6000,A5,'Use cases'!$K$2:$K$6000,"*NEW:*") -> 0 | N5: =IF(AND(G5>=6,H5>=2,I5>=2),"Covered","GAP") -> Covered
A6: FL-05 | B6: Flights | C6: Changes and cancellations | D6: Manage booking | E6: Supplier APIs, fare rules | F6: In build | G6: =COUNTIF('Use cases'!$C$2:$C$6000,A6) -> 11 | H6: =COUNTIFS('Use cases'!$C$2:$C$6000,A6,'Use cases'!$H$2:$H$6000,"") -> 8 | I6: =G6-H6 -> 3 | J6: =COUNTIFS('Use cases'!$C$2:$C$6000,A6,'Use cases'!$E$2:$E$6000,"Pay") -> 0 | K6: =COUNTIFS('Use cases'!$C$2:$C$6000,A6,'Use cases'!$K$2:$K$6000,"*Handoff*") -> 1 | L6: =COUNTIFS('Use cases'!$C$2:$C$6000,A6,'Use cases'!$I$2:$I$6000,"(Gratifi starts it)*") -> 0 | M6: =COUNTIFS('Use cases'!$C$2:$C$6000,A6,'Use cases'!$K$2:$K$6000,"*NEW:*") -> 0 | N6: =IF(AND(G6>=6,H6>=2,I6>=2),"Covered","GAP") -> Covered
A7: FL-06 | B7: Flights | C7: Check-in and day of travel | D7: Boarding pass, status, gate | E7: Airline feeds | F7: In build | G7: =COUNTIF('Use cases'!$C$2:$C$6000,A7) -> 23 | H7: =COUNTIFS('Use cases'!$C$2:$C$6000,A7,'Use cases'!$H$2:$H$6000,"") -> 19 | I7: =G7-H7 -> 4 | J7: =COUNTIFS('Use cases'!$C$2:$C$6000,A7,'Use cases'!$E$2:$E$6000,"Pay") -> 0 | K7: =COUNTIFS('Use cases'!$C$2:$C$6000,A7,'Use cases'!$K$2:$K$6000,"*Handoff*") -> 3 | L7: =COUNTIFS('Use cases'!$C$2:$C$6000,A7,'Use cases'!$I$2:$I$6000,"(Gratifi starts it)*") -> 2 | M7: =COUNTIFS('Use cases'!$C$2:$C$6000,A7,'Use cases'!$K$2:$K$6000,"*NEW:*") -> 0 | N7: =IF(AND(G7>=6,H7>=2,I7>=2),"Covered","GAP") -> Covered
A8: FL-07 | B8: Flights | C8: Disruption and compensation | D8: Delays, cancellations, claims | E8: Airline feeds, local rules | F8: In build | G8: =COUNTIF('Use cases'!$C$2:$C$6000,A8) -> 15 | H8: =COUNTIFS('Use cases'!$C$2:$C$6000,A8,'Use cases'!$H$2:$H$6000,"") -> 4 | I8: =G8-H8 -> 11 | J8: =COUNTIFS('Use cases'!$C$2:$C$6000,A8,'Use cases'!$E$2:$E$6000,"Pay") -> 0 | K8: =COUNTIFS('Use cases'!$C$2:$C$6000,A8,'Use cases'!$K$2:$K$6000,"*Handoff*") -> 7 | L8: =COUNTIFS('Use cases'!$C$2:$C$6000,A8,'Use cases'!$I$2:$I$6000,"(Gratifi starts it)*") -> 9 | M8: =COUNTIFS('Use cases'!$C$2:$C$6000,A8,'Use cases'!$K$2:$K$6000,"*NEW:*") -> 0 | N8: =IF(AND(G8>=6,H8>=2,I8>=2),"Covered","GAP") -> Covered
A9: FL-08 | B9: Flights | C9: Payment, refunds and invoices | D9: Points, card, refunds, tax invoices | E9: R360 core, bank | F9: In build | G9: =COUNTIF('Use cases'!$C$2:$C$6000,A9) -> 26 | H9: =COUNTIFS('Use cases'!$C$2:$C$6000,A9,'Use cases'!$H$2:$H$6000,"") -> 21 | I9: =G9-H9 -> 5 | J9: =COUNTIFS('Use cases'!$C$2:$C$6000,A9,'Use cases'!$E$2:$E$6000,"Pay") -> 15 | K9: =COUNTIFS('Use cases'!$C$2:$C$6000,A9,'Use cases'!$K$2:$K$6000,"*Handoff*") -> 3 | L9: =COUNTIFS('Use cases'!$C$2:$C$6000,A9,'Use cases'!$I$2:$I$6000,"(Gratifi starts it)*") -> 1 | M9: =COUNTIFS('Use cases'!$C$2:$C$6000,A9,'Use cases'!$K$2:$K$6000,"*NEW:*") -> 0 | N9: =IF(AND(G9>=6,H9>=2,I9>=2),"Covered","GAP") -> Covered
A10: ST-01 | B10: Stays | C10: Hotels | D10: Search, compare, book rooms | E10: TripSure 2.5M+ hotels, HotelBeds, WebBeds, Expedia MCP | F10: Hotels-first launch | G10: =COUNTIF('Use cases'!$C$2:$C$6000,A10) -> 36 | H10: =COUNTIFS('Use cases'!$C$2:$C$6000,A10,'Use cases'!$H$2:$H$6000,"") -> 29 | I10: =G10-H10 -> 7 | J10: =COUNTIFS('Use cases'!$C$2:$C$6000,A10,'Use cases'!$E$2:$E$6000,"Pay") -> 8 | K10: =COUNTIFS('Use cases'!$C$2:$C$6000,A10,'Use cases'!$K$2:$K$6000,"*Handoff*") -> 3 | L10: =COUNTIFS('Use cases'!$C$2:$C$6000,A10,'Use cases'!$I$2:$I$6000,"(Gratifi starts it)*") -> 2 | M10: =COUNTIFS('Use cases'!$C$2:$C$6000,A10,'Use cases'!$K$2:$K$6000,"*NEW:*") -> 4 | N10: =IF(AND(G10>=6,H10>=2,I10>=2),"Covered","GAP") -> Covered
A11: ST-02 | B11: Stays | C11: Apartments and villas | D11: Longer and group stays | E11: Suppliers to confirm | F11: To source | G11: =COUNTIF('Use cases'!$C$2:$C$6000,A11) -> 17 | H11: =COUNTIFS('Use cases'!$C$2:$C$6000,A11,'Use cases'!$H$2:$H$6000,"") -> 11 | I11: =G11-H11 -> 6 | J11: =COUNTIFS('Use cases'!$C$2:$C$6000,A11,'Use cases'!$E$2:$E$6000,"Pay") -> 3 | K11: =COUNTIFS('Use cases'!$C$2:$C$6000,A11,'Use cases'!$K$2:$K$6000,"*Handoff*") -> 6 | L11: =COUNTIFS('Use cases'!$C$2:$C$6000,A11,'Use cases'!$I$2:$I$6000,"(Gratifi starts it)*") -> 2 | M11: =COUNTIFS('Use cases'!$C$2:$C$6000,A11,'Use cases'!$K$2:$K$6000,"*NEW:*") -> 5 | N11: =IF(AND(G11>=6,H11>=2,I11>=2),"Covered","GAP") -> Covered
A12: ST-03 | B12: Stays | C12: Resorts and packages | D12: Stay plus flights or extras | E12: TripSure, partners | F12: To source | G12: =COUNTIF('Use cases'!$C$2:$C$6000,A12) -> 15 | H12: =COUNTIFS('Use cases'!$C$2:$C$6000,A12,'Use cases'!$H$2:$H$6000,"") -> 12 | I12: =G12-H12 -> 3 | J12: =COUNTIFS('Use cases'!$C$2:$C$6000,A12,'Use cases'!$E$2:$E$6000,"Pay") -> 3 | K12: =COUNTIFS('Use cases'!$C$2:$C$6000,A12,'Use cases'!$K$2:$K$6000,"*Handoff*") -> 4 | L12: =COUNTIFS('Use cases'!$C$2:$C$6000,A12,'Use cases'!$I$2:$I$6000,"(Gratifi starts it)*") -> 2 | M12: =COUNTIFS('Use cases'!$C$2:$C$6000,A12,'Use cases'!$K$2:$K$6000,"*NEW:*") -> 2 | N12: =IF(AND(G12>=6,H12>=2,I12>=2),"Covered","GAP") -> Covered
A13: ST-04 | B13: Stays | C13: Changes and cancellations | D13: Dates, rooms, guests, refunds | E13: Supplier rules | F13: In build | G13: =COUNTIF('Use cases'!$C$2:$C$6000,A13) -> 18 | H13: =COUNTIFS('Use cases'!$C$2:$C$6000,A13,'Use cases'!$H$2:$H$6000,"") -> 10 | I13: =G13-H13 -> 8 | J13: =COUNTIFS('Use cases'!$C$2:$C$6000,A13,'Use cases'!$E$2:$E$6000,"Pay") -> 1 | K13: =COUNTIFS('Use cases'!$C$2:$C$6000,A13,'Use cases'!$K$2:$K$6000,"*Handoff*") -> 8 | L13: =COUNTIFS('Use cases'!$C$2:$C$6000,A13,'Use cases'!$I$2:$I$6000,"(Gratifi starts it)*") -> 2 | M13: =COUNTIFS('Use cases'!$C$2:$C$6000,A13,'Use cases'!$K$2:$K$6000,"*NEW:*") -> 0 | N13: =IF(AND(G13>=6,H13>=2,I13>=2),"Covered","GAP") -> Covered
... A106: EN-06 | B106: Engagement and moments | C106: Feedback and preferences | D106: Ratings, likes, what not to show | E106: Gratifi | F106: To build | G106: =COUNTIF('Use cases'!$C$2:$C$6000,A106) -> 22 | H106: =COUNTIFS('Use cases'!$C$2:$C$6000,A106,'Use cases'!$H$2:$H$6000,"") -> 18 | I106: =G106-H106 -> 4 | J106: =COUNTIFS('Use cases'!$C$2:$C$6000,A106,'Use cases'!$E$2:$E$6000,"Pay") -> 0 | K106: =COUNTIFS('Use cases'!$C$2:$C$6000,A106,'Use cases'!$K$2:$K$6000,"*Handoff*") -> 4 | L106: =COUNTIFS('Use cases'!$C$2:$C$6000,A106,'Use cases'!$I$2:$I$6000,"(Gratifi starts it)*") -> 1 | M106: =COUNTIFS('Use cases'!$C$2:$C$6000,A106,'Use cases'!$K$2:$K$6000,"*NEW:*") -> 4 | N106: =IF(AND(G106>=6,H106>=2,I106>=2),"Covered","GAP") -> Covered
A108: To add a product or service: add a row above this line with a new Item ID and copy the formulas in G to N. It shows GAP until its use cases exist.

Sheet Use cases
A1: ID | B1: Category | C1: Item ID | D1: Item | E1: Stage | F1: Job | G1: Constraint | H1: Exception | I1: Customer says | J1: Gratifi does | K1: UI blocks (kit) | L1: Rules: systems decide | M1: Market notes | N1: Volume | O1: Value | P1: Risk | Q1: Core path | R1: Priority | S1: Wave
A2: FL-01-001 | B2: Flights | C2: FL-01 | D2: One-way and return flights | E2: Discover | F2: Find somewhere to go | G2: Budget | I2: Somewhere warm in October for under 40,000 points | J2: Suggests 3 places the points cover, with flight price and weather | K2: Answer, Rail, Polaroid, Price | L2: Only places with live fares under the budget | N2: 4 | O2: 3 | P2: 1 | R2: =IF(OR(N2="",P2=""),"",ROUND(N2*O2/P2,1)) -> 12 | S2: =IF(R2="","",IF(Q2="Y",1,IF(P2>='Read me'!$B$16,3,IF(AND(R2>='Read me'!$B$14,P2<='Read me'!$B$15),1,2)))) -> 1
A3: FL-01-002 | B3: Flights | C3: FL-01 | D3: One-way and return flights | E3: Discover | F3: Find somewhere to go | G3: Dates fixed | I3: Where can I go for the long weekend? | J3: Finds direct flights for those dates, shortest first | K3: Answer, Rail, FlightCard | L3: Uses the bank holiday calendar for the market | M3: Holiday calendars differ: bank holidays (UK, EU), Diwali/Deepavali (IN, SG, MY), Eid/Hari Raya (AE, MY, SG, IN), Chinese New Year (SG, MY) | N3: 4 | O3: 3 | P3: 1 | R3: =IF(OR(N3="",P3=""),"",ROUND(N3*O3/P3,1)) -> 12 | S3: =IF(R3="","",IF(Q3="Y",1,IF(P3>='Read me'!$B$16,3,IF(AND(R3>='Read me'!$B$14,P3<='Read me'!$B$15),1,2)))) -> 1
A4: FL-01-003 | B4: Flights | C4: FL-01 | D4: One-way and return flights | E4: Discover | F4: Find somewhere to go | G4: Points only | I4: What can I get with my points alone? | J4: Shows trips fully covered by the balance | K4: Answer, Dial, Rail | L4: Balance and point value from the bank | N4: 4 | O4: 4 | P4: 1 | R4: =IF(OR(N4="",P4=""),"",ROUND(N4*O4/P4,1)) -> 16 | S4: =IF(R4="","",IF(Q4="Y",1,IF(P4>='Read me'!$B$16,3,IF(AND(R4>='Read me'!$B$14,P4<='Read me'!$B$15),1,2)))) -> 1
A5: FL-01-004 | B5: Flights | C5: FL-01 | D5: One-way and return flights | E5: Discover | F5: Find somewhere to go | G5: Travelling with kids | I5: Somewhere easy with a toddler, short flight | J5: Filters to under 3 hours, direct, family-friendly stays | K5: Answer, Rail, Chips | L5: Flight time cap is a hard filter | N5: 3 | O5: 3 | P5: 1 | R5: =IF(OR(N5="",P5=""),"",ROUND(N5*O5/P5,1)) -> 9 | S5: =IF(R5="","",IF(Q5="Y",1,IF(P5>='Read me'!$B$16,3,IF(AND(R5>='Read me'!$B$14,P5<='Read me'!$B$15),1,2)))) -> 1
A6: FL-01-005 | B6: Flights | C6: FL-01 | D6: One-way and return flights | E6: Discover | F6: Get a price alert | G6: Route known | I6: Tell me if London to Lisbon drops under £150 | J6: Sets an alert and confirms the threshold | K6: Toast, Toggle | L6: Alert fires on supplier price, not an estimate | N6: 3 | O6: 2 | P6: 1 | R6: =IF(OR(N6="",P6=""),"",ROUND(N6*O6/P6,1)) -> 6 | S6: =IF(R6="","",IF(Q6="Y",1,IF(P6>='Read me'!$B$16,3,IF(AND(R6>='Read me'!$B$14,P6<='Read me'!$B$15),1,2)))) -> 1
A7: FL-01-006 | B7: Flights | C7: FL-01 | D7: One-way and return flights | E7: Discover | F7: Get told about a deal | G7: Card benefit | I7: (Gratifi starts it) | J7: Moment: a card offer on a route the customer flies often | K7: StickyNote, OfferCard | L7: Only offers the customer is eligible for; marketing consent checked | M7: Consent rules differ: UK GDPR/PECR, EU GDPR, India DPDP Act, Singapore PDPA, Malaysia PDPA, UAE PDPL | N7: 3 | O7: 4 | P7: 2 | R7: =IF(OR(N7="",P7=""),"",ROUND(N7*O7/P7,1)) -> 6 | S7: =IF(R7="","",IF(Q7="Y",1,IF(P7>='Read me'!$B$16,3,IF(AND(R7>='Read me'!$B$14,P7<='Read me'!$B$15),1,2)))) -> 1
A8: FL-01-007 | B8: Flights | C8: FL-01 | D8: One-way and return flights | E8: Discover | F8: Plan around an event | G8: Date fixed by event | I8: Flights for the F1 weekend | J8: Finds flights and warns about peak prices | K8: Answer, PriceCalendar, StateCard | L8: Event dates from content partner | N8: 2 | O8: 3 | P8: 1 | R8: =IF(OR(N8="",P8=""),"",ROUND(N8*O8/P8,1)) -> 6 | S8: =IF(R8="","",IF(Q8="Y",1,IF(P8>='Read me'!$B$16,3,IF(AND(R8>='Read me'!$B$14,P8<='Read me'!$B$15),1,2)))) -> 1
A9: FL-01-008 | B9: Flights | C9: FL-01 | D9: One-way and return flights | E9: Discover | F9: Compare two places | G9: Undecided | I9: Lisbon or Porto for 3 nights? | J9: Side-by-side of flight, hotel and total in points | K9: Compare | L9: Totals include taxes | N9: 2 | O9: 3 | P9: 1 | R9: =IF(OR(N9="",P9=""),"",ROUND(N9*O9/P9,1)) -> 6 | S9: =IF(R9="","",IF(Q9="Y",1,IF(P9>='Read me'!$B$16,3,IF(AND(R9>='Read me'!$B$14,P9<='Read me'!$B$15),1,2)))) -> 1
A10: FL-01-009 | B10: Flights | C10: FL-01 | D10: One-way and return flights | E10: Search | F10: Book a return flight | G10: Dates fixed | I10: Lisbon for two, 16 to 18 October | J10: Three best options with a recommendation and the reason | K10: YouSaid, Steps, Answer, Rail, FlightCard, Suggestions | L10: Supplier fares only; the recommendation reason must be a stated fact | N10: 5 | O10: 5 | P10: 2 | Q10: Y | R10: =IF(OR(N10="",P10=""),"",ROUND(N10*O10/P10,1)) -> 12.5 | S10: =IF(R10="","",IF(Q10="Y",1,IF(P10>='Read me'!$B$16,3,IF(AND(R10>='Read me'!$B$14,P10<='Read me'!$B$15),1,2)))) -> 1
A11: FL-01-010 | B11: Flights | C11: FL-01 | D11: One-way and return flights | E11: Search | F11: Book a return flight | G11: Flexible dates | I11: Cheapest week in October to Lisbon | J11: Price calendar with the cheapest days marked | K11: PriceCalendar | L11: Calendar prices are cached; confirm live before pay | M11: Week starts Sunday in IN and SG, Monday elsewhere | N11: 5 | O11: 4 | P11: 2 | Q11: Y | R11: =IF(OR(N11="",P11=""),"",ROUND(N11*O11/P11,1)) -> 10 | S11: =IF(R11="","",IF(Q11="Y",1,IF(P11>='Read me'!$B$16,3,IF(AND(R11>='Read me'!$B$14,P11<='Read me'!$B$15),1,2)))) -> 1
A12: FL-01-011 | B12: Flights | C12: FL-01 | D12: One-way and return flights | E12: Search | F12: Book a one-way flight | G12: Dates fixed | I12: One way to Dubai on Friday | J12: Results for one-way only | K12: FlightCard, Rail | N12: 4 | O12: 4 | P12: 1 | R12: =IF(OR(N12="",P12=""),"",ROUND(N12*O12/P12,1)) -> 16 | S12: =IF(R12="","",IF(Q12="Y",1,IF(P12>='Read me'!$B$16,3,IF(AND(R12>='Read me'!$B$14,P12<='Read me'!$B$15),1,2)))) -> 1
A13: FL-01-012 | B13: Flights | C13: FL-01 | D13: One-way and return flights | E13: Search | F13: Search with filters | G13: Direct only | I13: Only direct | J13: Filters and says how many are left | K13: FilterBar, Chips | N13: 5 | O13: 3 | P13: 1 | R13: =IF(OR(N13="",P13=""),"",ROUND(N13*O13/P13,1)) -> 15 | S13: =IF(R13="","",IF(Q13="Y",1,IF(P13>='Read me'!$B$16,3,IF(AND(R13>='Read me'!$B$14,P13<='Read me'!$B$15),1,2)))) -> 1
A14: FL-01-013 | B14: Flights | C14: FL-01 | D14: One-way and return flights | E14: Search | F14: Search with filters | G14: Time of day | I14: Nothing before 9am | J14: Filters by departure time | K14: FilterBar | N14: 4 | O14: 3 | P14: 1 | R14: =IF(OR(N14="",P14=""),"",ROUND(N14*O14/P14,1)) -> 12 | S14: =IF(R14="","",IF(Q14="Y",1,IF(P14>='Read me'!$B$16,3,IF(AND(R14>='Read me'!$B$14,P14<='Read me'!$B$15),1,2)))) -> 1
A15: FL-01-014 | B15: Flights | C15: FL-01 | D15: One-way and return flights | E15: Search | F15: Search with filters | G15: Airline preference | I15: Only airlines where I earn miles | J15: Filters to airlines linked to the customer's schemes | K15: FilterBar, Badge | L15: Frequent flyer numbers from the profile | N15: 3 | O15: 3 | P15: 1 | R15: =IF(OR(N15="",P15=""),"",ROUND(N15*O15/P15,1)) -> 9 | S15: =IF(R15="","",IF(Q15="Y",1,IF(P15>='Read me'!$B$16,3,IF(AND(R15>='Read me'!$B$14,P15<='Read me'!$B$15),1,2)))) -> 1
A16: FL-01-015 | B16: Flights | C16: FL-01 | D16: One-way and return flights | E16: Search | F16: Search with filters | G16: Bag included | I16: Must include a checked bag | J16: Filters to fares with a checked bag, shows true total | K16: FilterBar, FareFamilies | L16: Total must include the bag | N16: 4 | O16: 3 | P16: 1 | R16: =IF(OR(N16="",P16=""),"",ROUND(N16*O16/P16,1)) -> 12 | S16: =IF(R16="","",IF(Q16="Y",1,IF(P16>='Read me'!$B$16,3,IF(AND(R16>='Read me'!$B$14,P16<='Read me'!$B$15),1,2)))) -> 1
A17: FL-01-016 | B17: Flights | C17: FL-01 | D17: One-way and return flights | E17: Search | F17: Search nearby airports | G17: City, not airport | I17: Any London airport | J17: Searches all airports for the city | K17: FlightCard | L17: Airport groups per city | N17: 4 | O17: 3 | P17: 1 | R17: =IF(OR(N17="",P17=""),"",ROUND(N17*O17/P17,1)) -> 12 | S17: =IF(R17="","",IF(Q17="Y",1,IF(P17>='Read me'!$B$16,3,IF(AND(R17>='Read me'!$B$14,P17<='Read me'!$B$15),1,2)))) -> 1
A18: FL-01-017 | B18: Flights | C18: FL-01 | D18: One-way and return flights | E18: Search | F18: Search by voice | G18: Hands busy | I18: (spoken) Flights to Goa next weekend | J18: Transcribes, confirms understanding, searches | K18: AskBar (listening), YouSaid | L18: Shows what it heard before acting | M18: Voice in English first; Hindi, Arabic, Malay later | N18: 3 | O18: 3 | P18: 2 | R18: =IF(OR(N18="",P18=""),"",ROUND(N18*O18/P18,1)) -> 4.5 | S18: =IF(R18="","",IF(Q18="Y",1,IF(P18>='Read me'!$B$16,3,IF(AND(R18>='Read me'!$B$14,P18<='Read me'!$B$15),1,2)))) -> 2
A19: FL-01-018 | B19: Flights | C19: FL-01 | D19: One-way and return flights | E19: Search | F19: Search premium cabins | G19: Business class | I19: Business class to Singapore | J19: Shows business fares and points cost | K19: FlightCard, FareFamilies | N19: 2 | O19: 5 | P19: 1 | R19: =IF(OR(N19="",P19=""),"",ROUND(N19*O19/P19,1)) -> 10 | S19: =IF(R19="","",IF(Q19="Y",1,IF(P19>='Read me'!$B$16,3,IF(AND(R19>='Read me'!$B$14,P19<='Read me'!$B$15),1,2)))) -> 1
A20: FL-01-019 | B20: Flights | C20: FL-01 | D20: One-way and return flights | E20: Search | F20: Search with points and cash | G20: Budget in points | I20: Use no more than 20,000 points | J20: Prices each option as points plus cash | K20: PointsSlider, Price | L20: Point value from the bank | N20: 4 | O20: 4 | P20: 1 | R20: =IF(OR(N20="",P20=""),"",ROUND(N20*O20/P20,1)) -> 16 | S20: =IF(R20="","",IF(Q20="Y",1,IF(P20>='Read me'!$B$16,3,IF(AND(R20>='Read me'!$B$14,P20<='Read me'!$B$15),1,2)))) -> 1
A21: FL-01-020 | B21: Flights | C21: FL-01 | D21: One-way and return flights | E21: Search | F21: Nothing found | G21: Too strict | H21: No results | I21: Direct, before 9am, under £100 | J21: Says which filter blocks it and offers the nearest options | K21: StateCard (empty) | L21: Never invents a flight | N21: 3 | O21: 3 | P21: 1 | R21: =IF(OR(N21="",P21=""),"",ROUND(N21*O21/P21,1)) -> 9 | S21: =IF(R21="","",IF(Q21="Y",1,IF(P21>='Read me'!$B$16,3,IF(AND(R21>='Read me'!$B$14,P21<='Read me'!$B$15),1,2)))) -> 1
A22: FL-01-021 | B22: Flights | C22: FL-01 | D22: One-way and return flights | E22: Search | F22: Search fails | G22: Supplier down | H22: Timeout | I22: (any search) | J22: Says the airline is not answering, nothing was booked, try again | K22: StateCard (error) | L22: Retry with backoff; switch supplier if available | N22: 2 | O22: 2 | P22: 2 | Q22: Y | R22: =IF(OR(N22="",P22=""),"",ROUND(N22*O22/P22,1)) -> 2 | S22: =IF(R22="","",IF(Q22="Y",1,IF(P22>='Read me'!$B$16,3,IF(AND(R22>='Read me'!$B$14,P22<='Read me'!$B$15),1,2)))) -> 1
A23: FL-01-022 | B23: Flights | C23: FL-01 | D23: One-way and return flights | E23: Search | F23: Book last minute | G23: Today | I23: Next flight to Edinburgh | J23: Shows flights leaving soonest with check-in cut-off | K23: FlightCard, Status | L23: Cut-off times per airline | N23: 2 | O23: 4 | P23: 2 | R23: =IF(OR(N23="",P23=""),"",ROUND(N23*O23/P23,1)) -> 4 | S23: =IF(R23="","",IF(Q23="Y",1,IF(P23>='Read me'!$B$16,3,IF(AND(R23>='Read me'!$B$14,P23<='Read me'!$B$15),1,2)))) -> 2
A24: FL-01-023 | B24: Flights | C24: FL-01 | D24: One-way and return flights | E24: Choose | F24: Choose between flights | G24: Two close options | I24: Which is better, the 7am or the 11am? | J24: Compares on what differs: time, bag, price, points back | K24: Compare | L24: Only facts from the fares | N24: 4 | O24: 4 | P24: 1 | R24: =IF(OR(N24="",P24=""),"",ROUND(N24*O24/P24,1)) -> 16 | S24: =IF(R24="","",IF(Q24="Y",1,IF(P24>='Read me'!$B$16,3,IF(AND(R24>='Read me'!$B$14,P24<='Read me'!$B$15),1,2)))) -> 1
A25: FL-01-024 | B25: Flights | C25: FL-01 | D25: One-way and return flights | E25: Choose | F25: Understand a fare | G25: Unsure what is included | I25: Does Light include a bag? | J25: Shows fare families, ticked and greyed | K25: FareFamilies | L25: Fare rules from the supplier, word for word in the source | N25: 5 | O25: 4 | P25: 2 | Q25: Y | R25: =IF(OR(N25="",P25=""),"",ROUND(N25*O25/P25,1)) -> 10 | S25: =IF(R25="","",IF(Q25="Y",1,IF(P25>='Read me'!$B$16,3,IF(AND(R25>='Read me'!$B$14,P25<='Read me'!$B$15),1,2)))) -> 1
A26: FL-01-025 | B26: Flights | C26: FL-01 | D26: One-way and return flights | E26: Choose | F26: Understand change rules | G26: Might change plans | I26: Can I change the date later? | J26: Plain-words fare rules: free, fee, not possible | K26: FareRules | L26: Rules from fare; never guessed | N26: 4 | O26: 4 | P26: 3 | R26: =IF(OR(N26="",P26=""),"",ROUND(N26*O26/P26,1)) -> 5.3 | S26: =IF(R26="","",IF(Q26="Y",1,IF(P26>='Read me'!$B$16,3,IF(AND(R26>='Read me'!$B$14,P26<='Read me'!$B$15),1,2)))) -> 2
A27: FL-01-026 | B27: Flights | C27: FL-01 | D27: One-way and return flights | E27: Choose | F27: See the full journey | G27: Connection | I27: How long is the stop in Porto? | J27: Itinerary with layover; tight ones in amber | K27: Itinerary | L27: Minimum connection time per airport | N27: 3 | O27: 3 | P27: 2 | R27: =IF(OR(N27="",P27=""),"",ROUND(N27*O27/P27,1)) -> 4.5 | S27: =IF(R27="","",IF(Q27="Y",1,IF(P27>='Read me'!$B$16,3,IF(AND(R27>='Read me'!$B$14,P27<='Read me'!$B$15),1,2)))) -> 2
A28: FL-01-027 | B28: Flights | C28: FL-01 | D28: One-way and return flights | E28: Choose | F28: See the plane | G28: Comfort | I28: What plane is it? | J28: Aircraft type and seat pitch if known | K28: Itinerary, Meta | N28: 2 | O28: 2 | P28: 1 | R28: =IF(OR(N28="",P28=""),"",ROUND(N28*O28/P28,1)) -> 4 | S28: =IF(R28="","",IF(Q28="Y",1,IF(P28>='Read me'!$B$16,3,IF(AND(R28>='Read me'!$B$14,P28<='Read me'!$B$15),1,2)))) -> 2
A29: FL-01-028 | B29: Flights | C29: FL-01 | D29: One-way and return flights | E29: Choose | F29: Choose travellers | G29: Children | I29: Two adults and a 3 year old | J29: Sets travellers with correct age bands | K29: Travellers | L29: Age on the day of travel; airline bands | N29: 4 | O29: 3 | P29: 2 | R29: =IF(OR(N29="",P29=""),"",ROUND(N29*O29/P29,1)) -> 6 | S29: =IF(R29="","",IF(Q29="Y",1,IF(P29>='Read me'!$B$16,3,IF(AND(R29>='Read me'!$B$14,P29<='Read me'!$B$15),1,2)))) -> 1
A30: FL-01-029 | B30: Flights | C30: FL-01 | D30: One-way and return flights | E30: Choose | F30: Choose travellers | G30: Infant on lap | I30: Plus a baby | J30: Adds infant, one per adult | K30: Travellers | L30: Infants never exceed adults | N30: 3 | O30: 3 | P30: 2 | R30: =IF(OR(N30="",P30=""),"",ROUND(N30*O30/P30,1)) -> 4.5 | S30: =IF(R30="","",IF(Q30="Y",1,IF(P30>='Read me'!$B$16,3,IF(AND(R30>='Read me'!$B$14,P30<='Read me'!$B$15),1,2)))) -> 2
A31: FL-01-030 | B31: Flights | C31: FL-01 | D31: One-way and return flights | E31: Choose | F31: Choose travellers | G31: Travelling alone as a minor | I31: My daughter is flying alone, she's 13 | J31: Explains the airline's unaccompanied minor service and hands over | K31: StateCard, Handoff | L31: Unaccompanied minors always go to a person | N31: 1 | O31: 3 | P31: 5 | R31: =IF(OR(N31="",P31=""),"",ROUND(N31*O31/P31,1)) -> 0.6 | S31: =IF(R31="","",IF(Q31="Y",1,IF(P31>='Read me'!$B$16,3,IF(AND(R31>='Read me'!$B$14,P31<='Read me'!$B$15),1,2)))) -> 3
A32: FL-01-031 | B32: Flights | C32: FL-01 | D32: One-way and return flights | E32: Choose | F32: Price changed | G32: Between search and choose | H32: Fare rose | I32: (taps a flight) | J32: Shows old and new price, asks to continue | K32: StateCard (price) | L32: Never book at a higher price without a new yes | N32: 3 | O32: 3 | P32: 3 | Q32: Y | R32: =IF(OR(N32="",P32=""),"",ROUND(N32*O32/P32,1)) -> 3 | S32: =IF(R32="","",IF(Q32="Y",1,IF(P32>='Read me'!$B$16,3,IF(AND(R32>='Read me'!$B$14,P32<='Read me'!$B$15),1,2)))) -> 1
A33: FL-01-032 | B33: Flights | C33: FL-01 | D33: One-way and return flights | E33: Choose | F33: Sold out | G33: Last seats | H33: Fare gone | I33: (taps a flight) | J33: Says it has gone and offers the next best | K33: StateCard (soldout) | N33: 3 | O33: 3 | P33: 2 | Q33: Y | R33: =IF(OR(N33="",P33=""),"",ROUND(N33*O33/P33,1)) -> 4.5 | S33: =IF(R33="","",IF(Q33="Y",1,IF(P33>='Read me'!$B$16,3,IF(AND(R33>='Read me'!$B$14,P33<='Read me'!$B$15),1,2)))) -> 1
A34: FL-01-033 | B34: Flights | C34: FL-01 | D34: One-way and return flights | E34: Choose | F34: Hold a fare | G34: Deciding | I34: Can you hold this for a day? | J34: Offers fare hold if the airline sells it | K34: StateCard, ConfirmSheet | L34: Hold price and time from the airline | N34: 2 | O34: 3 | P34: 3 | R34: =IF(OR(N34="",P34=""),"",ROUND(N34*O34/P34,1)) -> 2 | S34: =IF(R34="","",IF(Q34="Y",1,IF(P34>='Read me'!$B$16,3,IF(AND(R34>='Read me'!$B$14,P34<='Read me'!$B$15),1,2)))) -> 2
A35: FL-01-034 | B35: Flights | C35: FL-01 | D35: One-way and return flights | E35: Choose | F35: Check the carbon | G35: Green choice | I35: Which one is lower carbon? | J35: Shows estimated emissions per option | K35: Compare | L35: Estimate from a named source | M35: Carbon disclosure rules vary; EU strictest | N35: 1 | O35: 2 | P35: 2 | R35: =IF(OR(N35="",P35=""),"",ROUND(N35*O35/P35,1)) -> 1 | S35: =IF(R35="","",IF(Q35="Y",1,IF(P35>='Read me'!$B$16,3,IF(AND(R35>='Read me'!$B$14,P35<='Read me'!$B$15),1,2)))) -> 2
A36: FL-02-001 | B36: Flights | C36: FL-02 | D36: Multi-city, open jaw, groups | E36: Search | F36: Book a multi-city trip | G36: Several stops | I36: London to Lisbon, then Porto, then home | J36: Builds the legs and prices them together and separately | K36: Itinerary, Compare | L36: Separate tickets flagged: missed connections not protected | N36: 2 | O36: 4 | P36: 3 | R36: =IF(OR(N36="",P36=""),"",ROUND(N36*O36/P36,1)) -> 2.7 | S36: =IF(R36="","",IF(Q36="Y",1,IF(P36>='Read me'!$B$16,3,IF(AND(R36>='Read me'!$B$14,P36<='Read me'!$B$15),1,2)))) -> 2
A37: FL-02-002 | B37: Flights | C37: FL-02 | D37: Multi-city, open jaw, groups | E37: Search | F37: Search for a group | G37: 5 or more | I37: Flights for 8 of us | J37: Checks seat availability for 8, offers group fare route | K37: Travellers, StateCard, Handoff | L37: Over 9 passengers goes to group desk | N37: 2 | O37: 4 | P37: 3 | R37: =IF(OR(N37="",P37=""),"",ROUND(N37*O37/P37,1)) -> 2.7 | S37: =IF(R37="","",IF(Q37="Y",1,IF(P37>='Read me'!$B$16,3,IF(AND(R37>='Read me'!$B$14,P37<='Read me'!$B$15),1,2)))) -> 2
A38: FL-02-003 | B38: Flights | C38: FL-02 | D38: Multi-city, open jaw, groups | E38: Search | F38: Book a return flight | G38: Open jaw | I38: Fly into Lisbon, back from Porto | J38: Prices the open jaw as one trip | K38: Itinerary, FlightCard | L38: Fare construction by supplier | N38: 2 | O38: 3 | P38: 2 | R38: =IF(OR(N38="",P38=""),"",ROUND(N38*O38/P38,1)) -> 3 | S38: =IF(R38="","",IF(Q38="Y",1,IF(P38>='Read me'!$B$16,3,IF(AND(R38>='Read me'!$B$14,P38<='Read me'!$B$15),1,2)))) -> 2
A39: FL-02-004 | B39: Flights | C39: FL-02 | D39: Multi-city, open jaw, groups | E39: Search | F39: Book for someone else | G39: Gift trip | I39: Book flights for my parents | J39: Captures their names, pays from my points | K39: Travellers, PayWith | L39: Names must match passports | N39: 2 | O39: 4 | P39: 3 | R39: =IF(OR(N39="",P39=""),"",ROUND(N39*O39/P39,1)) -> 2.7 | S39: =IF(R39="","",IF(Q39="Y",1,IF(P39>='Read me'!$B$16,3,IF(AND(R39>='Read me'!$B$14,P39<='Read me'!$B$15),1,2)))) -> 2
A40: FL-02-005 | B40: Flights | C40: FL-02 | D40: Multi-city, open jaw, groups | E40: Search | F40: Book a multi-city trip | G40: Stopover | I40: London to Singapore with 3 nights in Dubai on the way | J40: Prices the stopover as one ticket and shows the extra cost of the stop | K40: Itinerary, FlightCard, PriceLines | L40: Fare construction by supplier; stopover rules from the fare | N40: 2 | O40: 4 | P40: 2 | R40: =IF(OR(N40="",P40=""),"",ROUND(N40*O40/P40,1)) -> 4 | S40: =IF(R40="","",IF(Q40="Y",1,IF(P40>='Read me'!$B$16,3,IF(AND(R40>='Read me'!$B$14,P40<='Read me'!$B$15),1,2)))) -> 2
A41: FL-02-006 | B41: Flights | C41: FL-02 | D41: Multi-city, open jaw, groups | E41: Search | F41: Search for a group | G41: 10 or more | I41: Flights for our team of 14 to Goa | J41: Explains group fares, collects names later, hands to the group desk | K41: Travellers, Answer, Handoff | L41: Group bookings over 9 go to the group desk | N41: 2 | O41: 4 | P41: 2 | R41: =IF(OR(N41="",P41=""),"",ROUND(N41*O41/P41,1)) -> 4 | S41: =IF(R41="","",IF(Q41="Y",1,IF(P41>='Read me'!$B$16,3,IF(AND(R41>='Read me'!$B$14,P41<='Read me'!$B$15),1,2)))) -> 2
A42: FL-02-007 | B42: Flights | C42: FL-02 | D42: Multi-city, open jaw, groups | E42: Choose | F42: Book a multi-city trip | G42: Several stops | H42: One leg sold out | I42: Book the three flights we planned | J42: Says which leg has gone, offers the nearest alternative for that leg only, keeps the rest | K42: Itinerary, StateCard (soldout), FlightCard | L42: Never book part of a multi-city trip without a new yes | N42: 2 | O42: 3 | P42: 3 | R42: =IF(OR(N42="",P42=""),"",ROUND(N42*O42/P42,1)) -> 2 | S42: =IF(R42="","",IF(Q42="Y",1,IF(P42>='Read me'!$B$16,3,IF(AND(R42>='Read me'!$B$14,P42<='Read me'!$B$15),1,2)))) -> 2
A43: FL-02-008 | B43: Flights | C43: FL-02 | D43: Multi-city, open jaw, groups | E43: Pay | F43: Book a multi-city trip | G43: Separate tickets | H43: Second ticket fails | I43: (confirms) | J43: First ticket booked, second failed: explains, offers to retry or cancel the first within its free window | K43: StateCard (error), Receipt, Handoff | L43: Pair separate tickets only with a clear warning; void window from the supplier | N43: 1 | O43: 3 | P43: 5 | R43: =IF(OR(N43="",P43=""),"",ROUND(N43*O43/P43,1)) -> 0.6 | S43: =IF(R43="","",IF(Q43="Y",1,IF(P43>='Read me'!$B$16,3,IF(AND(R43>='Read me'!$B$14,P43<='Read me'!$B$15),1,2)))) -> 3
A44: FL-02-009 | B44: Flights | C44: FL-02 | D44: Multi-city, open jaw, groups | E44: Pay | F44: Search for a group | G44: 10 or more | H44: Names not ready | I44: I'll send the names next week | J44: Holds the group fare if the airline allows and sets a reminder for the name deadline | K44: StateCard, Toast | L44: Name deadline and deposit from the airline | N44: 1 | O44: 3 | P44: 3 | R44: =IF(OR(N44="",P44=""),"",ROUND(N44*O44/P44,1)) -> 1 | S44: =IF(R44="","",IF(Q44="Y",1,IF(P44>='Read me'!$B$16,3,IF(AND(R44>='Read me'!$B$14,P44<='Read me'!$B$15),1,2)))) -> 2
A45: FL-02-010 | B45: Flights | C45: FL-02 | D45: Multi-city, open jaw, groups | E45: Before | F45: Change a multi-city trip | G45: Middle leg | I45: Stay two more nights in Dubai | J45: Prices changing the middle leg and shows the difference | K45: ChangeFlight, Itinerary | L45: Change rules apply per fare component | N45: 1 | O45: 3 | P45: 3 | R45: =IF(OR(N45="",P45=""),"",ROUND(N45*O45/P45,1)) -> 1 | S45: =IF(R45="","",IF(Q45="Y",1,IF(P45>='Read me'!$B$16,3,IF(AND(R45>='Read me'!$B$14,P45<='Read me'!$B$15),1,2)))) -> 2
A46: FL-03-001 | B46: Flights | C46: FL-03 | D46: Award seats and upgrades | E46: Discover | F46: Find award seats | G46: Points balance | I46: (Gratifi starts it) | J46: Tells them award seats to a saved destination have opened | K46: StickyNote, FlightCard | L46: Only with alert consent | N46: 2 | O46: 4 | P46: 2 | R46: =IF(OR(N46="",P46=""),"",ROUND(N46*O46/P46,1)) -> 4 | S46: =IF(R46="","",IF(Q46="Y",1,IF(P46>='Read me'!$B$16,3,IF(AND(R46>='Read me'!$B$14,P46<='Read me'!$B$15),1,2)))) -> 2
A47: FL-03-002 | B47: Flights | C47: FL-03 | D47: Award seats and upgrades | E47: Search | F47: Find award seats | G47: Points only | I47: Business class to Singapore with my airline miles | J47: Shows award seat availability and the miles and taxes needed | K47: FlightCard, FareFamilies, Price | L47: Award space from the airline or partner feed only | M47: Award programmes and partners differ per bank and market | N47: 2 | O47: 5 | P47: 2 | R47: =IF(OR(N47="",P47=""),"",ROUND(N47*O47/P47,1)) -> 5 | S47: =IF(R47="","",IF(Q47="Y",1,IF(P47>='Read me'!$B$16,3,IF(AND(R47>='Read me'!$B$14,P47<='Read me'!$B$15),1,2)))) -> 2
A48: FL-03-003 | B48: Flights | C48: FL-03 | D48: Award seats and upgrades | E48: Search | F48: Find award seats | G48: Flexible dates | I48: Any day in March with award seats for two | J48: Calendar of days with two award seats | K48: PriceCalendar | L48: Award space changes by the minute; confirm before transfer | N48: 2 | O48: 4 | P48: 2 | R48: =IF(OR(N48="",P48=""),"",ROUND(N48*O48/P48,1)) -> 4 | S48: =IF(R48="","",IF(Q48="Y",1,IF(P48>='Read me'!$B$16,3,IF(AND(R48>='Read me'!$B$14,P48<='Read me'!$B$15),1,2)))) -> 2
A49: FL-03-004 | B49: Flights | C49: FL-03 | D49: Award seats and upgrades | E49: Choose | F49: Find award seats | G49: Need a transfer first | I49: I have bank points, not miles | J49: Shows the transfer needed, the rate, how long it takes, and warns it cannot be undone | K49: Answer, PriceLines, ConfirmSheet | L49: Never transfer before checking award space is still there | N49: 2 | O49: 5 | P49: 4 | R49: =IF(OR(N49="",P49=""),"",ROUND(N49*O49/P49,1)) -> 2.5 | S49: =IF(R49="","",IF(Q49="Y",1,IF(P49>='Read me'!$B$16,3,IF(AND(R49>='Read me'!$B$14,P49<='Read me'!$B$15),1,2)))) -> 3
A50: FL-03-005 | B50: Flights | C50: FL-03 | D50: Award seats and upgrades | E50: Pay | F50: Find award seats | G50: Transfer done | H50: Seat gone after transfer | I50: (after transfer) | J50: Says the seat went before booking, offers other dates; miles stay in the airline account | K50: StateCard (soldout), Handoff | L50: Transfers are final; say so before, not after | N50: 1 | O50: 3 | P50: 5 | R50: =IF(OR(N50="",P50=""),"",ROUND(N50*O50/P50,1)) -> 0.6 | S50: =IF(R50="","",IF(Q50="Y",1,IF(P50>='Read me'!$B$16,3,IF(AND(R50>='Read me'!$B$14,P50<='Read me'!$B$15),1,2)))) -> 3
A51: FL-03-006 | B51: Flights | C51: FL-03 | D51: Award seats and upgrades | E51: Add-ons | F51: Upgrade with points | G51: Booked | I51: Can I upgrade to business? | J51: Checks upgrade price in points and cash | K51: FareFamilies, ConfirmSheet | L51: Upgrade inventory from the airline | N51: 2 | O51: 4 | P51: 2 | R51: =IF(OR(N51="",P51=""),"",ROUND(N51*O51/P51,1)) -> 4 | S51: =IF(R51="","",IF(Q51="Y",1,IF(P51>='Read me'!$B$16,3,IF(AND(R51>='Read me'!$B$14,P51<='Read me'!$B$15),1,2)))) -> 2
A52: FL-03-007 | B52: Flights | C52: FL-03 | D52: Award seats and upgrades | E52: Add-ons | F52: Upgrade with points | G52: Booked | H52: No upgrade space | I52: Upgrade me to business | J52: Says no space now, offers a waitlist or alert if the airline supports it | K52: StateCard, Toggle | L52: Upgrade inventory from the airline | N52: 2 | O52: 3 | P52: 2 | R52: =IF(OR(N52="",P52=""),"",ROUND(N52*O52/P52,1)) -> 3 | S52: =IF(R52="","",IF(Q52="Y",1,IF(P52>='Read me'!$B$16,3,IF(AND(R52>='Read me'!$B$14,P52<='Read me'!$B$15),1,2)))) -> 2
A53: FL-03-008 | B53: Flights | C53: FL-03 | D53: Award seats and upgrades | E53: Add-ons | F53: Upgrade with points | G53: Bid upgrade | I53: Can I bid for an upgrade? | J53: Explains the airline's bid scheme and places a bid in points or cash | K53: Answer, PointsSlider, ConfirmSheet | L53: Bid rules from the airline; charged only if accepted | N53: 1 | O53: 3 | P53: 3 | R53: =IF(OR(N53="",P53=""),"",ROUND(N53*O53/P53,1)) -> 1 | S53: =IF(R53="","",IF(Q53="Y",1,IF(P53>='Read me'!$B$16,3,IF(AND(R53>='Read me'!$B$14,P53<='Read me'!$B$15),1,2)))) -> 2
A54: FL-03-009 | B54: Flights | C54: FL-03 | D54: Award seats and upgrades | E54: Before | F54: Cancel an award booking | G54: Plans changed | I54: Cancel my award flight | J54: Shows the redeposit fee and what comes back as miles | K54: FareRules, ConfirmSheet | L54: Redeposit fees from the airline programme | N54: 1 | O54: 3 | P54: 3 | R54: =IF(OR(N54="",P54=""),"",ROUND(N54*O54/P54,1)) -> 1 | S54: =IF(R54="","",IF(Q54="Y",1,IF(P54>='Read me'!$B$16,3,IF(AND(R54>='Read me'!$B$14,P54<='Read me'!$B$15),1,2)))) -> 2
A55: FL-04-001 | B55: Flights | C55: FL-04 | D55: Seats, bags, meals, assistance | E55: Add-ons | F55: Pick seats | G55: Together | I55: Seats together please | J55: Seat map with a suggested pair | K55: SeatMap | L55: Seat prices from the airline | N55: 5 | O55: 4 | P55: 1 | Q55: Y | R55: =IF(OR(N55="",P55=""),"",ROUND(N55*O55/P55,1)) -> 20 | S55: =IF(R55="","",IF(Q55="Y",1,IF(P55>='Read me'!$B$16,3,IF(AND(R55>='Read me'!$B$14,P55<='Read me'!$B$15),1,2)))) -> 1
A56: FL-04-002 | B56: Flights | C56: FL-04 | D56: Seats, bags, meals, assistance | E56: Add-ons | F56: Pick seats | G56: Preference saved | I56: (automatic) | J56: Uses saved aisle or window preference | K56: StickyNote (blue), SeatMap | L56: Preference from profile | N56: 4 | O56: 3 | P56: 1 | R56: =IF(OR(N56="",P56=""),"",ROUND(N56*O56/P56,1)) -> 12 | S56: =IF(R56="","",IF(Q56="Y",1,IF(P56>='Read me'!$B$16,3,IF(AND(R56>='Read me'!$B$14,P56<='Read me'!$B$15),1,2)))) -> 1
A57: FL-04-003 | B57: Flights | C57: FL-04 | D57: Seats, bags, meals, assistance | E57: Add-ons | F57: Pick seats | G57: Extra legroom | I57: Exit row please | J57: Shows extra-legroom seats and price, explains exit row rules | K57: SeatMap | L57: Exit row eligibility rules | N57: 3 | O57: 3 | P57: 2 | R57: =IF(OR(N57="",P57=""),"",ROUND(N57*O57/P57,1)) -> 4.5 | S57: =IF(R57="","",IF(Q57="Y",1,IF(P57>='Read me'!$B$16,3,IF(AND(R57>='Read me'!$B$14,P57<='Read me'!$B$15),1,2)))) -> 2
A58: FL-04-004 | B58: Flights | C58: FL-04 | D58: Seats, bags, meals, assistance | E58: Add-ons | F58: Seat taken | G58: Choosing | H58: Seat gone | I58: (taps seat) | J58: Says it has gone, suggests the nearest pair | K58: StateCard (soldout) | N58: 2 | O58: 2 | P58: 1 | Q58: Y | R58: =IF(OR(N58="",P58=""),"",ROUND(N58*O58/P58,1)) -> 4 | S58: =IF(R58="","",IF(Q58="Y",1,IF(P58>='Read me'!$B$16,3,IF(AND(R58>='Read me'!$B$14,P58<='Read me'!$B$15),1,2)))) -> 1
A59: FL-04-005 | B59: Flights | C59: FL-04 | D59: Seats, bags, meals, assistance | E59: Add-ons | F59: Add bags | G59: Checked bag | I59: Add a suitcase | J59: Adds bag, shows price per person per flight | K59: BagPicker | L59: Bag prices from the airline | M59: Cabin allowance usually 7kg on Asian carriers; 10kg or more on some European ones | N59: 5 | O59: 4 | P59: 1 | Q59: Y | R59: =IF(OR(N59="",P59=""),"",ROUND(N59*O59/P59,1)) -> 20 | S59: =IF(R59="","",IF(Q59="Y",1,IF(P59>='Read me'!$B$16,3,IF(AND(R59>='Read me'!$B$14,P59<='Read me'!$B$15),1,2)))) -> 1
A60: FL-04-006 | B60: Flights | C60: FL-04 | D60: Seats, bags, meals, assistance | E60: Add-ons | F60: Add bags | G60: Sports equipment | I60: I'm taking golf clubs | J60: Adds special baggage if the airline allows | K60: BagPicker, Handoff | L60: Special items from the airline list | N60: 1 | O60: 2 | P60: 2 | R60: =IF(OR(N60="",P60=""),"",ROUND(N60*O60/P60,1)) -> 1 | S60: =IF(R60="","",IF(Q60="Y",1,IF(P60>='Read me'!$B$16,3,IF(AND(R60>='Read me'!$B$14,P60<='Read me'!$B$15),1,2)))) -> 2
A61: FL-04-007 | B61: Flights | C61: FL-04 | D61: Seats, bags, meals, assistance | E61: Add-ons | F61: Add meals | G61: Dietary | I61: Vegetarian meal | J61: Requests the meal, confirms it is a request | K61: Toast | L61: Meal requests are not guaranteed | M61: Common requests differ: Jain meals (IN), halal (AE, MY) | N61: 2 | O61: 2 | P61: 1 | R61: =IF(OR(N61="",P61=""),"",ROUND(N61*O61/P61,1)) -> 4 | S61: =IF(R61="","",IF(Q61="Y",1,IF(P61>='Read me'!$B$16,3,IF(AND(R61>='Read me'!$B$14,P61<='Read me'!$B$15),1,2)))) -> 2
A62: FL-04-008 | B62: Flights | C62: FL-04 | D62: Seats, bags, meals, assistance | E62: Add-ons | F62: Add lounge | G62: Card benefit | I62: Can I use a lounge? | J62: Checks card benefit, books the pass | K62: BenefitRow, LoungePass | L62: Visits left from the bank | N62: 3 | O62: 4 | P62: 1 | R62: =IF(OR(N62="",P62=""),"",ROUND(N62*O62/P62,1)) -> 12 | S62: =IF(R62="","",IF(Q62="Y",1,IF(P62>='Read me'!$B$16,3,IF(AND(R62>='Read me'!$B$14,P62<='Read me'!$B$15),1,2)))) -> 1
A63: FL-04-009 | B63: Flights | C63: FL-04 | D63: Seats, bags, meals, assistance | E63: Add-ons | F63: Add fast track | G63: Short on time | I63: Add fast track security | J63: Adds if available at the airport | K63: Toast, PriceLines | N63: 2 | O63: 3 | P63: 1 | R63: =IF(OR(N63="",P63=""),"",ROUND(N63*O63/P63,1)) -> 6 | S63: =IF(R63="","",IF(Q63="Y",1,IF(P63>='Read me'!$B$16,3,IF(AND(R63>='Read me'!$B$14,P63<='Read me'!$B$15),1,2)))) -> 1
A64: FL-04-010 | B64: Flights | C64: FL-04 | D64: Seats, bags, meals, assistance | E64: Add-ons | F64: Add travel insurance | G64: Card cover | I64: Am I covered? | J64: Explains card travel cover, offers top-up if not covered | K64: Answer, BenefitRow | L64: Cover terms from the bank; not advice | M64: Insurance selling rules differ per market; may need a licensed partner | N64: 3 | O64: 4 | P64: 4 | R64: =IF(OR(N64="",P64=""),"",ROUND(N64*O64/P64,1)) -> 3 | S64: =IF(R64="","",IF(Q64="Y",1,IF(P64>='Read me'!$B$16,3,IF(AND(R64>='Read me'!$B$14,P64<='Read me'!$B$15),1,2)))) -> 3
A65: FL-04-011 | B65: Flights | C65: FL-04 | D65: Seats, bags, meals, assistance | E65: Add-ons | F65: Add a hotel | G65: Same trip | I65: Add a hotel | J65: Hotel search for the trip dates and destination | K65: HotelCard, Rail | N65: 4 | O65: 5 | P65: 1 | R65: =IF(OR(N65="",P65=""),"",ROUND(N65*O65/P65,1)) -> 20 | S65: =IF(R65="","",IF(Q65="Y",1,IF(P65>='Read me'!$B$16,3,IF(AND(R65>='Read me'!$B$14,P65<='Read me'!$B$15),1,2)))) -> 1
A66: FL-04-012 | B66: Flights | C66: FL-04 | D66: Seats, bags, meals, assistance | E66: Add-ons | F66: Add a ride | G66: Airport transfer | I66: Car to the airport | J66: Books a ride timed to the flight | K66: RideOption | L66: Timing from flight and traffic | N66: 3 | O66: 3 | P66: 2 | R66: =IF(OR(N66="",P66=""),"",ROUND(N66*O66/P66,1)) -> 4.5 | S66: =IF(R66="","",IF(Q66="Y",1,IF(P66>='Read me'!$B$16,3,IF(AND(R66>='Read me'!$B$14,P66<='Read me'!$B$15),1,2)))) -> 2
A67: FL-04-013 | B67: Flights | C67: FL-04 | D67: Seats, bags, meals, assistance | E67: Add-ons | F67: Add special assistance | G67: Reduced mobility | I67: My mother needs a wheelchair | J67: Requests assistance and confirms with the airline | K67: StateCard, Handoff | L67: Always confirmed with the airline | N67: 1 | O67: 3 | P67: 4 | R67: =IF(OR(N67="",P67=""),"",ROUND(N67*O67/P67,1)) -> 0.8 | S67: =IF(R67="","",IF(Q67="Y",1,IF(P67>='Read me'!$B$16,3,IF(AND(R67>='Read me'!$B$14,P67<='Read me'!$B$15),1,2)))) -> 3
A68: FL-04-014 | B68: Flights | C68: FL-04 | D68: Seats, bags, meals, assistance | E68: Add-ons | F68: Travel with a pet | G68: Pet in cabin | I68: Can my dog come? | J68: Explains the airline's pet rules and hands over to book | K68: Answer, Handoff | L68: Pet rules from the airline | M68: Pet import rules differ strictly by country | N68: 1 | O68: 2 | P68: 3 | R68: =IF(OR(N68="",P68=""),"",ROUND(N68*O68/P68,1)) -> 0.7 | S68: =IF(R68="","",IF(Q68="Y",1,IF(P68>='Read me'!$B$16,3,IF(AND(R68>='Read me'!$B$14,P68<='Read me'!$B$15),1,2)))) -> 2
A69: FL-04-015 | B69: Flights | C69: FL-04 | D69: Seats, bags, meals, assistance | E69: Add-ons | F69: Add infant seat | G69: Baby | I69: Can I get a bassinet? | J69: Requests a bassinet seat | K69: SeatMap, Toast | L69: Bassinet rows are airline-controlled | N69: 1 | O69: 2 | P69: 2 | R69: =IF(OR(N69="",P69=""),"",ROUND(N69*O69/P69,1)) -> 1 | S69: =IF(R69="","",IF(Q69="Y",1,IF(P69>='Read me'!$B$16,3,IF(AND(R69>='Read me'!$B$14,P69<='Read me'!$B$15),1,2)))) -> 2
A70: FL-04-016 | B70: Flights | C70: FL-04 | D70: Seats, bags, meals, assistance | E70: Add-ons | F70: Add bags | G70: Checked bag | H70: Bag price rose | I70: Add a suitcase | J70: Shows the new bag price before adding | K70: BagPicker, StateCard (price) | L70: Re-price before charging | N70: 2 | O70: 2 | P70: 2 | Q70: Y | R70: =IF(OR(N70="",P70=""),"",ROUND(N70*O70/P70,1)) -> 2 | S70: =IF(R70="","",IF(Q70="Y",1,IF(P70>='Read me'!$B$16,3,IF(AND(R70>='Read me'!$B$14,P70<='Read me'!$B$15),1,2)))) -> 1
A71: FL-04-017 | B71: Flights | C71: FL-04 | D71: Seats, bags, meals, assistance | E71: Add-ons | F71: Add meals | G71: Dietary | H71: Meal not available | I71: Vegan meal please | J71: Says the airline doesn't offer it on this flight and suggests bringing food | K71: StateCard | L71: Meal list from the airline | N71: 1 | O71: 2 | P71: 2 | R71: =IF(OR(N71="",P71=""),"",ROUND(N71*O71/P71,1)) -> 1 | S71: =IF(R71="","",IF(Q71="Y",1,IF(P71>='Read me'!$B$16,3,IF(AND(R71>='Read me'!$B$14,P71<='Read me'!$B$15),1,2)))) -> 2
A72: FL-04-018 | B72: Flights | C72: FL-04 | D72: Seats, bags, meals, assistance | E72: Add-ons | F72: Pick seats | G72: Paid seat | H72: Seat charge failed | I72: (confirms seat) | J72: Says the seat wasn't charged or held, offers to try again | K72: StateCard (error), SeatMap | L72: No seat without payment | N72: 1 | O72: 2 | P72: 2 | R72: =IF(OR(N72="",P72=""),"",ROUND(N72*O72/P72,1)) -> 1 | S72: =IF(R72="","",IF(Q72="Y",1,IF(P72>='Read me'!$B$16,3,IF(AND(R72>='Read me'!$B$14,P72<='Read me'!$B$15),1,2)))) -> 2
A73: FL-05-001 | B73: Flights | C73: FL-05 | D73: Changes and cancellations | E73: Before | F73: Change the date | G73: Before travel | I73: Move my outbound to Saturday | J73: Shows old and new, fee and fare difference, asks to confirm | K73: ChangeFlight, ConfirmSheet | L73: Fees from fare rules | N73: 3 | O73: 4 | P73: 3 | R73: =IF(OR(N73="",P73=""),"",ROUND(N73*O73/P73,1)) -> 4 | S73: =IF(R73="","",IF(Q73="Y",1,IF(P73>='Read me'!$B$16,3,IF(AND(R73>='Read me'!$B$14,P73<='Read me'!$B$15),1,2)))) -> 2
A74: FL-05-002 | B74: Flights | C74: FL-05 | D74: Changes and cancellations | E74: Before | F74: Change the name | G74: Typo | I74: My name is spelt wrong | J74: Checks airline rules for name corrections, hands over if needed | K74: StateCard, Handoff | L74: Name changes are airline decisions | N74: 2 | O74: 3 | P74: 4 | R74: =IF(OR(N74="",P74=""),"",ROUND(N74*O74/P74,1)) -> 1.5 | S74: =IF(R74="","",IF(Q74="Y",1,IF(P74>='Read me'!$B$16,3,IF(AND(R74>='Read me'!$B$14,P74<='Read me'!$B$15),1,2)))) -> 3
A75: FL-05-003 | B75: Flights | C75: FL-05 | D75: Changes and cancellations | E75: Before | F75: Cancel the booking | G75: Plans changed | I75: Cancel my flight | J75: Shows what comes back and how, asks to confirm | K75: FareRules, ConfirmSheet, Receipt | L75: Refund amounts from fare rules only | N75: 3 | O75: 3 | P75: 4 | R75: =IF(OR(N75="",P75=""),"",ROUND(N75*O75/P75,1)) -> 2.3 | S75: =IF(R75="","",IF(Q75="Y",1,IF(P75>='Read me'!$B$16,3,IF(AND(R75>='Read me'!$B$14,P75<='Read me'!$B$15),1,2)))) -> 3
A76: FL-05-004 | B76: Flights | C76: FL-05 | D76: Changes and cancellations | E76: Before | F76: Change the date | G76: Non-changeable fare | H76: Change not allowed | I76: Move my flight to Monday | J76: Explains the fare doesn't allow changes and shows the options: cancel for taxes back, or keep | K76: FareRules, StateCard | L76: Never promise a change the fare rules forbid | N76: 3 | O76: 3 | P76: 4 | R76: =IF(OR(N76="",P76=""),"",ROUND(N76*O76/P76,1)) -> 2.3 | S76: =IF(R76="","",IF(Q76="Y",1,IF(P76>='Read me'!$B$16,3,IF(AND(R76>='Read me'!$B$14,P76<='Read me'!$B$15),1,2)))) -> 3
A77: FL-05-005 | B77: Flights | C77: FL-05 | D77: Changes and cancellations | E77: Before | F77: Change the date | G77: Before travel | H77: Fare difference is higher | I77: Move it to Saturday | J77: Shows fee plus fare difference; asks to confirm the total | K77: ChangeFlight, ConfirmSheet | L77: Re-price at confirm | N77: 3 | O77: 4 | P77: 3 | R77: =IF(OR(N77="",P77=""),"",ROUND(N77*O77/P77,1)) -> 4 | S77: =IF(R77="","",IF(Q77="Y",1,IF(P77>='Read me'!$B$16,3,IF(AND(R77>='Read me'!$B$14,P77<='Read me'!$B$15),1,2)))) -> 2
A78: FL-05-006 | B78: Flights | C78: FL-05 | D78: Changes and cancellations | E78: Before | F78: Change the time | G78: Same day | I78: Can I take the earlier flight? | J78: Checks same-day change rules and seats, confirms | K78: ChangeFlight, ConfirmSheet | L78: Same-day change rules from the airline | N78: 2 | O78: 3 | P78: 3 | R78: =IF(OR(N78="",P78=""),"",ROUND(N78*O78/P78,1)) -> 2 | S78: =IF(R78="","",IF(Q78="Y",1,IF(P78>='Read me'!$B$16,3,IF(AND(R78>='Read me'!$B$14,P78<='Read me'!$B$15),1,2)))) -> 2
A79: FL-05-007 | B79: Flights | C79: FL-05 | D79: Changes and cancellations | E79: Before | F79: Cancel the booking | G79: Refundable fare | I79: Cancel and refund | J79: Shows refund amount, where it goes (card or points) and when | K79: FareRules, ConfirmSheet, Receipt | L79: Refund to the original method: points back as points | N79: 3 | O79: 3 | P79: 4 | R79: =IF(OR(N79="",P79=""),"",ROUND(N79*O79/P79,1)) -> 2.3 | S79: =IF(R79="","",IF(Q79="Y",1,IF(P79>='Read me'!$B$16,3,IF(AND(R79>='Read me'!$B$14,P79<='Read me'!$B$15),1,2)))) -> 3
A80: FL-05-008 | B80: Flights | C80: FL-05 | D80: Changes and cancellations | E80: Before | F80: Cancel the booking | G80: Within 24 hours | I80: I booked the wrong day an hour ago | J80: Checks the free cancellation window and cancels in full | K80: ConfirmSheet, Receipt | L80: Free window depends on airline and market (to confirm) | M80: Some markets and airlines give 24-hour free cancellation (to confirm per airline) | N80: 2 | O80: 3 | P80: 3 | R80: =IF(OR(N80="",P80=""),"",ROUND(N80*O80/P80,1)) -> 2 | S80: =IF(R80="","",IF(Q80="Y",1,IF(P80>='Read me'!$B$16,3,IF(AND(R80>='Read me'!$B$14,P80<='Read me'!$B$15),1,2)))) -> 2
A81: FL-05-009 | B81: Flights | C81: FL-05 | D81: Changes and cancellations | E81: Before | F81: Cancel the booking | G81: Travel credit | I81: Keep it as credit instead | J81: Converts to airline credit if allowed and shows expiry | K81: Receipt, Toast | L81: Credit terms from the airline | N81: 2 | O81: 3 | P81: 3 | R81: =IF(OR(N81="",P81=""),"",ROUND(N81*O81/P81,1)) -> 2 | S81: =IF(R81="","",IF(Q81="Y",1,IF(P81>='Read me'!$B$16,3,IF(AND(R81>='Read me'!$B$14,P81<='Read me'!$B$15),1,2)))) -> 2
A82: FL-05-010 | B82: Flights | C82: FL-05 | D82: Changes and cancellations | E82: Before | F82: Change the date | G82: Change request | H82: Supplier down | I82: Change my flight | J82: Says the airline system is not answering, nothing changed, will retry and tell them | K82: StateCard (error), Toast | L82: No change without supplier confirmation | N82: 1 | O82: 2 | P82: 3 | R82: =IF(OR(N82="",P82=""),"",ROUND(N82*O82/P82,1)) -> 0.7 | S82: =IF(R82="","",IF(Q82="Y",1,IF(P82>='Read me'!$B$16,3,IF(AND(R82>='Read me'!$B$14,P82<='Read me'!$B$15),1,2)))) -> 2
A83: FL-05-011 | B83: Flights | C83: FL-05 | D83: Changes and cancellations | E83: Before | F83: Add a traveller | G83: Booked | I83: Can my son join the same flight? | J83: Books a separate ticket on the same flight and links the bookings | K83: FlightCard, Travellers, ConfirmSheet | L83: Separate ticket; linked for seats | N83: 2 | O83: 3 | P83: 2 | R83: =IF(OR(N83="",P83=""),"",ROUND(N83*O83/P83,1)) -> 3 | S83: =IF(R83="","",IF(Q83="Y",1,IF(P83>='Read me'!$B$16,3,IF(AND(R83>='Read me'!$B$14,P83<='Read me'!$B$15),1,2)))) -> 2
A84: FL-06-001 | B84: Flights | C84: FL-06 | D84: Check-in and day of travel | E84: Before | F84: Check in | G84: Online | I84: (automatic) | J84: Checks in when it opens, sends boarding passes | K84: Toast, BoardingPass | L84: Consent to auto check-in | M84: India: web check-in expected for domestic flights | N84: 5 | O84: 4 | P84: 2 | Q84: Y | R84: =IF(OR(N84="",P84=""),"",ROUND(N84*O84/P84,1)) -> 10 | S84: =IF(R84="","",IF(Q84="Y",1,IF(P84>='Read me'!$B$16,3,IF(AND(R84>='Read me'!$B$14,P84<='Read me'!$B$15),1,2)))) -> 1
A85: FL-06-002 | B85: Flights | C85: FL-06 | D85: Check-in and day of travel | E85: Before | F85: Add passport details | G85: International | I85: (before check-in) | J85: Asks for passport details once, stores securely | K85: StateCard, Handoff | L85: Document data held by the bank, tokenised | N85: 4 | O85: 3 | P85: 4 | R85: =IF(OR(N85="",P85=""),"",ROUND(N85*O85/P85,1)) -> 3 | S85: =IF(R85="","",IF(Q85="Y",1,IF(P85>='Read me'!$B$16,3,IF(AND(R85>='Read me'!$B$14,P85<='Read me'!$B$15),1,2)))) -> 3
A86: FL-06-003 | B86: Flights | C86: FL-06 | D86: Check-in and day of travel | E86: Before | F86: Check visa needs | G86: International | I86: Do I need a visa for Dubai? | J86: Gives the official source and the rule for their passport | K86: Answer | L86: Visa info from an official source only; always linked | M86: Rules differ by passport and destination; e-visas common for IN, AE | N86: 3 | O86: 4 | P86: 4 | R86: =IF(OR(N86="",P86=""),"",ROUND(N86*O86/P86,1)) -> 3 | S86: =IF(R86="","",IF(Q86="Y",1,IF(P86>='Read me'!$B$16,3,IF(AND(R86>='Read me'!$B$14,P86<='Read me'!$B$15),1,2)))) -> 3
A87: FL-06-004 | B87: Flights | C87: FL-06 | D87: Check-in and day of travel | E87: Before | F87: Check ID needs | G87: Domestic | I87: What ID do I need? | J87: Says what the airline accepts | K87: Answer | L87: From the airline | M87: India: photo ID, DigiYatra optional. Malaysia: MyKad for domestic; Sabah and Sarawak have their own entry rules | N87: 3 | O87: 3 | P87: 3 | R87: =IF(OR(N87="",P87=""),"",ROUND(N87*O87/P87,1)) -> 3 | S87: =IF(R87="","",IF(Q87="Y",1,IF(P87>='Read me'!$B$16,3,IF(AND(R87>='Read me'!$B$14,P87<='Read me'!$B$15),1,2)))) -> 2
A88: FL-06-005 | B88: Flights | C88: FL-06 | D88: Check-in and day of travel | E88: Before | F88: Share the trip | G88: Family | I88: Send the plan to my wife | J88: Shares a read-only trip link | K88: SendTo, TripFolder | L88: Sharing needs the customer's yes | N88: 3 | O88: 2 | P88: 2 | R88: =IF(OR(N88="",P88=""),"",ROUND(N88*O88/P88,1)) -> 3 | S88: =IF(R88="","",IF(Q88="Y",1,IF(P88>='Read me'!$B$16,3,IF(AND(R88>='Read me'!$B$14,P88<='Read me'!$B$15),1,2)))) -> 2
A89: FL-06-006 | B89: Flights | C89: FL-06 | D89: Check-in and day of travel | E89: Before | F89: Get reminded | G89: Leaving time | I89: (automatic) | J89: Tells them when to leave for the airport | K89: StickyNote, Toast | L89: Traffic data | N89: 4 | O89: 3 | P89: 1 | R89: =IF(OR(N89="",P89=""),"",ROUND(N89*O89/P89,1)) -> 12 | S89: =IF(R89="","",IF(Q89="Y",1,IF(P89>='Read me'!$B$16,3,IF(AND(R89>='Read me'!$B$14,P89<='Read me'!$B$15),1,2)))) -> 1
A90: FL-06-007 | B90: Flights | C90: FL-06 | D90: Check-in and day of travel | E90: Before | F90: Check the weather | G90: Packing | I90: What's the weather in Lisbon? | J90: Weather for the trip dates | K90: Answer | N90: 3 | O90: 1 | P90: 1 | R90: =IF(OR(N90="",P90=""),"",ROUND(N90*O90/P90,1)) -> 3 | S90: =IF(R90="","",IF(Q90="Y",1,IF(P90>='Read me'!$B$16,3,IF(AND(R90>='Read me'!$B$14,P90<='Read me'!$B$15),1,2)))) -> 2
A91: FL-06-008 | B91: Flights | C91: FL-06 | D91: Check-in and day of travel | E91: Before | F91: Currency and card abroad | G91: Spending | I91: Will my card work in Portugal? | J91: Explains foreign fees on this card | K91: BenefitRow, Answer | L91: Fees from the bank | N91: 3 | O91: 3 | P91: 2 | R91: =IF(OR(N91="",P91=""),"",ROUND(N91*O91/P91,1)) -> 4.5 | S91: =IF(R91="","",IF(Q91="Y",1,IF(P91>='Read me'!$B$16,3,IF(AND(R91>='Read me'!$B$14,P91<='Read me'!$B$15),1,2)))) -> 2
A92: FL-06-009 | B92: Flights | C92: FL-06 | D92: Check-in and day of travel | E92: Before | F92: Add a frequent flyer number | G92: Earn miles | I92: Add my miles number | J92: Adds it to the booking | K92: Toast | L92: Number checked by the airline | N92: 3 | O92: 2 | P92: 1 | R92: =IF(OR(N92="",P92=""),"",ROUND(N92*O92/P92,1)) -> 6 | S92: =IF(R92="","",IF(Q92="Y",1,IF(P92>='Read me'!$B$16,3,IF(AND(R92>='Read me'!$B$14,P92<='Read me'!$B$15),1,2)))) -> 1
A93: FL-06-010 | B93: Flights | C93: FL-06 | D93: Check-in and day of travel | E93: Before | F93: Travelling during a religious period | G93: Ramadan | I93: Are there meals on my flight during Ramadan? | J93: Explains the airline's service and airport opening hours | K93: Answer | L93: From airline and airport | M93: Relevant in AE, MY and IN; dates move each year | N93: 1 | O93: 2 | P93: 2 | R93: =IF(OR(N93="",P93=""),"",ROUND(N93*O93/P93,1)) -> 1 | S93: =IF(R93="","",IF(Q93="Y",1,IF(P93>='Read me'!$B$16,3,IF(AND(R93>='Read me'!$B$14,P93<='Read me'!$B$15),1,2)))) -> 2
A94: FL-06-011 | B94: Flights | C94: FL-06 | D94: Check-in and day of travel | E94: Before | F94: Check in | G94: Online | H94: Check-in failed | I94: (automatic) | J94: Says online check-in didn't work and why, and what to do | K94: StateCard, Toast | L94: Airline check-in rules | N94: 2 | O94: 3 | P94: 3 | Q94: Y | R94: =IF(OR(N94="",P94=""),"",ROUND(N94*O94/P94,1)) -> 2 | S94: =IF(R94="","",IF(Q94="Y",1,IF(P94>='Read me'!$B$16,3,IF(AND(R94>='Read me'!$B$14,P94<='Read me'!$B$15),1,2)))) -> 1
A95: FL-06-012 | B95: Flights | C95: FL-06 | D95: Check-in and day of travel | E95: During | F95: Show boarding pass | G95: At the airport | I95: Boarding pass | J95: Shows it, bright and offline | K95: BoardingPass | L95: Available offline | N95: 5 | O95: 4 | P95: 1 | Q95: Y | R95: =IF(OR(N95="",P95=""),"",ROUND(N95*O95/P95,1)) -> 20 | S95: =IF(R95="","",IF(Q95="Y",1,IF(P95>='Read me'!$B$16,3,IF(AND(R95>='Read me'!$B$14,P95<='Read me'!$B$15),1,2)))) -> 1
A96: FL-06-013 | B96: Flights | C96: FL-06 | D96: Check-in and day of travel | E96: During | F96: Track the flight | G96: Live | I96: Is my flight on time? | J96: Live status, gate, times | K96: FlightTracker, Status | L96: Status from the airline feed | N96: 5 | O96: 4 | P96: 2 | Q96: Y | R96: =IF(OR(N96="",P96=""),"",ROUND(N96*O96/P96,1)) -> 10 | S96: =IF(R96="","",IF(Q96="Y",1,IF(P96>='Read me'!$B$16,3,IF(AND(R96>='Read me'!$B$14,P96<='Read me'!$B$15),1,2)))) -> 1
A97: FL-06-014 | B97: Flights | C97: FL-06 | D97: Check-in and day of travel | E97: During | F97: Gate change | G97: Live | H97: Gate moved | I97: (Gratifi starts it) | J97: Push and card with the new gate and walk time | K97: FlightTracker, Toast | N97: 3 | O97: 3 | P97: 2 | R97: =IF(OR(N97="",P97=""),"",ROUND(N97*O97/P97,1)) -> 4.5 | S97: =IF(R97="","",IF(Q97="Y",1,IF(P97>='Read me'!$B$16,3,IF(AND(R97>='Read me'!$B$14,P97<='Read me'!$B$15),1,2)))) -> 2
A98: FL-06-015 | B98: Flights | C98: FL-06 | D98: Check-in and day of travel | E98: During | F98: Find the lounge | G98: At the airport | I98: Where's the lounge? | J98: Lounge pass with directions | K98: LoungePass | N98: 3 | O98: 3 | P98: 1 | R98: =IF(OR(N98="",P98=""),"",ROUND(N98*O98/P98,1)) -> 9 | S98: =IF(R98="","",IF(Q98="Y",1,IF(P98>='Read me'!$B$16,3,IF(AND(R98>='Read me'!$B$14,P98<='Read me'!$B$15),1,2)))) -> 1
A99: FL-06-016 | B99: Flights | C99: FL-06 | D99: Check-in and day of travel | E99: During | F99: Pick up someone | G99: Arrivals | I99: When does Sam land? | J99: Tracks a shared flight | K99: FlightTracker | L99: Only flights shared with them | N99: 2 | O99: 2 | P99: 2 | R99: =IF(OR(N99="",P99=""),"",ROUND(N99*O99/P99,1)) -> 2 | S99: =IF(R99="","",IF(Q99="Y",1,IF(P99>='Read me'!$B$16,3,IF(AND(R99>='Read me'!$B$14,P99<='Read me'!$B$15),1,2)))) -> 2
A100: FL-06-017 | B100: Flights | C100: FL-06 | D100: Check-in and day of travel | E100: During | F100: Security wait times | G100: At the airport | I100: How long is security? | J100: Shows the airport's published wait if available | K100: Answer | L100: Only published data | N100: 2 | O100: 2 | P100: 1 | R100: =IF(OR(N100="",P100=""),"",ROUND(N100*O100/P100,1)) -> 4 | S100: =IF(R100="","",IF(Q100="Y",1,IF(P100>='Read me'!$B$16,3,IF(AND(R100>='Read me'!$B$14,P100<='Read me'!$B$15),1,2)))) -> 2
...

Sheet Kit gaps
A1: Block to build | B1: Use cases needing it | C1: Items | D1: Also called
A2: ClaimTracker | B2: =COUNTIF('Use cases'!$K$2:$K$6000,"*NEW: ClaimTracker,*")+COUNTIF('Use cases'!$K$2:$K$6000,"*NEW: ClaimTracker")+COUNTIF('Use cases'!$K$2:$K$6000,"*NEW: ClaimTracker *") -> 75 | C2: BE-02, BE-03, BE-04, BE-05, BE-06, BE-07, BS-03, BS-04, BS-05, BS-07, CO-01, CO-02, CO-03, CO-04, DN-04, EN-03, EN-05, EN-06, SH-05, ST-05, TD-01, TD-03 | D2: RequestTracker, ApplicationTracker, MissingPointsClaim
A3: ServiceCard | B3: =COUNTIF('Use cases'!$K$2:$K$6000,"*NEW: ServiceCard,*")+COUNTIF('Use cases'!$K$2:$K$6000,"*NEW: ServiceCard")+COUNTIF('Use cases'!$K$2:$K$6000,"*NEW: ServiceCard *") -> 29 | C3: AP-01, AP-02, AP-04, AP-05, AP-06
A4: SubscriptionCard | B4: =COUNTIF('Use cases'!$K$2:$K$6000,"*NEW: SubscriptionCard,*")+COUNTIF('Use cases'!$K$2:$K$6000,"*NEW: SubscriptionCard")+COUNTIF('Use cases'!$K$2:$K$6000,"*NEW: SubscriptionCard *") -> 28 | C4: SB-01, SB-02, SB-03, SB-04, SB-05, SB-06
A5: Upload | B5: =COUNTIF('Use cases'!$K$2:$K$6000,"*NEW: Upload,*")+COUNTIF('Use cases'!$K$2:$K$6000,"*NEW: Upload")+COUNTIF('Use cases'!$K$2:$K$6000,"*NEW: Upload *") -> 26 | C5: BE-02, BE-03, BE-04, BS-08, GC-05, QC-01, QC-02, QC-03, SH-02, SH-03, SH-06, SH-07, TD-01, TD-03 | D5: PhotoUpload, EvidenceUpload, DocumentUpload, ReceiptCapture
A6: Basket | B6: =COUNTIF('Use cases'!$K$2:$K$6000,"*NEW: Basket,*")+COUNTIF('Use cases'!$K$2:$K$6000,"*NEW: Basket")+COUNTIF('Use cases'!$K$2:$K$6000,"*NEW: Basket *") -> 25 | C6: QC-01, QC-02, QC-03, SH-03
A7: CardControls | B7: =COUNTIF('Use cases'!$K$2:$K$6000,"*NEW: CardControls,*")+COUNTIF('Use cases'!$K$2:$K$6000,"*NEW: CardControls")+COUNTIF('Use cases'!$K$2:$K$6000,"*NEW: CardControls *") -> 25 | C7: BS-04, BS-06, BS-08
A8: RestaurantCard | B8: =COUNTIF('Use cases'!$K$2:$K$6000,"*NEW: RestaurantCard,*")+COUNTIF('Use cases'!$K$2:$K$6000,"*NEW: RestaurantCard")+COUNTIF('Use cases'!$K$2:$K$6000,"*NEW: RestaurantCard *") -> 21 | C8: CO-01, DN-01, DN-02, ET-04, QC-03
A9: Map | B9: =COUNTIF('Use cases'!$K$2:$K$6000,"*NEW: Map,*")+COUNTIF('Use cases'!$K$2:$K$6000,"*NEW: Map")+COUNTIF('Use cases'!$K$2:$K$6000,"*NEW: Map *") -> 18 | C9: AP-01, AP-04, AP-05, AP-06, DN-01, DN-03, EX-01, EX-02, GT-02, GT-04, ST-01 | D9: MapView, TerminalMap
A10: VoucherCode | B10: =COUNTIF('Use cases'!$K$2:$K$6000,"*NEW: VoucherCode,*")+COUNTIF('Use cases'!$K$2:$K$6000,"*NEW: VoucherCode")+COUNTIF('Use cases'!$K$2:$K$6000,"*NEW: VoucherCode *") -> 17 | C10: GC-01, GC-02, GC-04, SB-01, SB-02, SB-03
A11: DeliveryTracker | B11: =COUNTIF('Use cases'!$K$2:$K$6000,"*NEW: DeliveryTracker,*")+COUNTIF('Use cases'!$K$2:$K$6000,"*NEW: DeliveryTracker")+COUNTIF('Use cases'!$K$2:$K$6000,"*NEW: DeliveryTracker *") -> 16 | C11: CO-02, QC-01, QC-02, QC-03, SH-06, SH-07
A12: RightsGuide | B12: =COUNTIF('Use cases'!$K$2:$K$6000,"*NEW: RightsGuide,*")+COUNTIF('Use cases'!$K$2:$K$6000,"*NEW: RightsGuide")+COUNTIF('Use cases'!$K$2:$K$6000,"*NEW: RightsGuide *") -> 16 | C12: BE-07
A13: AlertSettings | B13: =COUNTIF('Use cases'!$K$2:$K$6000,"*NEW: AlertSettings,*")+COUNTIF('Use cases'!$K$2:$K$6000,"*NEW: AlertSettings")+COUNTIF('Use cases'!$K$2:$K$6000,"*NEW: AlertSettings *") -> 16 | C13: EN-01, EN-02 | D13: QuietHours
A14: TicketWallet | B14: =COUNTIF('Use cases'!$K$2:$K$6000,"*NEW: TicketWallet,*")+COUNTIF('Use cases'!$K$2:$K$6000,"*NEW: TicketWallet")+COUNTIF('Use cases'!$K$2:$K$6000,"*NEW: TicketWallet *") -> 14 | C14: AP-02, AP-06, DN-03, ET-01, ET-02, ET-03, ET-05, EX-01, EX-03 | D14: ServicePass
A15: ConciergeBrief | B15: =COUNTIF('Use cases'!$K$2:$K$6000,"*NEW: ConciergeBrief,*")+COUNTIF('Use cases'!$K$2:$K$6000,"*NEW: ConciergeBrief")+COUNTIF('Use cases'!$K$2:$K$6000,"*NEW: ConciergeBrief *") -> 14 | C15: CO-01, CO-02, CO-03, CO-04
A16: CharityCard | B16: =COUNTIF('Use cases'!$K$2:$K$6000,"*NEW: CharityCard,*")+COUNTIF('Use cases'!$K$2:$K$6000,"*NEW: CharityCard")+COUNTIF('Use cases'!$K$2:$K$6000,"*NEW: CharityCard *") -> 14 | C16: CH-01, CH-02, CH-03
A17: GreeterCard | B17: =COUNTIF('Use cases'!$K$2:$K$6000,"*NEW: GreeterCard,*")+COUNTIF('Use cases'!$K$2:$K$6000,"*NEW: GreeterCard")+COUNTIF('Use cases'!$K$2:$K$6000,"*NEW: GreeterCard *") -> 13 | C17: AP-01, AP-04, AP-06, GT-02
A18: PolicyCard | B18: =COUNTIF('Use cases'!$K$2:$K$6000,"*NEW: PolicyCard,*")+COUNTIF('Use cases'!$K$2:$K$6000,"*NEW: PolicyCard")+COUNTIF('Use cases'!$K$2:$K$6000,"*NEW: PolicyCard *") -> 13 | C18: TD-03
A19: InstalmentPlan | B19: =COUNTIF('Use cases'!$K$2:$K$6000,"*NEW: InstalmentPlan,*")+COUNTIF('Use cases'!$K$2:$K$6000,"*NEW: InstalmentPlan")+COUNTIF('Use cases'!$K$2:$K$6000,"*NEW: InstalmentPlan *") -> 12 | C19: BE-06, BS-03, BS-05, CO-04, SH-01, SH-03 | D19: PlanTable, PaymentSchedule
A20: ChallengeCard | B20: =COUNTIF('Use cases'!$K$2:$K$6000,"*NEW: ChallengeCard,*")+COUNTIF('Use cases'!$K$2:$K$6000,"*NEW: ChallengeCard")+COUNTIF('Use cases'!$K$2:$K$6000,"*NEW: ChallengeCard *") -> 12 | C20: EN-03
A21: SupportLines | B21: =COUNTIF('Use cases'!$K$2:$K$6000,"*NEW: SupportLines,*")+COUNTIF('Use cases'!$K$2:$K$6000,"*NEW: SupportLines")+COUNTIF('Use cases'!$K$2:$K$6000,"*NEW: SupportLines *") -> 12 | C21: BS-04, BS-05, BS-06, BS-07, BS-08
A22: TrainCard | B22: =COUNTIF('Use cases'!$K$2:$K$6000,"*NEW: TrainCard,*")+COUNTIF('Use cases'!$K$2:$K$6000,"*NEW: TrainCard")+COUNTIF('Use cases'!$K$2:$K$6000,"*NEW: TrainCard *") -> 11 | C22: GT-03
A23: VenueSeatMap | B23: =COUNTIF('Use cases'!$K$2:$K$6000,"*NEW: VenueSeatMap,*")+COUNTIF('Use cases'!$K$2:$K$6000,"*NEW: VenueSeatMap")+COUNTIF('Use cases'!$K$2:$K$6000,"*NEW: VenueSeatMap *") -> 11 | C23: ET-01, ET-02, ET-03, ET-04, ET-05
A24: ReturnFlow | B24: =COUNTIF('Use cases'!$K$2:$K$6000,"*NEW: ReturnFlow,*")+COUNTIF('Use cases'!$K$2:$K$6000,"*NEW: ReturnFlow")+COUNTIF('Use cases'!$K$2:$K$6000,"*NEW: ReturnFlow *") -> 11 | C24: SH-02, SH-03, SH-06, SH-07
A25: IssuePicker | B25: =COUNTIF('Use cases'!$K$2:$K$6000,"*NEW: IssuePicker,*")+COUNTIF('Use cases'!$K$2:$K$6000,"*NEW: IssuePicker")+COUNTIF('Use cases'!$K$2:$K$6000,"*NEW: IssuePicker *") -> 10 | C25: QC-01, QC-02, QC-03, SH-07
A26: RiskDisclosure | B26: =COUNTIF('Use cases'!$K$2:$K$6000,"*NEW: RiskDisclosure,*")+COUNTIF('Use cases'!$K$2:$K$6000,"*NEW: RiskDisclosure")+COUNTIF('Use cases'!$K$2:$K$6000,"*NEW: RiskDisclosure *") -> 10 | C26: IV-01, IV-02, IV-03
A27: MoneyBackRoute | B27: =COUNTIF('Use cases'!$K$2:$K$6000,"*NEW: MoneyBackRoute,*")+COUNTIF('Use cases'!$K$2:$K$6000,"*NEW: MoneyBackRoute")+COUNTIF('Use cases'!$K$2:$K$6000,"*NEW: MoneyBackRoute *") -> 10 | C27: BE-03
A28: AddressPicker | B28: =COUNTIF('Use cases'!$K$2:$K$6000,"*NEW: AddressPicker,*")+COUNTIF('Use cases'!$K$2:$K$6000,"*NEW: AddressPicker")+COUNTIF('Use cases'!$K$2:$K$6000,"*NEW: AddressPicker *") -> 9 | C28: QC-01, QC-02, SB-04, SH-03, SH-04, SH-06, SH-07
A29: MemoryList | B29: =COUNTIF('Use cases'!$K$2:$K$6000,"*NEW: MemoryList,*")+COUNTIF('Use cases'!$K$2:$K$6000,"*NEW: MemoryList")+COUNTIF('Use cases'!$K$2:$K$6000,"*NEW: MemoryList *") -> 8 | C29: BS-01, EN-04, EN-06
A30: ReferralCard | B30: =COUNTIF('Use cases'!$K$2:$K$6000,"*NEW: ReferralCard,*")+COUNTIF('Use cases'!$K$2:$K$6000,"*NEW: ReferralCard")+COUNTIF('Use cases'!$K$2:$K$6000,"*NEW: ReferralCard *") -> 8 | C30: EN-05
A31: StatementCard | B31: =COUNTIF('Use cases'!$K$2:$K$6000,"*NEW: StatementCard,*")+COUNTIF('Use cases'!$K$2:$K$6000,"*NEW: StatementCard")+COUNTIF('Use cases'!$K$2:$K$6000,"*NEW: StatementCard *") -> 8 | C31: BS-01, BS-03
A32: CardholderList | B32: =COUNTIF('Use cases'!$K$2:$K$6000,"*NEW: CardholderList,*")+COUNTIF('Use cases'!$K$2:$K$6000,"*NEW: CardholderList")+COUNTIF('Use cases'!$K$2:$K$6000,"*NEW: CardholderList *") -> 8 | C32: BS-04, BS-08
A33: EarnTracker | B33: =COUNTIF('Use cases'!$K$2:$K$6000,"*NEW: EarnTracker,*")+COUNTIF('Use cases'!$K$2:$K$6000,"*NEW: EarnTracker")+COUNTIF('Use cases'!$K$2:$K$6000,"*NEW: EarnTracker *") -> 7 | C33: SH-05
A34: HoldingsCard | B34: =COUNTIF('Use cases'!$K$2:$K$6000,"*NEW: HoldingsCard,*")+COUNTIF('Use cases'!$K$2:$K$6000,"*NEW: HoldingsCard")+COUNTIF('Use cases'!$K$2:$K$6000,"*NEW: HoldingsCard *") -> 7 | C34: IV-01, IV-02, IV-03
A35: BalanceCard | B35: =COUNTIF('Use cases'!$K$2:$K$6000,"*NEW: BalanceCard,*")+COUNTIF('Use cases'!$K$2:$K$6000,"*NEW: BalanceCard")+COUNTIF('Use cases'!$K$2:$K$6000,"*NEW: BalanceCard *") -> 7 | C35: BS-02, BS-06
A36: SpendBreakdown | B36: =COUNTIF('Use cases'!$K$2:$K$6000,"*NEW: SpendBreakdown,*")+COUNTIF('Use cases'!$K$2:$K$6000,"*NEW: SpendBreakdown")+COUNTIF('Use cases'!$K$2:$K$6000,"*NEW: SpendBreakdown *") -> 7 | C36: BS-02, BS-03, BS-06, BS-08
A37: MenuCard | B37: =COUNTIF('Use cases'!$K$2:$K$6000,"*NEW: MenuCard,*")+COUNTIF('Use cases'!$K$2:$K$6000,"*NEW: MenuCard")+COUNTIF('Use cases'!$K$2:$K$6000,"*NEW: MenuCard *") -> 6 | C37: DN-01, DN-02, QC-03 | D37: MenuItemOptions
A38: VariantPicker | B38: =COUNTIF('Use cases'!$K$2:$K$6000,"*NEW: VariantPicker,*")+COUNTIF('Use cases'!$K$2:$K$6000,"*NEW: VariantPicker")+COUNTIF('Use cases'!$K$2:$K$6000,"*NEW: VariantPicker *") -> 6 | C38: SH-01, SH-06, SH-07
A39: FxRate | B39: =COUNTIF('Use cases'!$K$2:$K$6000,"*NEW: FxRate,*")+COUNTIF('Use cases'!$K$2:$K$6000,"*NEW: FxRate")+COUNTIF('Use cases'!$K$2:$K$6000,"*NEW: FxRate *") -> 6 | C39: TD-02
A40: EsimPlan | B40: =COUNTIF('Use cases'!$K$2:$K$6000,"*NEW: EsimPlan,*")+COUNTIF('Use cases'!$K$2:$K$6000,"*NEW: EsimPlan")+COUNTIF('Use cases'!$K$2:$K$6000,"*NEW: EsimPlan *") -> 6 | C40: TD-04
A41: DocumentWallet | B41: =COUNTIF('Use cases'!$K$2:$K$6000,"*NEW: DocumentWallet,*")+COUNTIF('Use cases'!$K$2:$K$6000,"*NEW: DocumentWallet")+COUNTIF('Use cases'!$K$2:$K$6000,"*NEW: DocumentWallet *") -> 6 | C41: TD-05
A42: RideTracker | B42: =COUNTIF('Use cases'!$K$2:$K$6000,"*NEW: RideTracker,*")+COUNTIF('Use cases'!$K$2:$K$6000,"*NEW: RideTracker")+COUNTIF('Use cases'!$K$2:$K$6000,"*NEW: RideTracker *") -> 5 | C42: GT-01, GT-02
A43: CarCard | B43: =COUNTIF('Use cases'!$K$2:$K$6000,"*NEW: CarCard,*")+COUNTIF('Use cases'!$K$2:$K$6000,"*NEW: CarCard")+COUNTIF('Use cases'!$K$2:$K$6000,"*NEW: CarCard *") -> 5 | C43: GT-04
A44: GiftMessage | B44: =COUNTIF('Use cases'!$K$2:$K$6000,"*NEW: GiftMessage,*")+COUNTIF('Use cases'!$K$2:$K$6000,"*NEW: GiftMessage")+COUNTIF('Use cases'!$K$2:$K$6000,"*NEW: GiftMessage *") -> 5 | C44: GC-03, SB-04, SH-02
A45: RecipientList | B45: =COUNTIF('Use cases'!$K$2:$K$6000,"*NEW: RecipientList,*")+COUNTIF('Use cases'!$K$2:$K$6000,"*NEW: RecipientList")+COUNTIF('Use cases'!$K$2:$K$6000,"*NEW: RecipientList *") -> 5 | C45: GC-03, GC-05
A46: MilestoneTracker | B46: =COUNTIF('Use cases'!$K$2:$K$6000,"*NEW: MilestoneTracker,*")+COUNTIF('Use cases'!$K$2:$K$6000,"*NEW: MilestoneTracker")+COUNTIF('Use cases'!$K$2:$K$6000,"*NEW: MilestoneTracker *") -> 5 | C46: PM-06
A47: PriceChart | B47: =COUNTIF('Use cases'!$K$2:$K$6000,"*NEW: PriceChart,*")+COUNTIF('Use cases'!$K$2:$K$6000,"*NEW: PriceChart")+COUNTIF('Use cases'!$K$2:$K$6000,"*NEW: PriceChart *") -> 5 | C47: IV-01, IV-02, IV-03
A48: StreakTracker | B48: =COUNTIF('Use cases'!$K$2:$K$6000,"*NEW: StreakTracker,*")+COUNTIF('Use cases'!$K$2:$K$6000,"*NEW: StreakTracker")+COUNTIF('Use cases'!$K$2:$K$6000,"*NEW: StreakTracker *") -> 5 | C48: EN-03
A49: DirectDebitCard | B49: =COUNTIF('Use cases'!$K$2:$K$6000,"*NEW: DirectDebitCard,*")+COUNTIF('Use cases'!$K$2:$K$6000,"*NEW: DirectDebitCard")+COUNTIF('Use cases'!$K$2:$K$6000,"*NEW: DirectDebitCard *") -> 5 | C49: BS-02, BS-05
A50: ApprovalPrompt | B50: =COUNTIF('Use cases'!$K$2:$K$6000,"*NEW: ApprovalPrompt,*")+COUNTIF('Use cases'!$K$2:$K$6000,"*NEW: ApprovalPrompt")+COUNTIF('Use cases'!$K$2:$K$6000,"*NEW: ApprovalPrompt *") -> 5 | C50: BS-04, BS-06
A51: LoyaltyNumber | B51: =COUNTIF('Use cases'!$K$2:$K$6000,"*NEW: LoyaltyNumber,*")+COUNTIF('Use cases'!$K$2:$K$6000,"*NEW: LoyaltyNumber")+COUNTIF('Use cases'!$K$2:$K$6000,"*NEW: LoyaltyNumber *") -> 4 | C51: ST-06
A52: SubstitutionPicker | B52: =COUNTIF('Use cases'!$K$2:$K$6000,"*NEW: SubstitutionPicker,*")+COUNTIF('Use cases'!$K$2:$K$6000,"*NEW: SubstitutionPicker")+COUNTIF('Use cases'!$K$2:$K$6000,"*NEW: SubstitutionPicker *") -> 4 | C52: QC-01, QC-02
A53: SizePicker | B53: =COUNTIF('Use cases'!$K$2:$K$6000,"*NEW: SizePicker,*")+COUNTIF('Use cases'!$K$2:$K$6000,"*NEW: SizePicker")+COUNTIF('Use cases'!$K$2:$K$6000,"*NEW: SizePicker *") -> 4 | C53: SH-02
A54: ProgrammeLink | B54: =COUNTIF('Use cases'!$K$2:$K$6000,"*NEW: ProgrammeLink,*")+COUNTIF('Use cases'!$K$2:$K$6000,"*NEW: ProgrammeLink")+COUNTIF('Use cases'!$K$2:$K$6000,"*NEW: ProgrammeLink *") -> 4 | C54: PM-01, PM-02
A55: KycCheck | B55: =COUNTIF('Use cases'!$K$2:$K$6000,"*NEW: KycCheck,*")+COUNTIF('Use cases'!$K$2:$K$6000,"*NEW: KycCheck")+COUNTIF('Use cases'!$K$2:$K$6000,"*NEW: KycCheck *") -> 4 | C55: IV-01, IV-02, IV-03, TD-02
A56: TaxSummary | B56: =COUNTIF('Use cases'!$K$2:$K$6000,"*NEW: TaxSummary,*")+COUNTIF('Use cases'!$K$2:$K$6000,"*NEW: TaxSummary")+COUNTIF('Use cases'!$K$2:$K$6000,"*NEW: TaxSummary *") -> 4 | C56: CH-03
A57: SecureCardDetails | B57: =COUNTIF('Use cases'!$K$2:$K$6000,"*NEW: SecureCardDetails,*")+COUNTIF('Use cases'!$K$2:$K$6000,"*NEW: SecureCardDetails")+COUNTIF('Use cases'!$K$2:$K$6000,"*NEW: SecureCardDetails *") -> 4 | C57: BS-04, BS-06
A58: AmountSlider | B58: =COUNTIF('Use cases'!$K$2:$K$6000,"*NEW: AmountSlider,*")+COUNTIF('Use cases'!$K$2:$K$6000,"*NEW: AmountSlider")+COUNTIF('Use cases'!$K$2:$K$6000,"*NEW: AmountSlider *") -> 4 | C58: BS-05
A59: ReviewSummary | B59: =COUNTIF('Use cases'!$K$2:$K$6000,"*NEW: ReviewSummary,*")+COUNTIF('Use cases'!$K$2:$K$6000,"*NEW: ReviewSummary")+COUNTIF('Use cases'!$K$2:$K$6000,"*NEW: ReviewSummary *") -> 3 | C59: SH-01, SH-06, ST-01 | D59: SellerRating
A60: Queue | B60: =COUNTIF('Use cases'!$K$2:$K$6000,"*NEW: Queue,*")+COUNTIF('Use cases'!$K$2:$K$6000,"*NEW: Queue")+COUNTIF('Use cases'!$K$2:$K$6000,"*NEW: Queue *") -> 3 | C60: DN-04, ET-02
A61: StockAlert | B61: =COUNTIF('Use cases'!$K$2:$K$6000,"*NEW: StockAlert,*")+COUNTIF('Use cases'!$K$2:$K$6000,"*NEW: StockAlert")+COUNTIF('Use cases'!$K$2:$K$6000,"*NEW: StockAlert *") -> 3 | C61: SH-01, SH-02, SH-03
A62: WarrantyCard | B62: =COUNTIF('Use cases'!$K$2:$K$6000,"*NEW: WarrantyCard,*")+COUNTIF('Use cases'!$K$2:$K$6000,"*NEW: WarrantyCard")+COUNTIF('Use cases'!$K$2:$K$6000,"*NEW: WarrantyCard *") -> 3 | C62: SH-03, SH-07
A63: GiftCardWallet | B63: =COUNTIF('Use cases'!$K$2:$K$6000,"*NEW: GiftCardWallet,*")+COUNTIF('Use cases'!$K$2:$K$6000,"*NEW: GiftCardWallet")+COUNTIF('Use cases'!$K$2:$K$6000,"*NEW: GiftCardWallet *") -> 3 | C63: GC-02, GC-04
A64: RoomsAndGuests | B64: =COUNTIF('Use cases'!$K$2:$K$6000,"*NEW: RoomsAndGuests,*")+COUNTIF('Use cases'!$K$2:$K$6000,"*NEW: RoomsAndGuests")+COUNTIF('Use cases'!$K$2:$K$6000,"*NEW: RoomsAndGuests *") -> 2 | C64: ST-01, ST-02
A65: PhotoGallery | B65: =COUNTIF('Use cases'!$K$2:$K$6000,"*NEW: PhotoGallery,*")+COUNTIF('Use cases'!$K$2:$K$6000,"*NEW: PhotoGallery")+COUNTIF('Use cases'!$K$2:$K$6000,"*NEW: PhotoGallery *") -> 2 | C65: ST-01, ST-02
A66: HouseRules | B66: =COUNTIF('Use cases'!$K$2:$K$6000,"*NEW: HouseRules,*")+COUNTIF('Use cases'!$K$2:$K$6000,"*NEW: HouseRules")+COUNTIF('Use cases'!$K$2:$K$6000,"*NEW: HouseRules *") -> 2 | C66: ST-02
A67: CheckInInstructions | B67: =COUNTIF('Use cases'!$K$2:$K$6000,"*NEW: CheckInInstructions,*")+COUNTIF('Use cases'!$K$2:$K$6000,"*NEW: CheckInInstructions")+COUNTIF('Use cases'!$K$2:$K$6000,"*NEW: CheckInInstructions *") -> 2 | C67: ST-02
A68: DepositHold | B68: =COUNTIF('Use cases'!$K$2:$K$6000,"*NEW: DepositHold,*")+COUNTIF('Use cases'!$K$2:$K$6000,"*NEW: DepositHold")+COUNTIF('Use cases'!$K$2:$K$6000,"*NEW: DepositHold *") -> 2 | C68: GT-04, ST-02
A69: PackageBuilder | B69: =COUNTIF('Use cases'!$K$2:$K$6000,"*NEW: PackageBuilder,*")+COUNTIF('Use cases'!$K$2:$K$6000,"*NEW: PackageBuilder")+COUNTIF('Use cases'!$K$2:$K$6000,"*NEW: PackageBuilder *") -> 2 | C69: AP-05, ST-03
A70: TrainTicket | B70: =COUNTIF('Use cases'!$K$2:$K$6000,"*NEW: TrainTicket,*")+COUNTIF('Use cases'!$K$2:$K$6000,"*NEW: TrainTicket")+COUNTIF('Use cases'!$K$2:$K$6000,"*NEW: TrainTicket *") -> 2 | C70: GT-03
A71: DamageCheck | B71: =COUNTIF('Use cases'!$K$2:$K$6000,"*NEW: DamageCheck,*")+COUNTIF('Use cases'!$K$2:$K$6000,"*NEW: DamageCheck")+COUNTIF('Use cases'!$K$2:$K$6000,"*NEW: DamageCheck *") -> 2 | C71: GT-04
A72: DriverCard | B72: =COUNTIF('Use cases'!$K$2:$K$6000,"*NEW: DriverCard,*")+COUNTIF('Use cases'!$K$2:$K$6000,"*NEW: DriverCard")+COUNTIF('Use cases'!$K$2:$K$6000,"*NEW: DriverCard *") -> 2 | C72: GT-05
A73: Waiver | B73: =COUNTIF('Use cases'!$K$2:$K$6000,"*NEW: Waiver,*")+COUNTIF('Use cases'!$K$2:$K$6000,"*NEW: Waiver")+COUNTIF('Use cases'!$K$2:$K$6000,"*NEW: Waiver *") -> 2 | C73: EX-04, EX-05
A74: BulkOrder | B74: =COUNTIF('Use cases'!$K$2:$K$6000,"*NEW: BulkOrder,*")+COUNTIF('Use cases'!$K$2:$K$6000,"*NEW: BulkOrder")+COUNTIF('Use cases'!$K$2:$K$6000,"*NEW: BulkOrder *") -> 2 | C74: GC-05
A75: BulkReport | B75: =COUNTIF('Use cases'!$K$2:$K$6000,"*NEW: BulkReport,*")+COUNTIF('Use cases'!$K$2:$K$6000,"*NEW: BulkReport")+COUNTIF('Use cases'!$K$2:$K$6000,"*NEW: BulkReport *") -> 2 | C75: GC-05
A76: ExpiryTimeline | B76: =COUNTIF('Use cases'!$K$2:$K$6000,"*NEW: ExpiryTimeline,*")+COUNTIF('Use cases'!$K$2:$K$6000,"*NEW: ExpiryTimeline")+COUNTIF('Use cases'!$K$2:$K$6000,"*NEW: ExpiryTimeline *") -> 2 | C76: PM-04
A77: SuitabilityQuiz | B77: =COUNTIF('Use cases'!$K$2:$K$6000,"*NEW: SuitabilityQuiz,*")+COUNTIF('Use cases'!$K$2:$K$6000,"*NEW: SuitabilityQuiz")+COUNTIF('Use cases'!$K$2:$K$6000,"*NEW: SuitabilityQuiz *") -> 2 | C77: IV-02, IV-03
A78: VisaChecklist | B78: =COUNTIF('Use cases'!$K$2:$K$6000,"*NEW: VisaChecklist,*")+COUNTIF('Use cases'!$K$2:$K$6000,"*NEW: VisaChecklist")+COUNTIF('Use cases'!$K$2:$K$6000,"*NEW: VisaChecklist *") -> 2 | C78: TD-01
A79: EsimInstall | B79: =COUNTIF('Use cases'!$K$2:$K$6000,"*NEW: EsimInstall,*")+COUNTIF('Use cases'!$K$2:$K$6000,"*NEW: EsimInstall")+COUNTIF('Use cases'!$K$2:$K$6000,"*NEW: EsimInstall *") -> 2 | C79: TD-04
A80: PolicyDoc | B80: =COUNTIF('Use cases'!$K$2:$K$6000,"*NEW: PolicyDoc,*")+COUNTIF('Use cases'!$K$2:$K$6000,"*NEW: PolicyDoc")+COUNTIF('Use cases'!$K$2:$K$6000,"*NEW: PolicyDoc *") -> 2 | C80: BE-04
A81: RewardsLedger | B81: =COUNTIF('Use cases'!$K$2:$K$6000,"*NEW: RewardsLedger,*")+COUNTIF('Use cases'!$K$2:$K$6000,"*NEW: RewardsLedger")+COUNTIF('Use cases'!$K$2:$K$6000,"*NEW: RewardsLedger *") -> 2 | C81: BE-05, BE-06
A82: MembershipCard | B82: =COUNTIF('Use cases'!$K$2:$K$6000,"*NEW: MembershipCard,*")+COUNTIF('Use cases'!$K$2:$K$6000,"*NEW: MembershipCard")+COUNTIF('Use cases'!$K$2:$K$6000,"*NEW: MembershipCard *") -> 2 | C82: BE-05, EN-04
A83: ConversationHistory | B83: =COUNTIF('Use cases'!$K$2:$K$6000,"*NEW: ConversationHistory,*")+COUNTIF('Use cases'!$K$2:$K$6000,"*NEW: ConversationHistory")+COUNTIF('Use cases'!$K$2:$K$6000,"*NEW: ConversationHistory *") -> 2 | C83: BS-01
A84: SettingsList | B84: =COUNTIF('Use cases'!$K$2:$K$6000,"*NEW: SettingsList,*")+COUNTIF('Use cases'!$K$2:$K$6000,"*NEW: SettingsList")+COUNTIF('Use cases'!$K$2:$K$6000,"*NEW: SettingsList *") -> 2 | C84: BS-01
A85: ExportSheet | B85: =COUNTIF('Use cases'!$K$2:$K$6000,"*NEW: ExportSheet,*")+COUNTIF('Use cases'!$K$2:$K$6000,"*NEW: ExportSheet")+COUNTIF('Use cases'!$K$2:$K$6000,"*NEW: ExportSheet *") -> 2 | C85: BS-03, BS-08
A86: RepaymentCalculator | B86: =COUNTIF('Use cases'!$K$2:$K$6000,"*NEW: RepaymentCalculator,*")+COUNTIF('Use cases'!$K$2:$K$6000,"*NEW: RepaymentCalculator")+COUNTIF('Use cases'!$K$2:$K$6000,"*NEW: RepaymentCalculator *") -> 2 | C86: BS-05, BS-07
A87: CreditScoreCard | B87: =COUNTIF('Use cases'!$K$2:$K$6000,"*NEW: CreditScoreCard,*")+COUNTIF('Use cases'!$K$2:$K$6000,"*NEW: CreditScoreCard")+COUNTIF('Use cases'!$K$2:$K$6000,"*NEW: CreditScoreCard *") -> 2 | C87: BS-05
A88: ComplaintForm | B88: =COUNTIF('Use cases'!$K$2:$K$6000,"*NEW: ComplaintForm,*")+COUNTIF('Use cases'!$K$2:$K$6000,"*NEW: ComplaintForm")+COUNTIF('Use cases'!$K$2:$K$6000,"*NEW: ComplaintForm *") -> 2 | C88: BS-07
A89: Inclusions | B89: =COUNTIF('Use cases'!$K$2:$K$6000,"*NEW: Inclusions,*")+COUNTIF('Use cases'!$K$2:$K$6000,"*NEW: Inclusions")+COUNTIF('Use cases'!$K$2:$K$6000,"*NEW: Inclusions *") -> 1 | C89: ST-03
A90: DigitalKey | B90: =COUNTIF('Use cases'!$K$2:$K$6000,"*NEW: DigitalKey,*")+COUNTIF('Use cases'!$K$2:$K$6000,"*NEW: DigitalKey")+COUNTIF('Use cases'!$K$2:$K$6000,"*NEW: DigitalKey *") -> 1 | C90: ST-05
A91: RailSeatPicker | B91: =COUNTIF('Use cases'!$K$2:$K$6000,"*NEW: RailSeatPicker,*")+COUNTIF('Use cases'!$K$2:$K$6000,"*NEW: RailSeatPicker")+COUNTIF('Use cases'!$K$2:$K$6000,"*NEW: RailSeatPicker *") -> 1 | C91: GT-03
A92: RiderContact | B92: =COUNTIF('Use cases'!$K$2:$K$6000,"*NEW: RiderContact,*")+COUNTIF('Use cases'!$K$2:$K$6000,"*NEW: RiderContact")+COUNTIF('Use cases'!$K$2:$K$6000,"*NEW: RiderContact *") -> 1 | C92: QC-01
A93: TradeInQuote | B93: =COUNTIF('Use cases'!$K$2:$K$6000,"*NEW: TradeInQuote,*")+COUNTIF('Use cases'!$K$2:$K$6000,"*NEW: TradeInQuote")+COUNTIF('Use cases'!$K$2:$K$6000,"*NEW: TradeInQuote *") -> 1 | C93: SH-01
A94: SavingsGoal | B94: =COUNTIF('Use cases'!$K$2:$K$6000,"*NEW: SavingsGoal,*")+COUNTIF('Use cases'!$K$2:$K$6000,"*NEW: SavingsGoal")+COUNTIF('Use cases'!$K$2:$K$6000,"*NEW: SavingsGoal *") -> 1 | C94: SH-01
A95: ShadeFinder | B95: =COUNTIF('Use cases'!$K$2:$K$6000,"*NEW: ShadeFinder,*")+COUNTIF('Use cases'!$K$2:$K$6000,"*NEW: ShadeFinder")+COUNTIF('Use cases'!$K$2:$K$6000,"*NEW: ShadeFinder *") -> 1 | C95: SH-02
A96: OutboundLink | B96: =COUNTIF('Use cases'!$K$2:$K$6000,"*NEW: OutboundLink,*")+COUNTIF('Use cases'!$K$2:$K$6000,"*NEW: OutboundLink")+COUNTIF('Use cases'!$K$2:$K$6000,"*NEW: OutboundLink *") -> 1 | C96: SH-05
A97: GroupGift | B97: =COUNTIF('Use cases'!$K$2:$K$6000,"*NEW: GroupGift,*")+COUNTIF('Use cases'!$K$2:$K$6000,"*NEW: GroupGift")+COUNTIF('Use cases'!$K$2:$K$6000,"*NEW: GroupGift *") -> 1 | C97: GC-03
A98: PointsChart | B98: =COUNTIF('Use cases'!$K$2:$K$6000,"*NEW: PointsChart,*")+COUNTIF('Use cases'!$K$2:$K$6000,"*NEW: PointsChart")+COUNTIF('Use cases'!$K$2:$K$6000,"*NEW: PointsChart *") -> 1 | C98: PM-03
A99: GiftAidDeclaration | B99: =COUNTIF('Use cases'!$K$2:$K$6000,"*NEW: GiftAidDeclaration,*")+COUNTIF('Use cases'!$K$2:$K$6000,"*NEW: GiftAidDeclaration")+COUNTIF('Use cases'!$K$2:$K$6000,"*NEW: GiftAidDeclaration *") -> 1 | C99: CH-03
A100: DeviceCheck | B100: =COUNTIF('Use cases'!$K$2:$K$6000,"*NEW: DeviceCheck,*")+COUNTIF('Use cases'!$K$2:$K$6000,"*NEW: DeviceCheck")+COUNTIF('Use cases'!$K$2:$K$6000,"*NEW: DeviceCheck *") -> 1 | C100: TD-04
...

Sheet Markets
A1: Market | B1: Currency | C1: Number and date format | D1: How a payment is confirmed | E1: Automatic card payment is called | F1: Tax on fares | G1: Flight disruption rule | H1: Amounts set in law? | I1: Week starts | J1: Languages | K1: To confirm with the bank
A2: United Kingdom | B2: GBP £ | C2: en-GB · 1,234.50 · Fri 16 Oct | D2: Face ID in the bank app | E2: Direct Debit | F2: No VAT on flights; Air Passenger Duty in fares | G2: UK261 | H2: Yes: £220, £350, £520 by distance | I2: Monday | J2: English | K2: Point value; claims process
A3: Eurozone | B3: EUR € | C3: en-IE for English; local languages later | D3: Face ID in the bank app (strong customer authentication) | E3: direct debit | F3: International flights usually VAT-exempt; local ticket taxes (to confirm) | G3: EU261 (reform agreed June 2026, adoption pending) | H3: Yes: €250, €400, €600 by distance | I3: Monday | J3: English first; German, French, Spanish, Italian, Dutch to add | K3: Point value; which languages first
A4: India | B4: INR ₹ | C4: en-IN · lakh grouping (1,00,000) · Fri 16 Oct | D4: One-time code (other methods allowed under RBI authentication rules; to confirm per bank) | E4: auto-debit | F4: GST; GST invoice needs company GSTIN | G4: DGCA CAR Section 3, Series M, Part IV | H4: Yes, set by DGCA; legal team to confirm current amounts | I4: Sunday | J4: English first; Hindi next | K4: Point value; authentication method; EMI terms
A5: UAE | B5: AED | C5: en-AE and ar-AE (right to left) | D5: Face ID in the bank app | E5: direct debit | F5: VAT zero-rated on international flights (to confirm) | G5: Airline policy (legal team to confirm any GCAA rule) | H5: Legal team to confirm | I5: Monday | J5: English and Arabic (Arabic copy needs native sign-off) | K5: Point value; Arabic copy
A6: Singapore | B6: SGD S$ | C6: en-SG · 1,234.50 | D6: Face ID in the bank app | E6: GIRO | F6: GST zero-rated on international flights; airport levies | G6: Airline policy; no statutory scheme | H6: No | I6: Sunday | J6: English | K6: Point value
A7: Malaysia | B7: MYR RM | C7: en-MY · 1,234.50 | D7: Approval in the bank's app | E7: auto-debit | F7: No SST on fares (to confirm); departure levy on international flights | G7: Malaysian Aviation Consumer Protection Code 2016, enforced by CAAM | H7: Legal team to confirm | I7: Monday | J7: English first; Malay next | K7: Point value; app approval flow
A9: These settings live in the kit as data (Markets card). A new market is one more row here and one more entry in the kit; no redesign.

Sheet Grammar
A1: The grammar
A3: Stage | B3: Means | D3: Most common exceptions | G3: Most common constraints
A4: Discover | B4: Before they know what they want | D4: Cancelled by supplier | E4: 20 | G4: Plans changed | H4: 37
A5: Search | B5: Looking for options | D5: Payment declined | E5: 18 | G5: Enough points | H5: 32
A6: Choose | B6: Comparing and deciding | D6: Sold out | E6: 13 | G6: Not enough points | H6: 21
A7: Pay | B7: Money or points move | D7: Price rose | E7: 12 | G7: Date fixed | H7: 21
A8: Add-ons | B8: Extras on top of the main thing | D8: Not eligible | E8: 10 | G8: Unhappy | H8: 19
A9: Before | B9: Bought or booked, not yet used | D9: Supplier down | E9: 9 | G9: Premium | H9: 18
A10: During | B10: Using it now | D10: Fraud flag | E10: 8 | G10: Feedback | H10: 16
A11: Problem | B11: Something went wrong | D11: Not enough points | E11: 7 | G11: Accessibility | H11: 15
A12: After | B12: Done; refunds, reviews, repeats | D12: Declined | E12: 6 | G12: Card benefit | H12: 14
A13: Account | B13: The bank and points side | D13: Code rejected | E13: 6 | G13: Travelling with kids | H13: 13
D14: Late delivery | E14: 6 | G14: Changed mind | H14: 13
D15: Short of points | E15: 5 | G15: Abroad | H15: 13
D16: Wrong item | E16: 4 | G16: Business | H16: 12
D17: Expired | E17: 4 | G17: Budget in points | H17: 11
D18: No ticket yet | E18: 3 | G18: Group | H18: 9
D19: No-show | E19: 3 | G19: Points | H19: 9
D20: No supply | E20: 3 | G20: Delivered | H20: 9
D21: Damaged | E21: 3 | G21: Trip booked | H21: 8
D22: Not as described | E22: 3 | G22: Business card | H22: 8
D23: Fraud | E23: 3 | G23: Dates fixed | H23: 7
D24: Not allowed | E24: 3 | G24: Before travel | H24: 7
D25: Points expired | E25: 3 | G25: Landed | H25: 7
... D43: Missed each other | E43: 2 | G43: Repeat | H43: 5
