Workbook

Sheet Read me
A1: Gratifi: flight use cases
A2: Every thing a customer might want done with a flight, written as one row each, with what Gratifi does, the UI blocks it uses from the Gratifi UI kit, what the systems decide, and what changes by market.
A4: How a row is built
A5: Stage × Job × Constraint × Exception. The same job ("Book a return flight") appears once per constraint that changes the answer, and once per exception that changes the flow.
A6: Customer says is one real example; the agent is trained on many phrasings per row. Gratifi does is the answer shape. UI blocks name components in the kit. Rules are decided by systems, never by the model.
A8: Scoring (1 low to 5 high)
A9: Volume: how often customers ask. Value: revenue or loyalty impact. Risk: harm if wrong (money, rights, safety). Priority = Volume × Value ÷ Risk.
A11: Build waves (edit the blue cells to change them)
A12: Wave 1 needs priority of at least | B12: 6
A13: Wave 1 needs risk no higher than | B13: 2
A14: Rows with risk of at least this go to wave 3 (legal and human sign-off first) | B14: 4
A15: Core path (Y) rows are wave 1 whatever their score: a customer cannot book without them.
A16: Status
A17: • Scores are a first pass by Claude for discussion; the product team should re-score with real volumes from partner banks.
A18: • Compensation amounts are named only where set by law (UK261, EU261). For India (DGCA), Malaysia (MAVCOM), Singapore and UAE the rule is named and the amount must come from each bank's legal team.
A19: • Airlines in the kit are fictional. Market notes are prompts to check, not legal advice.
A20: • To add a use case: add a row at the bottom of "Use cases" and copy the Priority and Wave formulas down.

Sheet Summary
A1: Summary
A3: Stage | B3: Use cases | C3: Wave 1 | D3: Wave 2 | E3: Wave 3 | F3: Average priority
A4: Inspire | B4: =COUNTIF('Use cases'!$B$2:$B$119,A4) -> 8 | C4: =COUNTIFS('Use cases'!$B$2:$B$119,$A4,'Use cases'!$P$2:$P$119,1) -> 8 | D4: =COUNTIFS('Use cases'!$B$2:$B$119,$A4,'Use cases'!$P$2:$P$119,2) -> 0 | E4: =COUNTIFS('Use cases'!$B$2:$B$119,$A4,'Use cases'!$P$2:$P$119,3) -> 0 | F4: =IFERROR(ROUND(AVERAGEIF('Use cases'!$B$2:$B$119,A4,'Use cases'!$O$2:$O$119),1),0) -> 9.1
A5: Search | B5: =COUNTIF('Use cases'!$B$2:$B$119,A5) -> 18 | C5: =COUNTIFS('Use cases'!$B$2:$B$119,$A5,'Use cases'!$P$2:$P$119,1) -> 11 | D5: =COUNTIFS('Use cases'!$B$2:$B$119,$A5,'Use cases'!$P$2:$P$119,2) -> 7 | E5: =COUNTIFS('Use cases'!$B$2:$B$119,$A5,'Use cases'!$P$2:$P$119,3) -> 0 | F5: =IFERROR(ROUND(AVERAGEIF('Use cases'!$B$2:$B$119,A5,'Use cases'!$O$2:$O$119),1),0) -> 8.6
A6: Choose | B6: =COUNTIF('Use cases'!$B$2:$B$119,A6) -> 12 | C6: =COUNTIFS('Use cases'!$B$2:$B$119,$A6,'Use cases'!$P$2:$P$119,1) -> 3 | D6: =COUNTIFS('Use cases'!$B$2:$B$119,$A6,'Use cases'!$P$2:$P$119,2) -> 8 | E6: =COUNTIFS('Use cases'!$B$2:$B$119,$A6,'Use cases'!$P$2:$P$119,3) -> 1 | F6: =IFERROR(ROUND(AVERAGEIF('Use cases'!$B$2:$B$119,A6,'Use cases'!$O$2:$O$119),1),0) -> 5.1
A7: Pay | B7: =COUNTIF('Use cases'!$B$2:$B$119,A7) -> 15 | C7: =COUNTIFS('Use cases'!$B$2:$B$119,$A7,'Use cases'!$P$2:$P$119,1) -> 7 | D7: =COUNTIFS('Use cases'!$B$2:$B$119,$A7,'Use cases'!$P$2:$P$119,2) -> 5 | E7: =COUNTIFS('Use cases'!$B$2:$B$119,$A7,'Use cases'!$P$2:$P$119,3) -> 3 | F7: =IFERROR(ROUND(AVERAGEIF('Use cases'!$B$2:$B$119,A7,'Use cases'!$O$2:$O$119),1),0) -> 4.9
A8: Extras | B8: =COUNTIF('Use cases'!$B$2:$B$119,A8) -> 16 | C8: =COUNTIFS('Use cases'!$B$2:$B$119,$A8,'Use cases'!$P$2:$P$119,1) -> 6 | D8: =COUNTIFS('Use cases'!$B$2:$B$119,$A8,'Use cases'!$P$2:$P$119,2) -> 8 | E8: =COUNTIFS('Use cases'!$B$2:$B$119,$A8,'Use cases'!$P$2:$P$119,3) -> 2 | F8: =IFERROR(ROUND(AVERAGEIF('Use cases'!$B$2:$B$119,A8,'Use cases'!$O$2:$O$119),1),0) -> 7.3
A9: Before the trip | B9: =COUNTIF('Use cases'!$B$2:$B$119,A9) -> 14 | C9: =COUNTIFS('Use cases'!$B$2:$B$119,$A9,'Use cases'!$P$2:$P$119,1) -> 3 | D9: =COUNTIFS('Use cases'!$B$2:$B$119,$A9,'Use cases'!$P$2:$P$119,2) -> 6 | E9: =COUNTIFS('Use cases'!$B$2:$B$119,$A9,'Use cases'!$P$2:$P$119,3) -> 5 | F9: =IFERROR(ROUND(AVERAGEIF('Use cases'!$B$2:$B$119,A9,'Use cases'!$O$2:$O$119),1),0) -> 4.2
A10: Day of travel | B10: =COUNTIF('Use cases'!$B$2:$B$119,A10) -> 10 | C10: =COUNTIFS('Use cases'!$B$2:$B$119,$A10,'Use cases'!$P$2:$P$119,1) -> 4 | D10: =COUNTIFS('Use cases'!$B$2:$B$119,$A10,'Use cases'!$P$2:$P$119,2) -> 3 | E10: =COUNTIFS('Use cases'!$B$2:$B$119,$A10,'Use cases'!$P$2:$P$119,3) -> 3 | F10: =IFERROR(ROUND(AVERAGEIF('Use cases'!$B$2:$B$119,A10,'Use cases'!$O$2:$O$119),1),0) -> 6.1
A11: Disruption | B11: =COUNTIF('Use cases'!$B$2:$B$119,A11) -> 11 | C11: =COUNTIFS('Use cases'!$B$2:$B$119,$A11,'Use cases'!$P$2:$P$119,1) -> 1 | D11: =COUNTIFS('Use cases'!$B$2:$B$119,$A11,'Use cases'!$P$2:$P$119,2) -> 1 | E11: =COUNTIFS('Use cases'!$B$2:$B$119,$A11,'Use cases'!$P$2:$P$119,3) -> 9 | F11: =IFERROR(ROUND(AVERAGEIF('Use cases'!$B$2:$B$119,A11,'Use cases'!$O$2:$O$119),1),0) -> 2
A12: After the trip | B12: =COUNTIF('Use cases'!$B$2:$B$119,A12) -> 6 | C12: =COUNTIFS('Use cases'!$B$2:$B$119,$A12,'Use cases'!$P$2:$P$119,1) -> 4 | D12: =COUNTIFS('Use cases'!$B$2:$B$119,$A12,'Use cases'!$P$2:$P$119,2) -> 1 | E12: =COUNTIFS('Use cases'!$B$2:$B$119,$A12,'Use cases'!$P$2:$P$119,3) -> 1 | F12: =IFERROR(ROUND(AVERAGEIF('Use cases'!$B$2:$B$119,A12,'Use cases'!$O$2:$O$119),1),0) -> 6
A13: Points and card | B13: =COUNTIF('Use cases'!$B$2:$B$119,A13) -> 8 | C13: =COUNTIFS('Use cases'!$B$2:$B$119,$A13,'Use cases'!$P$2:$P$119,1) -> 5 | D13: =COUNTIFS('Use cases'!$B$2:$B$119,$A13,'Use cases'!$P$2:$P$119,2) -> 2 | E13: =COUNTIFS('Use cases'!$B$2:$B$119,$A13,'Use cases'!$P$2:$P$119,3) -> 1 | F13: =IFERROR(ROUND(AVERAGEIF('Use cases'!$B$2:$B$119,A13,'Use cases'!$O$2:$O$119),1),0) -> 8
A14: Total | B14: =SUM(B4:B13) -> 118 | C14: =SUM(C4:C13) -> 52 | D14: =SUM(D4:D13) -> 41 | E14: =SUM(E4:E13) -> 25 | F14: =ROUND(AVERAGE('Use cases'!$O$2:$O$119),1) -> 6.1
A16: Wave 1 is what the agent handles end to end first. Wave 3 needs legal sign-off and a human in the loop before launch.

Sheet Use cases
A1: ID | B1: Stage | C1: Job | D1: Constraint | E1: Exception | F1: Customer says | G1: Gratifi does | H1: UI blocks (kit) | I1: Rules: systems decide | J1: Market notes | K1: Volume | L1: Value | M1: Risk | N1: Core path | O1: Priority | P1: Wave
A2: FL-INS-01 | B2: Inspire | C2: Find somewhere to go | D2: Budget | F2: Somewhere warm in October for under 40,000 points | G2: Suggests 3 places the points cover, with flight price and weather | H2: Answer, Rail, Polaroid, Price | I2: Only places with live fares under the budget | K2: 4 | L2: 3 | M2: 1 | O2: =ROUND(K2*L2/M2,1) -> 12 | P2: =IF(N2="Y",1,IF(M2>='Read me'!$B$14,3,IF(AND(O2>='Read me'!$B$12,M2<='Read me'!$B$13),1,2))) -> 1
A3: FL-INS-02 | B3: Inspire | C3: Find somewhere to go | D3: Dates fixed | F3: Where can I go for the long weekend? | G3: Finds direct flights for those dates, shortest first | H3: Answer, Rail, FlightCard | I3: Uses the bank holiday calendar for the market | J3: Holiday calendars differ per market: bank holidays (UK), Diwali (IN), Eid (AE, MY), Chinese New Year (SG, MY) | K3: 4 | L3: 3 | M3: 1 | O3: =ROUND(K3*L3/M3,1) -> 12 | P3: =IF(N3="Y",1,IF(M3>='Read me'!$B$14,3,IF(AND(O3>='Read me'!$B$12,M3<='Read me'!$B$13),1,2))) -> 1
A4: FL-INS-03 | B4: Inspire | C4: Find somewhere to go | D4: Points only | F4: What can I get with my points alone? | G4: Shows trips fully covered by the balance | H4: Answer, Dial, Rail | I4: Balance and point value from the bank | K4: 4 | L4: 4 | M4: 1 | O4: =ROUND(K4*L4/M4,1) -> 16 | P4: =IF(N4="Y",1,IF(M4>='Read me'!$B$14,3,IF(AND(O4>='Read me'!$B$12,M4<='Read me'!$B$13),1,2))) -> 1
A5: FL-INS-04 | B5: Inspire | C5: Find somewhere to go | D5: Travelling with kids | F5: Somewhere easy with a toddler, short flight | G5: Filters to under 3 hours, direct, family-friendly stays | H5: Answer, Rail, Chips | I5: Flight time cap is a hard filter | K5: 3 | L5: 3 | M5: 1 | O5: =ROUND(K5*L5/M5,1) -> 9 | P5: =IF(N5="Y",1,IF(M5>='Read me'!$B$14,3,IF(AND(O5>='Read me'!$B$12,M5<='Read me'!$B$13),1,2))) -> 1
A6: FL-INS-05 | B6: Inspire | C6: Get a price alert | D6: Route known | F6: Tell me if London to Lisbon drops under £150 | G6: Sets an alert and confirms the threshold | H6: Toast, Toggle | I6: Alert fires on supplier price, not an estimate | K6: 3 | L6: 2 | M6: 1 | O6: =ROUND(K6*L6/M6,1) -> 6 | P6: =IF(N6="Y",1,IF(M6>='Read me'!$B$14,3,IF(AND(O6>='Read me'!$B$12,M6<='Read me'!$B$13),1,2))) -> 1
A7: FL-INS-06 | B7: Inspire | C7: Get told about a deal | D7: Card benefit | F7: (Gratifi starts it) | G7: Moment: a card offer on a route the customer flies often | H7: StickyNote, OfferCard | I7: Only offers the customer is eligible for; marketing consent checked | J7: Consent rules differ: UK GDPR/PECR, EU GDPR, India DPDP Act, Singapore PDPA, Malaysia PDPA, UAE PDPL | K7: 3 | L7: 4 | M7: 2 | O7: =ROUND(K7*L7/M7,1) -> 6 | P7: =IF(N7="Y",1,IF(M7>='Read me'!$B$14,3,IF(AND(O7>='Read me'!$B$12,M7<='Read me'!$B$13),1,2))) -> 1
A8: FL-INS-07 | B8: Inspire | C8: Plan around an event | D8: Date fixed by event | F8: Flights for the F1 weekend | G8: Finds flights and warns about peak prices | H8: Answer, PriceCalendar, StateCard | I8: Event dates from content partner | K8: 2 | L8: 3 | M8: 1 | O8: =ROUND(K8*L8/M8,1) -> 6 | P8: =IF(N8="Y",1,IF(M8>='Read me'!$B$14,3,IF(AND(O8>='Read me'!$B$12,M8<='Read me'!$B$13),1,2))) -> 1
A9: FL-INS-08 | B9: Inspire | C9: Compare two places | D9: Undecided | F9: Lisbon or Porto for 3 nights? | G9: Side-by-side of flight, hotel and total in points | H9: Compare | I9: Totals include taxes | K9: 2 | L9: 3 | M9: 1 | O9: =ROUND(K9*L9/M9,1) -> 6 | P9: =IF(N9="Y",1,IF(M9>='Read me'!$B$14,3,IF(AND(O9>='Read me'!$B$12,M9<='Read me'!$B$13),1,2))) -> 1
A10: FL-SRC-01 | B10: Search | C10: Book a return flight | D10: Dates fixed | F10: Lisbon for two, 16 to 18 October | G10: Three best options with a recommendation and the reason | H10: YouSaid, Steps, Answer, Rail, FlightCard, Suggestions | I10: Supplier fares only; the recommendation reason must be a stated fact | K10: 5 | L10: 5 | M10: 2 | N10: Y | O10: =ROUND(K10*L10/M10,1) -> 12.5 | P10: =IF(N10="Y",1,IF(M10>='Read me'!$B$14,3,IF(AND(O10>='Read me'!$B$12,M10<='Read me'!$B$13),1,2))) -> 1
A11: FL-SRC-02 | B11: Search | C11: Book a return flight | D11: Flexible dates | F11: Cheapest week in October to Lisbon | G11: Price calendar with the cheapest days marked | H11: PriceCalendar | I11: Calendar prices are cached; confirm live before pay | J11: Week starts Sunday in IN and SG, Monday elsewhere | K11: 5 | L11: 4 | M11: 2 | N11: Y | O11: =ROUND(K11*L11/M11,1) -> 10 | P11: =IF(N11="Y",1,IF(M11>='Read me'!$B$14,3,IF(AND(O11>='Read me'!$B$12,M11<='Read me'!$B$13),1,2))) -> 1
A12: FL-SRC-03 | B12: Search | C12: Book a one-way flight | D12: Dates fixed | F12: One way to Dubai on Friday | G12: Results for one-way only | H12: FlightCard, Rail | K12: 4 | L12: 4 | M12: 1 | O12: =ROUND(K12*L12/M12,1) -> 16 | P12: =IF(N12="Y",1,IF(M12>='Read me'!$B$14,3,IF(AND(O12>='Read me'!$B$12,M12<='Read me'!$B$13),1,2))) -> 1
A13: FL-SRC-04 | B13: Search | C13: Book a multi-city trip | D13: Several stops | F13: London to Lisbon, then Porto, then home | G13: Builds the legs and prices them together and separately | H13: Itinerary, Compare | I13: Separate tickets flagged: missed connections not protected | K13: 2 | L13: 4 | M13: 3 | O13: =ROUND(K13*L13/M13,1) -> 2.7 | P13: =IF(N13="Y",1,IF(M13>='Read me'!$B$14,3,IF(AND(O13>='Read me'!$B$12,M13<='Read me'!$B$13),1,2))) -> 2
A14: FL-SRC-05 | B14: Search | C14: Search with filters | D14: Direct only | F14: Only direct | G14: Filters and says how many are left | H14: FilterBar, Chips | K14: 5 | L14: 3 | M14: 1 | O14: =ROUND(K14*L14/M14,1) -> 15 | P14: =IF(N14="Y",1,IF(M14>='Read me'!$B$14,3,IF(AND(O14>='Read me'!$B$12,M14<='Read me'!$B$13),1,2))) -> 1
A15: FL-SRC-06 | B15: Search | C15: Search with filters | D15: Time of day | F15: Nothing before 9am | G15: Filters by departure time | H15: FilterBar | K15: 4 | L15: 3 | M15: 1 | O15: =ROUND(K15*L15/M15,1) -> 12 | P15: =IF(N15="Y",1,IF(M15>='Read me'!$B$14,3,IF(AND(O15>='Read me'!$B$12,M15<='Read me'!$B$13),1,2))) -> 1
A16: FL-SRC-07 | B16: Search | C16: Search with filters | D16: Airline preference | F16: Only airlines where I earn miles | G16: Filters to airlines linked to the customer's schemes | H16: FilterBar, Badge | I16: Frequent flyer numbers from the profile | K16: 3 | L16: 3 | M16: 1 | O16: =ROUND(K16*L16/M16,1) -> 9 | P16: =IF(N16="Y",1,IF(M16>='Read me'!$B$14,3,IF(AND(O16>='Read me'!$B$12,M16<='Read me'!$B$13),1,2))) -> 1
A17: FL-SRC-08 | B17: Search | C17: Search with filters | D17: Bag included | F17: Must include a checked bag | G17: Filters to fares with a checked bag, shows true total | H17: FilterBar, FareFamilies | I17: Total must include the bag | K17: 4 | L17: 3 | M17: 1 | O17: =ROUND(K17*L17/M17,1) -> 12 | P17: =IF(N17="Y",1,IF(M17>='Read me'!$B$14,3,IF(AND(O17>='Read me'!$B$12,M17<='Read me'!$B$13),1,2))) -> 1
A18: FL-SRC-09 | B18: Search | C18: Search nearby airports | D18: City, not airport | F18: Any London airport | G18: Searches all airports for the city | H18: FlightCard | I18: Airport groups per city | K18: 4 | L18: 3 | M18: 1 | O18: =ROUND(K18*L18/M18,1) -> 12 | P18: =IF(N18="Y",1,IF(M18>='Read me'!$B$14,3,IF(AND(O18>='Read me'!$B$12,M18<='Read me'!$B$13),1,2))) -> 1
A19: FL-SRC-10 | B19: Search | C19: Search by voice | D19: Hands busy | F19: (spoken) Flights to Goa next weekend | G19: Transcribes, confirms understanding, searches | H19: AskBar (listening), YouSaid | I19: Shows what it heard before acting | J19: Voice in English first; Hindi, Arabic, Malay later | K19: 3 | L19: 3 | M19: 2 | O19: =ROUND(K19*L19/M19,1) -> 4.5 | P19: =IF(N19="Y",1,IF(M19>='Read me'!$B$14,3,IF(AND(O19>='Read me'!$B$12,M19<='Read me'!$B$13),1,2))) -> 2
A20: FL-SRC-11 | B20: Search | C20: Search for a group | D20: 5 or more | F20: Flights for 8 of us | G20: Checks seat availability for 8, offers group fare route | H20: Travellers, StateCard, Handoff | I20: Over 9 passengers goes to group desk | K20: 2 | L20: 4 | M20: 3 | O20: =ROUND(K20*L20/M20,1) -> 2.7 | P20: =IF(N20="Y",1,IF(M20>='Read me'!$B$14,3,IF(AND(O20>='Read me'!$B$12,M20<='Read me'!$B$13),1,2))) -> 2
A21: FL-SRC-12 | B21: Search | C21: Search premium cabins | D21: Business class | F21: Business class to Singapore | G21: Shows business fares and points cost | H21: FlightCard, FareFamilies | K21: 2 | L21: 5 | M21: 1 | O21: =ROUND(K21*L21/M21,1) -> 10 | P21: =IF(N21="Y",1,IF(M21>='Read me'!$B$14,3,IF(AND(O21>='Read me'!$B$12,M21<='Read me'!$B$13),1,2))) -> 1
A22: FL-SRC-13 | B22: Search | C22: Search with points and cash | D22: Budget in points | F22: Use no more than 20,000 points | G22: Prices each option as points plus cash | H22: PointsSlider, Price | I22: Point value from the bank | K22: 4 | L22: 4 | M22: 1 | O22: =ROUND(K22*L22/M22,1) -> 16 | P22: =IF(N22="Y",1,IF(M22>='Read me'!$B$14,3,IF(AND(O22>='Read me'!$B$12,M22<='Read me'!$B$13),1,2))) -> 1
A23: FL-SRC-14 | B23: Search | C23: Nothing found | D23: Too strict | E23: No results | F23: Direct, before 9am, under £100 | G23: Says which filter blocks it and offers the nearest options | H23: StateCard (empty) | I23: Never invents a flight | K23: 3 | L23: 3 | M23: 1 | O23: =ROUND(K23*L23/M23,1) -> 9 | P23: =IF(N23="Y",1,IF(M23>='Read me'!$B$14,3,IF(AND(O23>='Read me'!$B$12,M23<='Read me'!$B$13),1,2))) -> 1
A24: FL-SRC-15 | B24: Search | C24: Search fails | D24: Supplier down | E24: Timeout | F24: (any search) | G24: Says the airline is not answering, nothing was booked, try again | H24: StateCard (error) | I24: Retry with backoff; switch supplier if available | K24: 2 | L24: 2 | M24: 2 | O24: =ROUND(K24*L24/M24,1) -> 2 | P24: =IF(N24="Y",1,IF(M24>='Read me'!$B$14,3,IF(AND(O24>='Read me'!$B$12,M24<='Read me'!$B$13),1,2))) -> 2
A25: FL-SRC-16 | B25: Search | C25: Book a return flight | D25: Open jaw | F25: Fly into Lisbon, back from Porto | G25: Prices the open jaw as one trip | H25: Itinerary, FlightCard | I25: Fare construction by supplier | K25: 2 | L25: 3 | M25: 2 | O25: =ROUND(K25*L25/M25,1) -> 3 | P25: =IF(N25="Y",1,IF(M25>='Read me'!$B$14,3,IF(AND(O25>='Read me'!$B$12,M25<='Read me'!$B$13),1,2))) -> 2
A26: FL-SRC-17 | B26: Search | C26: Book for someone else | D26: Gift trip | F26: Book flights for my parents | G26: Captures their names, pays from my points | H26: Travellers, PayWith | I26: Names must match passports | K26: 2 | L26: 4 | M26: 3 | O26: =ROUND(K26*L26/M26,1) -> 2.7 | P26: =IF(N26="Y",1,IF(M26>='Read me'!$B$14,3,IF(AND(O26>='Read me'!$B$12,M26<='Read me'!$B$13),1,2))) -> 2
A27: FL-SRC-18 | B27: Search | C27: Book last minute | D27: Today | F27: Next flight to Edinburgh | G27: Shows flights leaving soonest with check-in cut-off | H27: FlightCard, Status | I27: Cut-off times per airline | K27: 2 | L27: 4 | M27: 2 | O27: =ROUND(K27*L27/M27,1) -> 4 | P27: =IF(N27="Y",1,IF(M27>='Read me'!$B$14,3,IF(AND(O27>='Read me'!$B$12,M27<='Read me'!$B$13),1,2))) -> 2
A28: FL-CHO-01 | B28: Choose | C28: Choose between flights | D28: Two close options | F28: Which is better, the 7am or the 11am? | G28: Compares on what differs: time, bag, price, points back | H28: Compare | I28: Only facts from the fares | K28: 4 | L28: 4 | M28: 1 | O28: =ROUND(K28*L28/M28,1) -> 16 | P28: =IF(N28="Y",1,IF(M28>='Read me'!$B$14,3,IF(AND(O28>='Read me'!$B$12,M28<='Read me'!$B$13),1,2))) -> 1
A29: FL-CHO-02 | B29: Choose | C29: Understand a fare | D29: Unsure what is included | F29: Does Light include a bag? | G29: Shows fare families, ticked and greyed | H29: FareFamilies | I29: Fare rules from the supplier, word for word in the source | K29: 5 | L29: 4 | M29: 2 | N29: Y | O29: =ROUND(K29*L29/M29,1) -> 10 | P29: =IF(N29="Y",1,IF(M29>='Read me'!$B$14,3,IF(AND(O29>='Read me'!$B$12,M29<='Read me'!$B$13),1,2))) -> 1
A30: FL-CHO-03 | B30: Choose | C30: Understand change rules | D30: Might change plans | F30: Can I change the date later? | G30: Plain-words fare rules: free, fee, not possible | H30: FareRules | I30: Rules from fare; never guessed | K30: 4 | L30: 4 | M30: 3 | O30: =ROUND(K30*L30/M30,1) -> 5.3 | P30: =IF(N30="Y",1,IF(M30>='Read me'!$B$14,3,IF(AND(O30>='Read me'!$B$12,M30<='Read me'!$B$13),1,2))) -> 2
A31: FL-CHO-04 | B31: Choose | C31: See the full journey | D31: Connection | F31: How long is the stop in Porto? | G31: Itinerary with layover; tight ones in amber | H31: Itinerary | I31: Minimum connection time per airport | K31: 3 | L31: 3 | M31: 2 | O31: =ROUND(K31*L31/M31,1) -> 4.5 | P31: =IF(N31="Y",1,IF(M31>='Read me'!$B$14,3,IF(AND(O31>='Read me'!$B$12,M31<='Read me'!$B$13),1,2))) -> 2
A32: FL-CHO-05 | B32: Choose | C32: See the plane | D32: Comfort | F32: What plane is it? | G32: Aircraft type and seat pitch if known | H32: Itinerary, Meta | K32: 2 | L32: 2 | M32: 1 | O32: =ROUND(K32*L32/M32,1) -> 4 | P32: =IF(N32="Y",1,IF(M32>='Read me'!$B$14,3,IF(AND(O32>='Read me'!$B$12,M32<='Read me'!$B$13),1,2))) -> 2
A33: FL-CHO-06 | B33: Choose | C33: Choose travellers | D33: Children | F33: Two adults and a 3 year old | G33: Sets travellers with correct age bands | H33: Travellers | I33: Age on the day of travel; airline bands | K33: 4 | L33: 3 | M33: 2 | O33: =ROUND(K33*L33/M33,1) -> 6 | P33: =IF(N33="Y",1,IF(M33>='Read me'!$B$14,3,IF(AND(O33>='Read me'!$B$12,M33<='Read me'!$B$13),1,2))) -> 1
A34: FL-CHO-07 | B34: Choose | C34: Choose travellers | D34: Infant on lap | F34: Plus a baby | G34: Adds infant, one per adult | H34: Travellers | I34: Infants never exceed adults | K34: 3 | L34: 3 | M34: 2 | O34: =ROUND(K34*L34/M34,1) -> 4.5 | P34: =IF(N34="Y",1,IF(M34>='Read me'!$B$14,3,IF(AND(O34>='Read me'!$B$12,M34<='Read me'!$B$13),1,2))) -> 2
A35: FL-CHO-08 | B35: Choose | C35: Choose travellers | D35: Travelling alone as a minor | F35: My daughter is flying alone, she's 13 | G35: Explains the airline's unaccompanied minor service and hands over | H35: StateCard, Handoff | I35: Unaccompanied minors always go to a person | K35: 1 | L35: 3 | M35: 5 | O35: =ROUND(K35*L35/M35,1) -> 0.6 | P35: =IF(N35="Y",1,IF(M35>='Read me'!$B$14,3,IF(AND(O35>='Read me'!$B$12,M35<='Read me'!$B$13),1,2))) -> 3
A36: FL-CHO-09 | B36: Choose | C36: Price changed | D36: Between search and choose | E36: Fare rose | F36: (taps a flight) | G36: Shows old and new price, asks to continue | H36: StateCard (price) | I36: Never book at a higher price without a new yes | K36: 3 | L36: 3 | M36: 3 | O36: =ROUND(K36*L36/M36,1) -> 3 | P36: =IF(N36="Y",1,IF(M36>='Read me'!$B$14,3,IF(AND(O36>='Read me'!$B$12,M36<='Read me'!$B$13),1,2))) -> 2
A37: FL-CHO-10 | B37: Choose | C37: Sold out | D37: Last seats | E37: Fare gone | F37: (taps a flight) | G37: Says it has gone and offers the next best | H37: StateCard (soldout) | K37: 3 | L37: 3 | M37: 2 | O37: =ROUND(K37*L37/M37,1) -> 4.5 | P37: =IF(N37="Y",1,IF(M37>='Read me'!$B$14,3,IF(AND(O37>='Read me'!$B$12,M37<='Read me'!$B$13),1,2))) -> 2
A38: FL-CHO-11 | B38: Choose | C38: Hold a fare | D38: Deciding | F38: Can you hold this for a day? | G38: Offers fare hold if the airline sells it | H38: StateCard, ConfirmSheet | I38: Hold price and time from the airline | K38: 2 | L38: 3 | M38: 3 | O38: =ROUND(K38*L38/M38,1) -> 2 | P38: =IF(N38="Y",1,IF(M38>='Read me'!$B$14,3,IF(AND(O38>='Read me'!$B$12,M38<='Read me'!$B$13),1,2))) -> 2
A39: FL-CHO-12 | B39: Choose | C39: Check the carbon | D39: Green choice | F39: Which one is lower carbon? | G39: Shows estimated emissions per option | H39: Compare | I39: Estimate from a named source | J39: Carbon disclosure rules vary; EU strictest | K39: 1 | L39: 2 | M39: 2 | O39: =ROUND(K39*L39/M39,1) -> 1 | P39: =IF(N39="Y",1,IF(M39>='Read me'!$B$14,3,IF(AND(O39>='Read me'!$B$12,M39<='Read me'!$B$13),1,2))) -> 2
A40: FL-PAY-01 | B40: Pay | C40: Pay with points | D40: Enough points | F40: Pay with points | G40: Shows points total, confirm, done | H40: PayWith, ConfirmSheet, Receipt | I40: Points value from the bank; spend needs a button with the amount | J40: Confirm: Face ID (UK, EU, AE, SG), one-time code (IN), bank app approval (MY) | K40: 5 | L40: 5 | M40: 3 | N40: Y | O40: =ROUND(K40*L40/M40,1) -> 8.3 | P40: =IF(N40="Y",1,IF(M40>='Read me'!$B$14,3,IF(AND(O40>='Read me'!$B$12,M40<='Read me'!$B$13),1,2))) -> 1
A41: FL-PAY-02 | B41: Pay | C41: Pay with points and card | D41: Not enough points | F41: Use my points and put the rest on my card | G41: Splits points and card, shows both totals | H41: PayWith, PointsSlider, ConfirmSheet | I41: Minimum card part set by the bank | J41: Card part follows local card authentication rules | K41: 5 | L41: 5 | M41: 3 | N41: Y | O41: =ROUND(K41*L41/M41,1) -> 8.3 | P41: =IF(N41="Y",1,IF(M41>='Read me'!$B$14,3,IF(AND(O41>='Read me'!$B$12,M41<='Read me'!$B$13),1,2))) -> 1
A42: FL-PAY-03 | B42: Pay | C42: Pay by card only | D42: Save points | F42: Keep my points, pay by card | G42: Card only, shows points earned | H42: PayWith, ConfirmSheet, Back | K42: 4 | L42: 4 | M42: 2 | N42: Y | O42: =ROUND(K42*L42/M42,1) -> 8 | P42: =IF(N42="Y",1,IF(M42>='Read me'!$B$14,3,IF(AND(O42>='Read me'!$B$12,M42<='Read me'!$B$13),1,2))) -> 1
A43: FL-PAY-04 | B43: Pay | C43: Choose the split | D43: Specific amount | F43: Use exactly 10,000 points | G43: Sets the slider, shows the card part | H43: PointsSlider | I43: Steps in the bank's minimum unit | K43: 3 | L43: 3 | M43: 2 | O43: =ROUND(K43*L43/M43,1) -> 4.5 | P43: =IF(N43="Y",1,IF(M43>='Read me'!$B$14,3,IF(AND(O43>='Read me'!$B$12,M43<='Read me'!$B$13),1,2))) -> 2
A44: FL-PAY-05 | B44: Pay | C44: Not enough points | D44: Points only asked | E44: Short of points | F44: Pay with points | G44: Says how many short and offers points and card | H44: PayWith (disabled option), StateCard | K44: 4 | L44: 3 | M44: 2 | O44: =ROUND(K44*L44/M44,1) -> 6 | P44: =IF(N44="Y",1,IF(M44>='Read me'!$B$14,3,IF(AND(O44>='Read me'!$B$12,M44<='Read me'!$B$13),1,2))) -> 1
A45: FL-PAY-06 | B45: Pay | C45: Payment declined | D45: Card issue | E45: Declined | F45: (confirms) | G45: Says nothing was booked, offers another card or points | H45: StateCard (error) | I45: No booking without payment success | K45: 2 | L45: 3 | M45: 4 | N45: Y | O45: =ROUND(K45*L45/M45,1) -> 1.5 | P45: =IF(N45="Y",1,IF(M45>='Read me'!$B$14,3,IF(AND(O45>='Read me'!$B$12,M45<='Read me'!$B$13),1,2))) -> 1
A46: FL-PAY-07 | B46: Pay | C46: Authentication fails | D46: Face ID / code | E46: Failed or timed out | F46: (confirms) | G46: Lets them retry; after 3 fails, hands to the bank's flow | H46: ConfirmSheet, StateCard | I46: Lockout rules from the bank | J46: OTP retry limits set by the bank (IN) | K46: 2 | L46: 3 | M46: 4 | O46: =ROUND(K46*L46/M46,1) -> 1.5 | P46: =IF(N46="Y",1,IF(M46>='Read me'!$B$14,3,IF(AND(O46>='Read me'!$B$12,M46<='Read me'!$B$13),1,2))) -> 3
A47: FL-PAY-08 | B47: Pay | C47: Price changed at pay | D47: Final check | E47: Fare rose | F47: (confirms) | G47: Stops, shows new price, asks again | H47: StateCard (price) | I47: Re-price before every payment | K47: 3 | L47: 3 | M47: 4 | N47: Y | O47: =ROUND(K47*L47/M47,1) -> 2.3 | P47: =IF(N47="Y",1,IF(M47>='Read me'!$B$14,3,IF(AND(O47>='Read me'!$B$12,M47<='Read me'!$B$13),1,2))) -> 1
A48: FL-PAY-09 | B48: Pay | C48: Get an invoice | D48: Business trip | F48: I need a tax invoice for my company | G48: Captures company details, sends invoice | H48: Receipt, Handoff | I48: Invoice issued by the supplier | J48: India: GST invoice needs the company GSTIN at booking. UK/EU: VAT receipts | K48: 2 | L48: 3 | M48: 2 | O48: =ROUND(K48*L48/M48,1) -> 3 | P48: =IF(N48="Y",1,IF(M48>='Read me'!$B$14,3,IF(AND(O48>='Read me'!$B$12,M48<='Read me'!$B$13),1,2))) -> 2
A49: FL-PAY-10 | B49: Pay | C49: Pay in instalments | D49: Large spend | F49: Can I split this over 3 months? | G49: Explains the bank's instalment plan if eligible | H49: Answer, Handoff | I49: Eligibility and rates from the bank only | J49: EMI common in IN and MY; credit rules differ per market | K49: 2 | L49: 4 | M49: 4 | O49: =ROUND(K49*L49/M49,1) -> 2 | P49: =IF(N49="Y",1,IF(M49>='Read me'!$B$14,3,IF(AND(O49>='Read me'!$B$12,M49<='Read me'!$B$13),1,2))) -> 3
A50: FL-PAY-11 | B50: Pay | C50: Use a voucher | D50: Has a code | F50: I have a £50 travel voucher | G50: Applies it and shows the new total | H50: PriceLines | I50: Voucher validity checked by the issuer | K50: 2 | L50: 3 | M50: 2 | O50: =ROUND(K50*L50/M50,1) -> 3 | P50: =IF(N50="Y",1,IF(M50>='Read me'!$B$14,3,IF(AND(O50>='Read me'!$B$12,M50<='Read me'!$B$13),1,2))) -> 2
A51: FL-PAY-12 | B51: Pay | C51: Booking confirmed | D51: Success | F51: (after pay) | G51: Receipt with reference, what happens next | H51: CheckPop, Receipt | K51: 5 | L51: 4 | M51: 1 | N51: Y | O51: =ROUND(K51*L51/M51,1) -> 20 | P51: =IF(N51="Y",1,IF(M51>='Read me'!$B$14,3,IF(AND(O51>='Read me'!$B$12,M51<='Read me'!$B$13),1,2))) -> 1
A52: FL-PAY-13 | B52: Pay | C52: Booking pending | D52: Supplier slow | E52: No ticket yet | F52: (after pay) | G52: Says it is paid and being ticketed, will confirm in minutes | H52: StateCard, Toast | I52: Refund automatically if not ticketed in the set time | K52: 2 | L52: 3 | M52: 4 | O52: =ROUND(K52*L52/M52,1) -> 1.5 | P52: =IF(N52="Y",1,IF(M52>='Read me'!$B$14,3,IF(AND(O52>='Read me'!$B$12,M52<='Read me'!$B$13),1,2))) -> 3
A53: FL-PAY-14 | B53: Pay | C53: Pay in another currency | D53: Foreign airline | F53: Why is this in euros? | G53: Explains currency and any card fee | H53: PriceLines, BenefitRow | I53: FX rate from the bank | K53: 2 | L53: 3 | M53: 3 | O53: =ROUND(K53*L53/M53,1) -> 2 | P53: =IF(N53="Y",1,IF(M53>='Read me'!$B$14,3,IF(AND(O53>='Read me'!$B$12,M53<='Read me'!$B$13),1,2))) -> 2
A54: FL-PAY-15 | B54: Pay | C54: Split payment with a friend | D54: Shared trip | F54: Split this with Sam | G54: Sends a request for their half | H54: SendTo, PriceLines | I54: Only if the bank supports requests | J54: Payment request rails differ: Faster Payments (UK), UPI (IN), PayNow (SG), DuitNow (MY) | K54: 2 | L54: 3 | M54: 3 | O54: =ROUND(K54*L54/M54,1) -> 2 | P54: =IF(N54="Y",1,IF(M54>='Read me'!$B$14,3,IF(AND(O54>='Read me'!$B$12,M54<='Read me'!$B$13),1,2))) -> 2
A55: FL-EXT-01 | B55: Extras | C55: Pick seats | D55: Together | F55: Seats together please | G55: Seat map with a suggested pair | H55: SeatMap | I55: Seat prices from the airline | K55: 5 | L55: 4 | M55: 1 | N55: Y | O55: =ROUND(K55*L55/M55,1) -> 20 | P55: =IF(N55="Y",1,IF(M55>='Read me'!$B$14,3,IF(AND(O55>='Read me'!$B$12,M55<='Read me'!$B$13),1,2))) -> 1
A56: FL-EXT-02 | B56: Extras | C56: Pick seats | D56: Preference saved | F56: (automatic) | G56: Uses saved aisle or window preference | H56: StickyNote (blue), SeatMap | I56: Preference from profile | K56: 4 | L56: 3 | M56: 1 | O56: =ROUND(K56*L56/M56,1) -> 12 | P56: =IF(N56="Y",1,IF(M56>='Read me'!$B$14,3,IF(AND(O56>='Read me'!$B$12,M56<='Read me'!$B$13),1,2))) -> 1
A57: FL-EXT-03 | B57: Extras | C57: Pick seats | D57: Extra legroom | F57: Exit row please | G57: Shows extra-legroom seats and price, explains exit row rules | H57: SeatMap | I57: Exit row eligibility rules | K57: 3 | L57: 3 | M57: 2 | O57: =ROUND(K57*L57/M57,1) -> 4.5 | P57: =IF(N57="Y",1,IF(M57>='Read me'!$B$14,3,IF(AND(O57>='Read me'!$B$12,M57<='Read me'!$B$13),1,2))) -> 2
A58: FL-EXT-04 | B58: Extras | C58: Seat taken | D58: Choosing | E58: Seat gone | F58: (taps seat) | G58: Says it has gone, suggests the nearest pair | H58: StateCard (soldout) | K58: 2 | L58: 2 | M58: 1 | O58: =ROUND(K58*L58/M58,1) -> 4 | P58: =IF(N58="Y",1,IF(M58>='Read me'!$B$14,3,IF(AND(O58>='Read me'!$B$12,M58<='Read me'!$B$13),1,2))) -> 2
A59: FL-EXT-05 | B59: Extras | C59: Add bags | D59: Checked bag | F59: Add a suitcase | G59: Adds bag, shows price per person per flight | H59: BagPicker | I59: Bag prices from the airline | J59: Cabin allowance usually 7kg on Asian carriers; 10kg or more on some European ones | K59: 5 | L59: 4 | M59: 1 | N59: Y | O59: =ROUND(K59*L59/M59,1) -> 20 | P59: =IF(N59="Y",1,IF(M59>='Read me'!$B$14,3,IF(AND(O59>='Read me'!$B$12,M59<='Read me'!$B$13),1,2))) -> 1
A60: FL-EXT-06 | B60: Extras | C60: Add bags | D60: Sports equipment | F60: I'm taking golf clubs | G60: Adds special baggage if the airline allows | H60: BagPicker, Handoff | I60: Special items from the airline list | K60: 1 | L60: 2 | M60: 2 | O60: =ROUND(K60*L60/M60,1) -> 1 | P60: =IF(N60="Y",1,IF(M60>='Read me'!$B$14,3,IF(AND(O60>='Read me'!$B$12,M60<='Read me'!$B$13),1,2))) -> 2
A61: FL-EXT-07 | B61: Extras | C61: Add meals | D61: Dietary | F61: Vegetarian meal | G61: Requests the meal, confirms it is a request | H61: Toast | I61: Meal requests are not guaranteed | J61: Common requests differ: Jain meals (IN), halal (AE, MY) | K61: 2 | L61: 2 | M61: 1 | O61: =ROUND(K61*L61/M61,1) -> 4 | P61: =IF(N61="Y",1,IF(M61>='Read me'!$B$14,3,IF(AND(O61>='Read me'!$B$12,M61<='Read me'!$B$13),1,2))) -> 2
A62: FL-EXT-08 | B62: Extras | C62: Add lounge | D62: Card benefit | F62: Can I use a lounge? | G62: Checks card benefit, books the pass | H62: BenefitRow, LoungePass | I62: Visits left from the bank | K62: 3 | L62: 4 | M62: 1 | O62: =ROUND(K62*L62/M62,1) -> 12 | P62: =IF(N62="Y",1,IF(M62>='Read me'!$B$14,3,IF(AND(O62>='Read me'!$B$12,M62<='Read me'!$B$13),1,2))) -> 1
A63: FL-EXT-09 | B63: Extras | C63: Add fast track | D63: Short on time | F63: Add fast track security | G63: Adds if available at the airport | H63: Toast, PriceLines | K63: 2 | L63: 3 | M63: 1 | O63: =ROUND(K63*L63/M63,1) -> 6 | P63: =IF(N63="Y",1,IF(M63>='Read me'!$B$14,3,IF(AND(O63>='Read me'!$B$12,M63<='Read me'!$B$13),1,2))) -> 1
A64: FL-EXT-10 | B64: Extras | C64: Add travel insurance | D64: Card cover | F64: Am I covered? | G64: Explains card travel cover, offers top-up if not covered | H64: Answer, BenefitRow | I64: Cover terms from the bank; not advice | J64: Insurance selling rules differ per market; may need a licensed partner | K64: 3 | L64: 4 | M64: 4 | O64: =ROUND(K64*L64/M64,1) -> 3 | P64: =IF(N64="Y",1,IF(M64>='Read me'!$B$14,3,IF(AND(O64>='Read me'!$B$12,M64<='Read me'!$B$13),1,2))) -> 3
A65: FL-EXT-11 | B65: Extras | C65: Add a hotel | D65: Same trip | F65: Add a hotel | G65: Hotel search for the trip dates and destination | H65: HotelCard, Rail | K65: 4 | L65: 5 | M65: 1 | O65: =ROUND(K65*L65/M65,1) -> 20 | P65: =IF(N65="Y",1,IF(M65>='Read me'!$B$14,3,IF(AND(O65>='Read me'!$B$12,M65<='Read me'!$B$13),1,2))) -> 1
A66: FL-EXT-12 | B66: Extras | C66: Add a ride | D66: Airport transfer | F66: Car to the airport | G66: Books a ride timed to the flight | H66: RideOption | I66: Timing from flight and traffic | K66: 3 | L66: 3 | M66: 2 | O66: =ROUND(K66*L66/M66,1) -> 4.5 | P66: =IF(N66="Y",1,IF(M66>='Read me'!$B$14,3,IF(AND(O66>='Read me'!$B$12,M66<='Read me'!$B$13),1,2))) -> 2
A67: FL-EXT-13 | B67: Extras | C67: Add special assistance | D67: Reduced mobility | F67: My mother needs a wheelchair | G67: Requests assistance and confirms with the airline | H67: StateCard, Handoff | I67: Always confirmed with the airline | K67: 1 | L67: 3 | M67: 4 | O67: =ROUND(K67*L67/M67,1) -> 0.8 | P67: =IF(N67="Y",1,IF(M67>='Read me'!$B$14,3,IF(AND(O67>='Read me'!$B$12,M67<='Read me'!$B$13),1,2))) -> 3
A68: FL-EXT-14 | B68: Extras | C68: Travel with a pet | D68: Pet in cabin | F68: Can my dog come? | G68: Explains the airline's pet rules and hands over to book | H68: Answer, Handoff | I68: Pet rules from the airline | J68: Pet import rules differ strictly by country | K68: 1 | L68: 2 | M68: 3 | O68: =ROUND(K68*L68/M68,1) -> 0.7 | P68: =IF(N68="Y",1,IF(M68>='Read me'!$B$14,3,IF(AND(O68>='Read me'!$B$12,M68<='Read me'!$B$13),1,2))) -> 2
A69: FL-EXT-15 | B69: Extras | C69: Upgrade with points | D69: Booked | F69: Can I upgrade to business? | G69: Checks upgrade price in points and cash | H69: FareFamilies, ConfirmSheet | I69: Upgrade inventory from the airline | K69: 2 | L69: 4 | M69: 2 | O69: =ROUND(K69*L69/M69,1) -> 4 | P69: =IF(N69="Y",1,IF(M69>='Read me'!$B$14,3,IF(AND(O69>='Read me'!$B$12,M69<='Read me'!$B$13),1,2))) -> 2
A70: FL-EXT-16 | B70: Extras | C70: Add infant seat | D70: Baby | F70: Can I get a bassinet? | G70: Requests a bassinet seat | H70: SeatMap, Toast | I70: Bassinet rows are airline-controlled | K70: 1 | L70: 2 | M70: 2 | O70: =ROUND(K70*L70/M70,1) -> 1 | P70: =IF(N70="Y",1,IF(M70>='Read me'!$B$14,3,IF(AND(O70>='Read me'!$B$12,M70<='Read me'!$B$13),1,2))) -> 2
A71: FL-PRE-01 | B71: Before the trip | C71: Check in | D71: Online | F71: (automatic) | G71: Checks in when it opens, sends boarding passes | H71: Toast, BoardingPass | I71: Consent to auto check-in | J71: India: web check-in expected for domestic flights | K71: 5 | L71: 4 | M71: 2 | N71: Y | O71: =ROUND(K71*L71/M71,1) -> 10 | P71: =IF(N71="Y",1,IF(M71>='Read me'!$B$14,3,IF(AND(O71>='Read me'!$B$12,M71<='Read me'!$B$13),1,2))) -> 1
A72: FL-PRE-02 | B72: Before the trip | C72: Add passport details | D72: International | F72: (before check-in) | G72: Asks for passport details once, stores securely | H72: StateCard, Handoff | I72: Document data held by the bank, tokenised | K72: 4 | L72: 3 | M72: 4 | O72: =ROUND(K72*L72/M72,1) -> 3 | P72: =IF(N72="Y",1,IF(M72>='Read me'!$B$14,3,IF(AND(O72>='Read me'!$B$12,M72<='Read me'!$B$13),1,2))) -> 3
A73: FL-PRE-03 | B73: Before the trip | C73: Check visa needs | D73: International | F73: Do I need a visa for Dubai? | G73: Gives the official source and the rule for their passport | H73: Answer | I73: Visa info from an official source only; always linked | J73: Rules differ by passport and destination; e-visas common for IN, AE | K73: 3 | L73: 4 | M73: 4 | O73: =ROUND(K73*L73/M73,1) -> 3 | P73: =IF(N73="Y",1,IF(M73>='Read me'!$B$14,3,IF(AND(O73>='Read me'!$B$12,M73<='Read me'!$B$13),1,2))) -> 3
A74: FL-PRE-04 | B74: Before the trip | C74: Check ID needs | D74: Domestic | F74: What ID do I need? | G74: Says what the airline accepts | H74: Answer | I74: From the airline | J74: India: photo ID, DigiYatra optional. Malaysia: MyKad for domestic; Sabah and Sarawak have their own entry rules | K74: 3 | L74: 3 | M74: 3 | O74: =ROUND(K74*L74/M74,1) -> 3 | P74: =IF(N74="Y",1,IF(M74>='Read me'!$B$14,3,IF(AND(O74>='Read me'!$B$12,M74<='Read me'!$B$13),1,2))) -> 2
A75: FL-PRE-05 | B75: Before the trip | C75: Share the trip | D75: Family | F75: Send the plan to my wife | G75: Shares a read-only trip link | H75: SendTo, TripFolder | I75: Sharing needs the customer's yes | K75: 3 | L75: 2 | M75: 2 | O75: =ROUND(K75*L75/M75,1) -> 3 | P75: =IF(N75="Y",1,IF(M75>='Read me'!$B$14,3,IF(AND(O75>='Read me'!$B$12,M75<='Read me'!$B$13),1,2))) -> 2
A76: FL-PRE-06 | B76: Before the trip | C76: Change the date | D76: Before travel | F76: Move my outbound to Saturday | G76: Shows old and new, fee and fare difference, asks to confirm | H76: ChangeFlight, ConfirmSheet | I76: Fees from fare rules | K76: 3 | L76: 4 | M76: 3 | O76: =ROUND(K76*L76/M76,1) -> 4 | P76: =IF(N76="Y",1,IF(M76>='Read me'!$B$14,3,IF(AND(O76>='Read me'!$B$12,M76<='Read me'!$B$13),1,2))) -> 2
A77: FL-PRE-07 | B77: Before the trip | C77: Change the name | D77: Typo | F77: My name is spelt wrong | G77: Checks airline rules for name corrections, hands over if needed | H77: StateCard, Handoff | I77: Name changes are airline decisions | K77: 2 | L77: 3 | M77: 4 | O77: =ROUND(K77*L77/M77,1) -> 1.5 | P77: =IF(N77="Y",1,IF(M77>='Read me'!$B$14,3,IF(AND(O77>='Read me'!$B$12,M77<='Read me'!$B$13),1,2))) -> 3
A78: FL-PRE-08 | B78: Before the trip | C78: Cancel the booking | D78: Plans changed | F78: Cancel my flight | G78: Shows what comes back and how, asks to confirm | H78: FareRules, ConfirmSheet, Receipt | I78: Refund amounts from fare rules only | K78: 3 | L78: 3 | M78: 4 | O78: =ROUND(K78*L78/M78,1) -> 2.3 | P78: =IF(N78="Y",1,IF(M78>='Read me'!$B$14,3,IF(AND(O78>='Read me'!$B$12,M78<='Read me'!$B$13),1,2))) -> 3
A79: FL-PRE-09 | B79: Before the trip | C79: Get reminded | D79: Leaving time | F79: (automatic) | G79: Tells them when to leave for the airport | H79: StickyNote, Toast | I79: Traffic data | K79: 4 | L79: 3 | M79: 1 | O79: =ROUND(K79*L79/M79,1) -> 12 | P79: =IF(N79="Y",1,IF(M79>='Read me'!$B$14,3,IF(AND(O79>='Read me'!$B$12,M79<='Read me'!$B$13),1,2))) -> 1
A80: FL-PRE-10 | B80: Before the trip | C80: Check the weather | D80: Packing | F80: What's the weather in Lisbon? | G80: Weather for the trip dates | H80: Answer | K80: 3 | L80: 1 | M80: 1 | O80: =ROUND(K80*L80/M80,1) -> 3 | P80: =IF(N80="Y",1,IF(M80>='Read me'!$B$14,3,IF(AND(O80>='Read me'!$B$12,M80<='Read me'!$B$13),1,2))) -> 2
A81: FL-PRE-11 | B81: Before the trip | C81: Currency and card abroad | D81: Spending | F81: Will my card work in Portugal? | G81: Explains foreign fees on this card | H81: BenefitRow, Answer | I81: Fees from the bank | K81: 3 | L81: 3 | M81: 2 | O81: =ROUND(K81*L81/M81,1) -> 4.5 | P81: =IF(N81="Y",1,IF(M81>='Read me'!$B$14,3,IF(AND(O81>='Read me'!$B$12,M81<='Read me'!$B$13),1,2))) -> 2
A82: FL-PRE-12 | B82: Before the trip | C82: Schedule change | D82: Airline moved it | E82: Time changed | F82: (Gratifi starts it) | G82: Explains the change and options: accept, change, refund | H82: StateCard, ChangeFlight | I82: Options from airline policy and local rules | J82: Refund rights for big schedule changes differ by market | K82: 3 | L82: 4 | M82: 4 | O82: =ROUND(K82*L82/M82,1) -> 3 | P82: =IF(N82="Y",1,IF(M82>='Read me'!$B$14,3,IF(AND(O82>='Read me'!$B$12,M82<='Read me'!$B$13),1,2))) -> 3
A83: FL-PRE-13 | B83: Before the trip | C83: Add a frequent flyer number | D83: Earn miles | F83: Add my miles number | G83: Adds it to the booking | H83: Toast | I83: Number checked by the airline | K83: 3 | L83: 2 | M83: 1 | O83: =ROUND(K83*L83/M83,1) -> 6 | P83: =IF(N83="Y",1,IF(M83>='Read me'!$B$14,3,IF(AND(O83>='Read me'!$B$12,M83<='Read me'!$B$13),1,2))) -> 1
A84: FL-PRE-14 | B84: Before the trip | C84: Travelling during a religious period | D84: Ramadan | F84: Are there meals on my flight during Ramadan? | G84: Explains the airline's service and airport opening hours | H84: Answer | I84: From airline and airport | J84: Relevant in AE, MY and IN; dates move each year | K84: 1 | L84: 2 | M84: 2 | O84: =ROUND(K84*L84/M84,1) -> 1 | P84: =IF(N84="Y",1,IF(M84>='Read me'!$B$14,3,IF(AND(O84>='Read me'!$B$12,M84<='Read me'!$B$13),1,2))) -> 2
A85: FL-DAY-01 | B85: Day of travel | C85: Show boarding pass | D85: At the airport | F85: Boarding pass | G85: Shows it, bright and offline | H85: BoardingPass | I85: Available offline | K85: 5 | L85: 4 | M85: 1 | N85: Y | O85: =ROUND(K85*L85/M85,1) -> 20 | P85: =IF(N85="Y",1,IF(M85>='Read me'!$B$14,3,IF(AND(O85>='Read me'!$B$12,M85<='Read me'!$B$13),1,2))) -> 1
A86: FL-DAY-02 | B86: Day of travel | C86: Track the flight | D86: Live | F86: Is my flight on time? | G86: Live status, gate, times | H86: FlightTracker, Status | I86: Status from the airline feed | K86: 5 | L86: 4 | M86: 2 | N86: Y | O86: =ROUND(K86*L86/M86,1) -> 10 | P86: =IF(N86="Y",1,IF(M86>='Read me'!$B$14,3,IF(AND(O86>='Read me'!$B$12,M86<='Read me'!$B$13),1,2))) -> 1
A87: FL-DAY-03 | B87: Day of travel | C87: Gate change | D87: Live | E87: Gate moved | F87: (Gratifi starts it) | G87: Push and card with the new gate and walk time | H87: FlightTracker, Toast | K87: 3 | L87: 3 | M87: 2 | O87: =ROUND(K87*L87/M87,1) -> 4.5 | P87: =IF(N87="Y",1,IF(M87>='Read me'!$B$14,3,IF(AND(O87>='Read me'!$B$12,M87<='Read me'!$B$13),1,2))) -> 2
A88: FL-DAY-04 | B88: Day of travel | C88: Find the lounge | D88: At the airport | F88: Where's the lounge? | G88: Lounge pass with directions | H88: LoungePass | K88: 3 | L88: 3 | M88: 1 | O88: =ROUND(K88*L88/M88,1) -> 9 | P88: =IF(N88="Y",1,IF(M88>='Read me'!$B$14,3,IF(AND(O88>='Read me'!$B$12,M88<='Read me'!$B$13),1,2))) -> 1
A89: FL-DAY-05 | B89: Day of travel | C89: Pick up someone | D89: Arrivals | F89: When does Sam land? | G89: Tracks a shared flight | H89: FlightTracker | I89: Only flights shared with them | K89: 2 | L89: 2 | M89: 2 | O89: =ROUND(K89*L89/M89,1) -> 2 | P89: =IF(N89="Y",1,IF(M89>='Read me'!$B$14,3,IF(AND(O89>='Read me'!$B$12,M89<='Read me'!$B$13),1,2))) -> 2
A90: FL-DAY-06 | B90: Day of travel | C90: Missed the flight | D90: Late | E90: No-show | F90: I've missed my flight | G90: Checks rules for no-shows and the next flights | H90: StateCard, FlightCard, Handoff | I90: No-show rules from fare | K90: 1 | L90: 3 | M90: 4 | O90: =ROUND(K90*L90/M90,1) -> 0.8 | P90: =IF(N90="Y",1,IF(M90>='Read me'!$B$14,3,IF(AND(O90>='Read me'!$B$12,M90<='Read me'!$B$13),1,2))) -> 3
A91: FL-DAY-07 | B91: Day of travel | C91: Denied boarding | D91: Overbooked | E91: Bumped | F91: They've given my seat away | G91: Explains rights and next options | H91: Disruption, Handoff | I91: Compensation named by rule | J91: UK261 and EU261 set amounts; DGCA (IN) and MAVCOM (MY) have their own rules; SG and AE follow airline policy | K91: 1 | L91: 3 | M91: 5 | O91: =ROUND(K91*L91/M91,1) -> 0.6 | P91: =IF(N91="Y",1,IF(M91>='Read me'!$B$14,3,IF(AND(O91>='Read me'!$B$12,M91<='Read me'!$B$13),1,2))) -> 3
A92: FL-DAY-08 | B92: Day of travel | C92: Lost bag | D92: On arrival | E92: Bag missing | F92: My bag didn't arrive | G92: Starts the report, tracks it | H92: StateCard, Handoff | I92: Report goes to the airline | K92: 1 | L92: 3 | M92: 4 | O92: =ROUND(K92*L92/M92,1) -> 0.8 | P92: =IF(N92="Y",1,IF(M92>='Read me'!$B$14,3,IF(AND(O92>='Read me'!$B$12,M92<='Read me'!$B$13),1,2))) -> 3
A93: FL-DAY-09 | B93: Day of travel | C93: Security wait times | D93: At the airport | F93: How long is security? | G93: Shows the airport's published wait if available | H93: Answer | I93: Only published data | K93: 2 | L93: 2 | M93: 1 | O93: =ROUND(K93*L93/M93,1) -> 4 | P93: =IF(N93="Y",1,IF(M93>='Read me'!$B$14,3,IF(AND(O93>='Read me'!$B$12,M93<='Read me'!$B$13),1,2))) -> 2
A94: FL-DAY-10 | B94: Day of travel | C94: Arrival: get into town | D94: Landed | F94: How do I get to the hotel? | G94: Offers ride, train, and time for each | H94: RideOption, Answer | K94: 3 | L94: 3 | M94: 1 | O94: =ROUND(K94*L94/M94,1) -> 9 | P94: =IF(N94="Y",1,IF(M94>='Read me'!$B$14,3,IF(AND(O94>='Read me'!$B$12,M94<='Read me'!$B$13),1,2))) -> 1
A95: FL-DIS-01 | B95: Disruption | C95: Flight delayed | D95: Short delay | F95: (Gratifi starts it) | G95: Heads-up with new times and what it means | H95: FlightTracker, Status | K95: 4 | L95: 3 | M95: 2 | O95: =ROUND(K95*L95/M95,1) -> 6 | P95: =IF(N95="Y",1,IF(M95>='Read me'!$B$14,3,IF(AND(O95>='Read me'!$B$12,M95<='Read me'!$B$13),1,2))) -> 1
A96: FL-DIS-02 | B96: Disruption | C96: Flight delayed | D96: Long delay | E96: Over 3 hours | F96: (Gratifi starts it) | G96: Explains rights, food vouchers, rebooking | H96: Disruption, Handoff | I96: Rights named by rule, amounts by legal team | J96: Amounts: UK £220 to £520, EU €250 to €600 by distance; others per local rule or airline | K96: 2 | L96: 4 | M96: 5 | O96: =ROUND(K96*L96/M96,1) -> 1.6 | P96: =IF(N96="Y",1,IF(M96>='Read me'!$B$14,3,IF(AND(O96>='Read me'!$B$12,M96<='Read me'!$B$13),1,2))) -> 3
A97: FL-DIS-03 | B97: Disruption | C97: Flight cancelled | D97: Before travel | F97: (Gratifi starts it) | G97: Options already worked out: next flight, other route, refund | H97: Disruption, ConfirmSheet, Receipt | I97: Refund always offered | K97: 2 | L97: 5 | M97: 5 | O97: =ROUND(K97*L97/M97,1) -> 2 | P97: =IF(N97="Y",1,IF(M97>='Read me'!$B$14,3,IF(AND(O97>='Read me'!$B$12,M97<='Read me'!$B$13),1,2))) -> 3
A98: FL-DIS-04 | B98: Disruption | C98: Flight cancelled | D98: At the airport | E98: Queue | F98: (Gratifi starts it) | G98: Rebooks before the queue, holds seats together | H98: Disruption, Receipt | I98: Seat hold time from the airline | K98: 2 | L98: 5 | M98: 5 | O98: =ROUND(K98*L98/M98,1) -> 2 | P98: =IF(N98="Y",1,IF(M98>='Read me'!$B$14,3,IF(AND(O98>='Read me'!$B$12,M98<='Read me'!$B$13),1,2))) -> 3
A99: FL-DIS-05 | B99: Disruption | C99: Missed connection | D99: Same ticket | E99: Late first flight | F99: (Gratifi starts it) | G99: Rebooks the onward flight | H99: Disruption, Itinerary | I99: Protected only on one ticket | K99: 1 | L99: 4 | M99: 5 | O99: =ROUND(K99*L99/M99,1) -> 0.8 | P99: =IF(N99="Y",1,IF(M99>='Read me'!$B$14,3,IF(AND(O99>='Read me'!$B$12,M99<='Read me'!$B$13),1,2))) -> 3
A100: FL-DIS-06 | B100: Disruption | C100: Missed connection | D100: Separate tickets | E100: Not protected | F100: (Gratifi starts it) | G100: Explains it is not protected, finds the next options | H100: StateCard, FlightCard, Handoff | K100: 1 | L100: 3 | M100: 5 | O100: =ROUND(K100*L100/M100,1) -> 0.6 | P100: =IF(N100="Y",1,IF(M100>='Read me'!$B$14,3,IF(AND(O100>='Read me'!$B$12,M100<='Read me'!$B$13),1,2))) -> 3
...

Sheet Markets
A1: Market | B1: Currency | C1: Number and date format | D1: How a payment is confirmed | E1: Automatic card payment is called | F1: Tax on fares | G1: Flight disruption rule | H1: Amounts set in law? | I1: Week starts | J1: Languages | K1: To confirm with the bank
A2: United Kingdom | B2: GBP £ | C2: en-GB · 1,234.50 · Fri 16 Oct | D2: Face ID in the bank app | E2: Direct Debit | F2: VAT; Air Passenger Duty in fares | G2: UK261 | H2: Yes: £220, £350, £520 by distance | I2: Monday | J2: English | K2: Point value; claims process
A3: Eurozone | B3: EUR € | C3: en-IE for English; local languages later | D3: Face ID in the bank app (strong customer authentication) | E3: direct debit | F3: VAT; local ticket taxes | G3: EU261 | H3: Yes: €250, €400, €600 by distance | I3: Monday | J3: English first; German, French, Spanish, Italian, Dutch to add | K3: Point value; which languages first
A4: India | B4: INR ₹ | C4: en-IN · lakh grouping (1,00,000) · Fri 16 Oct | D4: One-time code sent by SMS | E4: auto-debit | F4: GST; GST invoice needs company GSTIN | G4: DGCA passenger charter | H4: Set by DGCA; legal team to confirm current amounts | I4: Sunday | J4: English first; Hindi next | K4: Point value; OTP limits; EMI terms
A5: UAE | B5: AED | C5: en-AE and ar-AE (right to left) | D5: Face ID in the bank app | E5: direct debit | F5: VAT | G5: Airline policy (legal team to confirm any GCAA rule) | H5: Legal team to confirm | I5: Monday | J5: English and Arabic (Arabic copy needs native sign-off) | K5: Point value; Arabic copy
A6: Singapore | B6: SGD S$ | C6: en-SG · 1,234.50 | D6: Face ID in the bank app | E6: GIRO | F6: GST | G6: Airline policy; no statutory scheme | H6: No | I6: Sunday | J6: English | K6: Point value
A7: Malaysia | B7: MYR RM | C7: en-MY · 1,234.50 | D7: Approval in the bank's app | E7: auto-debit | F7: SST | G7: MAVCOM consumer code | H7: Legal team to confirm | I7: Monday | J7: English first; Malay next | K7: Point value; app approval flow
A9: These settings live in the kit as data (Markets card). A new market is one more row here and one more entry in the kit; no redesign.

Sheet Grammar
A1: The grammar
A3: Stage | B3: Means | C3: Constraints | D3: Exceptions
A4: Inspire | B4: Before they know where | C4: Dates fixed | D4: No results
A5: Search | B5: They know roughly what and when | C5: Flexible dates | D5: Supplier down
A6: Choose | B6: Comparing options and fares | C6: Budget in cash | D6: Price rose
A7: Pay | B7: Money or points move | C7: Budget in points | D7: Sold out
A8: Extras | B8: Seats, bags, lounge, hotel, rides | C8: Direct only | D8: Payment declined
A9: Before the trip | B9: Booked, not yet travelling | C9: Time of day | D9: Authentication failed
A10: Day of travel | B10: At or on the way to the airport | C10: Airline preference | D10: Not enough points
A11: Disruption | B11: Something went wrong | C11: Bag included | D11: Ticketing pending
A12: After the trip | B12: Home again | C12: Travelling with children | D12: Schedule change
A13: Points and card | B13: The bank side of travel | C13: Group of 5 or more | D13: Delay over 3 hours
C14: Premium cabin | D14: Cancellation
C15: Business trip | D15: Missed connection
C16: Accessibility needs | D16: Denied boarding
C17: Pet | D17: Diversion
C18: Separate tickets | D18: Downgrade
D19: Lost bag
A22: Every new row should combine one stage, one job, at most one constraint and at most one exception. The full space is several hundred rows; this sheet holds the ones worth building first plus the high-risk ones that must be designed now.
